Workbook
Name \0: #REF!
Name \0: #REF!
Name \0: #REF!
Name \0: #REF!
Name \0: #REF!
Name \00: #REF!
Name \00: #REF!
Name \00: #REF!
Name \00: #REF!
Name \00: #REF!
Name \44333: #REF!
Name \44333: #REF!
Name \44333: #REF!
Name \44333: #REF!
Name \44333: #REF!
Name \a: #REF!
Name \a: #REF!
Name \a: #REF!
Name \a: #REF!
Name \a: #REF!
Name \add9a: #REF!
Name \add9a: #REF!
Name \add9a: #REF!
Name \add9a: #REF!
Name \add9a: #REF!
Name \b: #REF!
Name \b: #REF!
Name \b: #REF!
Name \b: #REF!
Name \b: #REF!
Name \B1: #REF!
Name \B1: #REF!
Name \B1: #REF!
Name \B1: #REF!
Name \B10: #REF!
Name \B10: #REF!
Name \B10: #REF!
Name \B10: #REF!
Name \B11: #REF!
Name \B11: #REF!
Name \B11: #REF!
Name \B11: #REF!
Name \B12: #REF!
Name \B12: #REF!
Name \B12: #REF!
Name \B13: #REF!
Name \B13: #REF!
Name \B13: #REF!
Name \B14: #REF!
Name \B14: #REF!
Name \B14: #REF!
Name \B2: #REF!
Name \B2: #REF!
Name \B2: #REF!
Name \B3: #REF!
Name \B3: #REF!
Name \B3: #REF!
Name \B4: #REF!
Name \B4: #REF!
Name \B4: #REF!

Sheet Resumen Ejecutivo
C2: PROYECTO: | D2: CONSTRUCCIÓN DE 50 PILAS DE CONCRETO ARMADO PARA PMI'S EN EL ESTADO DE TAMAULIPAS (TAMPICO Y MANTE)
C3: CLIENTE: | D3: SYM KABAT | K3: Fecha
C4: RESUMEN EJECUTIVO | K4: =TODAY() -> 46076
B5: 1. INFORMACIÓN DE PROYECTO
B7: Fecha Presentación | C7: Fecha Adjudicación | F7: Inicio de Obra | K7: Público/ Privado
B8: 45809 | C8: 45817 | F8: 07.07.2025 | J8: Tipo Licitación: | K8: PRIVADO
B10: Contrato S/ IVA | C10: Contrato C/ IVA | F10: Anticipo s/ IVA | G10: Anticipo c/ IVA | J10: Personal Estratégico: | K10: N.A.
B11: =Producción!$I$9 -> 7818391.5 | C11: =B11*1.16 -> 9069334.1 | F11: ='Control Certificación'!$H$13 -> 929236.37 | G11: =F11*1.16 -> 1077914.2 | J11: Contacto:
B13: Fianza Anticipo | D13: 45689 | J13: Teléfono:
B14: Monto Afianzado | C14: Costo Poliza | D14: Vigencia | F14: Fin Contractual | G14: Fin Previsto
B17: Fianza Cumplimiento | D17: 45799 | F17: Fianza Vicios Ocultos
B18: Monto Afianzado | C18: Costo Fianza | D18: Vigencia | F18: Importe | G18: Vigencia
B21: Seguro CAR (Todo Riesgo de Construcción) | F21: Seguro Responsabilidad Civil
B22: Monto Afianzado | C22: Costo Fianza | D22: Vigencia | F22: Importe | G22: Vigencia
B25: 2. SITUACIÓN ACTUAL DE OBRA
B27: Anticipo | J27: =CONCATENATE("Actualizado hasta ",VLOOKUP(MAX(Certificacion[FECHA FACTURA]),Certificacion[[FECHA FACTURA]:[PERIODO Imp.]],2)) -> Actualizado hasta DIC 2025 Q1
B28: Anticipo S/Iva | C28: Amort. S/Iva acum. | D28: Amort. S/Iva pendiente | F28: Anticipo Liquido | G28: Amort. Líquida acum. | I28: Amort. Líquida pendiente
B29: ='Control Certificación'!$K$6 -> 929236.37 | C29: ='Control Certificación'!$O$6 -> 0 | D29: =B29-C29 -> 929236.37 | F29: ='Control Certificación'!$K$6*1.16 -> 1077914.2 | G29: ='Control Certificación'!$O$6*1.16 -> 0 | I29: =F29-G29 -> 1077914.2
B31: Certificación | H31: =IFERROR(CONCATENATE("Actualizado hasta ",VLOOKUP(MAX(Certificacion[FECHA FACTURA]),Certificacion[[FECHA FACTURA]:[PERIODO Imp.]],2)),"$") -> Actualizado hasta DIC 2025 Q1
B32: Certificación S/ Iva | C32: Adeudo s/ Iva | F32: Certificación Líquida | G32: Adeudo Líquido de cobro | J32: Días Vencimiento fra. más atrasada
B33: =SUMIF(Certificacion[APLICA],"ESTIMACION",Certificacion[IMPORTE]) -> 5685234.1 | C33: =SUMIFS(Certificacion[IMPORTE],Certificacion[APLICA],"ESTIMACION",Certificacion[FECHA DE PAGO],"") -> 5685234.1 | F33: =SUMIF(Certificacion[APLICA],"ESTIMACION",Certificacion[LIQUIDO A PAGAR]) -> 6594871.6 | G33: =SUMIFS(Certificacion[LIQUIDO A PAGAR],Certificacion[APLICA],"ESTIMACION",Certificacion[FECHA DE PAGO],"") -> 6594871.6 | J33: ='Control Certificación'!$R$8 -> 192 días
B35: Retenciones por fondo de garantía | H35: =IFERROR(CONCATENATE("Actualizado hasta ",VLOOKUP(MAX(Certificacion[FECHA FACTURA]),Certificacion[[FECHA FACTURA]:[PERIODO Imp.]],2)),"$") -> Actualizado hasta DIC 2025 Q1
B36: Retención acum. S/ Iva | C36: Pagos acum. S/ Iva | F36: Ret. Acum. Líquida | G36: Pago Acum. Líquido
B37: =SUMIF(Certificacion[APLICA],"RETENCION 5%",Certificacion[OTROS (FONDO GARANTÍA)]) -> 0 | C37: ='Resumen Ejecutivo'!B37-(SUMIFS(Certificacion[OTROS (FONDO GARANTÍA)],Certificacion[APLICA],"RETENCION 5%",Certificacion[FECHA DE PAGO],"")) -> 0 | F37: =SUMIF(Certificacion[APLICA],"RETENCION 5%",'Control Certificación'!$Q$15:$Q$95)*-1 -> 0 | G37: =F37-(SUMIFS('Control Certificación'!$Q$15:$Q$95,Certificacion[APLICA],"RETENCION 5%",Certificacion[FECHA DE PAGO],""))*-1 -> 0
B39: Producción | D39: =CONCATENATE("Actualizado hasta ",(HLOOKUP(MAX(Producción!#REF!),Producción!BN6:DI8,2))) -> #REF!
B40: Producción acumulada | C40: Producción Estimada | D40: Obra ejecutada no estimada
B41: =Producción!BL9 -> 5676539.1 | C41: =B33 -> 5685234.1 | D41: =B41-C41 -> -8694.988
B43: 3. ANÁLISIS TÉCNICO-ECONÓMICO DE LA OBRA
B45: Partidas principales por E7 | F45: Estudio | G45: Contrato | H45: Acumulado
F46: =F47+F51+F55 -> 0 | G46: =G47+G51+G55 -> 7740567.5 | H46: =H47+H51+H55 -> 5676539.1
B47: =Producción!E10 -> PILAS DE CIMENTACIÓN | F47: =F48-F49 -> 0 | G47: =G48-G49 -> 6371392.1 | H47: =H48-H49 -> 4698269
B48: Producción | G48: =Producción!I10 -> 6371392.1 | H48: =Producción!BL10 -> 4698269
B49: Costo Directo
B51: =Producción!E143 -> MECÁNICAS DE SUELOS Y TOPOGRAFÍAS | F51: =F52-F53 -> 0 | G51: =G52-G53 -> 991424.59 | H51: =H52-H53 -> 616735.43
B52: Producción | G52: =Producción!I143 -> 991424.59 | H52: =Producción!BL143 -> 616735.43
B53: Costo Directo
B55: =Producción!E254 -> SHELTER JIQUILPAN | F55: =F56-F57 -> 0 | G55: =G56-G57 -> 377750.82 | H55: =H56-H57 -> 361534.71
B56: Producción | G56: =Producción!I254 -> 377750.82 | H56: =Producción!BL254 -> 361534.71
B57: Costo Directo
B60: Resultado por familias | F60: Estudio | G60: ACTUAL Contrato | H60: Acumulado | J60: Pendiente | K60: Desvío
K61: =IFERROR(H61/G61,"")
B62: Costo Directo | F62: =SUBTOTAL(9,F63:F73) -> 7468590.2 | G62: =SUBTOTAL(9,G63:G73) -> 302381.54 | H62: =SUBTOTAL(9,H63:H73) -> 268646.04 | J62: =SUBTOTAL(9,J63:J73) -> 33735.5
B63: =IF(G63=0,"",'Costo Directo'!$E$14) -> SUBCONTRATOS | C63: ='Costo Directo'!$J$14 -> 114219.6 | D63: ='Costo Directo'!$J$14 -> 114219.6 | F63: 2787737.6 | G63: ='Costo Directo'!$J$14 -> 114219.6 | H63: ='Costo Directo'!$BK$14 -> 118847.27 | J63: =G63-H63 -> -4627.6729 | K63: =IFERROR(H63/G63,"") -> 1.0405156 | M63: =IFERROR(K63/Producción!#REF!,"")
B64: =IF(G64=0,"",'Costo Directo'!$E$26) -> MAQUINARIA | C64: ='Costo Directo'!$J$26 -> 4513.5 | D64: ='Costo Directo'!$J$26 -> 4513.5 | F64: 107443 | G64: ='Costo Directo'!$J$26 -> 4513.5 | H64: ='Costo Directo'!$BK$26 -> 7425 | J64: =G64-H64 -> -2911.5 | K64: =IFERROR(H64/G64,"") -> 1.6450648 | M64: =IFERROR(K64/Producción!#REF!,"")
B65: =IF(G65=0,"",'Costo Directo'!$E$68) -> MANO DE OBRA | C65: ='Costo Directo'!$J$68 -> 29063.929 | D65: ='Costo Directo'!$J$68 -> 29063.929 | F65: 682595.86 | G65: ='Costo Directo'!$J$68 -> 29063.929 | H65: ='Costo Directo'!$BK$68 -> 36205.812 | J65: =G65-H65 -> -7141.8834 | K65: =IFERROR(H65/G65,"") -> 1.2457301 | M65: =IFERROR(K65/Producción!#REF!,"")
B66: =IF(G66=0,"",'Costo Directo'!$E$121) -> MATERIALES | C66: ='Costo Directo'!$J$121 -> 124378.58 | D66: ='Costo Directo'!$J$121 -> 124378.58 | F66: 3149143.4 | G66: ='Costo Directo'!$J$121 -> 124378.58 | H66: ='Costo Directo'!$BK$174 -> 85320 | J66: =G66-H66 -> 39058.578 | K66: =IFERROR(H66/G66,"") -> 0.68597021 | M66: =IFERROR(K66/Producción!#REF!,"")
B67: =IF(G67=0,"",'Costo Directo'!$E$174) -> ACARREOS | C67: ='Costo Directo'!$J$174 -> 13090 | D67: ='Costo Directo'!$J$174 -> 13090 | F67: 318920 | G67: ='Costo Directo'!$J$174 -> 13090 | H67: ='Costo Directo'!$BK$187 -> 0 | J67: =G67-H67 -> 13090 | K67: =IFERROR(H67/G67,"") -> 0 | M67: =IFERROR(K67/Producción!#REF!,"")
B68: =IF(G68=0,"",'Costo Directo'!$E$187) | C68: ='Costo Directo'!$J$187 -> 0 | D68: ='Costo Directo'!$J$187 -> 0 | G68: ='Costo Directo'!$J$187 -> 0 | H68: ='Costo Directo'!$BK$210 -> 0 | J68: =G68-H68 -> 0 | K68: =IFERROR(H68/G68,"") | M68: =IFERROR(K68/Producción!#REF!,"")
B69: =IF(G69=0,"",'Costo Directo'!$E$210) | C69: ='Costo Directo'!$J$210 -> 0 | D69: ='Costo Directo'!$J$210 -> 0 | G69: ='Costo Directo'!$J$210 -> 0 | H69: ='Costo Directo'!$BK$227 -> 0 | J69: =G69-H69 -> 0 | K69: =IFERROR(H69/G69,"") | M69: =IFERROR(K69/Producción!#REF!,"")
B70: =IF(G70=0,"",'Costo Directo'!$E$227) | C70: ='Costo Directo'!$J$227 -> 0 | D70: ='Costo Directo'!$J$227 -> 0 | G70: ='Costo Directo'!$J$227 -> 0 | H70: ='Costo Directo'!$BK$235 -> 10423.979 | J70: =G70-H70 -> -10423.979 | K70: =IFERROR(H70/G70,"") | M70: =IFERROR(K70/Producción!#REF!,"")
B71: =IF(G71=0,"",'Costo Directo'!$E$235) -> HERRAMIENTA MENOR Y EPP | C71: ='Costo Directo'!$J$235 -> 17115.936 | D71: ='Costo Directo'!$J$235 -> 17115.936 | F71: 422750.39 | G71: ='Costo Directo'!$J$235 -> 17115.936 | H71: ='Costo Directo'!$BK$235 -> 10423.979 | J71: =G71-H71 -> 6691.957 | K71: =IFERROR(H71/G71,"") -> 0.60902186 | M71: =IFERROR(K71/Producción!#REF!,"")
B72: =IF(G72=0,"",'Costo Directo'!$E$241) | C72: ='Costo Directo'!$J$241 -> 0 | D72: ='Costo Directo'!$J$241 -> 0 | G72: ='Costo Directo'!$J$241 -> 0 | H72: ='Costo Directo'!$BK$241 -> 0 | J72: =G72-H72 -> 0 | K72: =IFERROR(H72/G72,"") | M72: =IFERROR(K72/Producción!#REF!,"")
B74: Costo Indirecto | F74: =SUBTOTAL(9,F75:F83) -> 2953481.1 | G74: =SUBTOTAL(9,G75:G83) -> 779074.19 | H74: =SUBTOTAL(9,H75:H83) -> 1774928.2 | J74: =SUBTOTAL(9,J75:J83) -> -995854.03
B75: =IF(G75=0,"",'Indirect Costs'!$D$11) -> PERSONAL | C75: ='Indirect Costs'!$I$11 -> 231000 | D75: ='Indirect Costs'!$I$11 -> 231000 | F75: 945600 | G75: ='Indirect Costs'!$I$11 -> 231000 | H75: ='Indirect Costs'!$BI$11 -> 1005958.2 | J75: =G75-H75 -> -774958.24 | K75: =IFERROR(H75/G75,"") -> 4.3547976 | M75: =IFERROR(K75/Producción!#REF!,"")
B76: =IF(G76=0,"",'Indirect Costs'!$D$52) -> EQUIPAMIENTO PARA PERSONAL DE OBRA | C76: ='Indirect Costs'!$I$52 -> 185750 | D76: ='Indirect Costs'!$I$52 -> 185750 | F76: 414000 | G76: ='Indirect Costs'!$I$52 -> 185750 | H76: ='Indirect Costs'!$BI$52 -> 396620.49 | J76: =G76-H76 -> -210870.49 | K76: =IFERROR(H76/G76,"") -> 2.1352382 | M76: =IFERROR(K76/Producción!#REF!,"")
B77: =IF(G77=0,"",'Indirect Costs'!$D$63) -> TRASLADOS Y HOSPEDAJES | C77: ='Indirect Costs'!$I$63 -> 40000 | D77: ='Indirect Costs'!$I$63 -> 40000 | F77: 120000 | G77: ='Indirect Costs'!$I$63 -> 40000 | H77: ='Indirect Costs'!$BI$63 -> 171311.52 | J77: =G77-H77 -> -131311.52 | K77: =IFERROR(H77/G77,"") -> 4.282788 | M77: =IFERROR(K77/Producción!#REF!,"")
B78: =IF(G78=0,"",'Indirect Costs'!$D$71) -> GASTOS DE OFICINA CENTRAL | C78: ='Indirect Costs'!$I$71 -> 18500 | D78: ='Indirect Costs'!$I$71 -> 18500 | F78: 60000 | G78: ='Indirect Costs'!$I$71 -> 18500 | H78: ='Indirect Costs'!$BI$71 -> 58081.833 | J78: =G78-H78 -> -39581.833 | K78: =IFERROR(H78/G78,"") -> 3.1395585 | M78: =IFERROR(K78/Producción!#REF!,"")
B79: =IF(G79=0,"",'Indirect Costs'!$D$82) | C79: ='Indirect Costs'!$I$82 -> 0 | D79: ='Indirect Costs'!$I$82 -> 0 | F79: 0 | G79: ='Indirect Costs'!$I$82 -> 0 | H79: ='Indirect Costs'!$BI$82 -> 0 | J79: =G79-H79 -> 0 | K79: =IFERROR(H79/G79,"") | M79: =IFERROR(K79/Producción!#REF!,"")
B80: =IF(G80=0,"",'Indirect Costs'!$D$91) -> OTROS COSTOS OPERATIVOS | C80: ='Indirect Costs'!$I$91 -> 99500 | D80: ='Indirect Costs'!$I$91 -> 99500 | F80: 462000 | G80: ='Indirect Costs'!$I$91 -> 99500 | H80: ='Indirect Costs'!$BI$91 -> 19297.503 | J80: =G80-H80 -> 80202.497 | K80: =IFERROR(H80/G80,"") -> 0.19394475 | M80: =IFERROR(K80/Producción!#REF!,"")
B81: =IF(G81=0,"",'Indirect Costs'!$D$116) -> FIANZAS, SEGUROS Y OTROS PREVIOS | C81: ='Indirect Costs'!$I$116 -> 129324.19 | D81: ='Indirect Costs'!$I$116 -> 129324.19 | F81: 491246 | G81: ='Indirect Costs'!$I$116 -> 129324.19 | H81: ='Indirect Costs'!$BI$116 -> 36612 | J81: =G81-H81 -> 92712.192 | K81: =IFERROR(H81/G81,"") -> 0.28310248 | M81: =IFERROR(K81/Producción!#REF!,"")
B82: =IF(G82=0,"",'Indirect Costs'!$D$132) -> PROYECTOS, GESTIONES E IMPUESTOS | C82: ='Indirect Costs'!$I$132 -> 75000 | D82: ='Indirect Costs'!$I$132 -> 75000 | F82: 460635.14 | G82: ='Indirect Costs'!$I$132 -> 75000 | H82: ='Indirect Costs'!$BI$132 -> 87046.64 | J82: =G82-H82 -> -12046.64 | K82: =IFERROR(H82/G82,"") -> 1.1606219 | M82: =IFERROR(K82/Producción!#REF!,"")
B84: Producción | F84: =SUBTOTAL(9,F85:F88) -> 13977121 | G84: =SUBTOTAL(9,G85:G88) -> 7740567.5 | H84: =SUBTOTAL(9,H85:H88) -> 5676539.1 | J84: =SUBTOTAL(9,J85:J88) -> 2064028.4
B85: =B47 -> PILAS DE CIMENTACIÓN | F85: 12586231 | G85: =G48 -> 6371392.1 | H85: =H48 -> 4698269 | J85: =G85-H85 -> 1673123.1 | K85: =IFERROR(H85/G85,"") -> 0.7374007 | M85: =IFERROR(K85/Producción!#REF!,"")
B86: =B51 -> MECÁNICAS DE SUELOS Y TOPOGRAFÍAS | F86: 1390890.1 | G86: =G52 -> 991424.59 | H86: =H52 -> 616735.43 | J86: =G86-H86 -> 374689.16 | K86: =IFERROR(H86/G86,"") -> 0.62206993 | M86: =IFERROR(K86/Producción!#REF!,"")
B87: =B55 -> SHELTER JIQUILPAN | G87: =G56 -> 377750.82 | H87: =H56 -> 361534.71 | J87: =G87-H87 -> 16216.11 | K87: =IFERROR(H87/G87,"") -> 0.95707194 | M87: =IFERROR(K87/Producción!#REF!,"")
B90: 4. ANÁLISIS DE RIESGOS Y MEJORAS APLICABLES AL PROYECTO, Y SU EFECTO SOBRE EL RESULTADO
B92: Descripción de riesgos / mejoras | E92: Consecuencias económicas s/ iva
E93: Variación Producción | G93: Variación Costo | J93: Variación Resultado
E94: =SUM(E95:E101) -> 0 | G94: =SUM(G95:G101) -> 0
B103: 5. INVERSIÓN EN ACTIVOS DE DIMOVERE APLICADA A ESTE PROYECTO
B105: Listado de activos | E105: Consecuencias económicas s/ iva (Hasta fin previsto)
E106: Importe Previsto | G106: Costo imputado acumulado | J106: Costo pendiente | K106: Variación Resultado
E107: =SUM(E108:E119) -> 0 | G107: =SUM(G108:G119) -> 197778.88 | J107: =SUM(J108:J119) -> -197778.88 | K107: =IFERROR(G107/E107,"")
B108: AC1 Equipo de cómputo y oficina | E108: =SUMIF('Indirect Costs'!$A$11:$A$138,"AC1",'Indirect Costs'!$I$11:$I$138)+SUMIF('Costo Directo'!$B$14:$B$247,"AC1",'Costo Directo'!$J$14:$J$247) -> 0 | F108: =SUMIF('Indirect Costs'!$A$11:$A$138,"AC1",'Indirect Costs'!$I$11:$I$138)+SUMIF('Costo Directo'!$B$14:$B$247,"AC1",'Costo Directo'!$J$14:$J$247)-B108 -> #VALUE! | G108: =SUMIFS(Imput!$I$12:$I$3751,Imput!$C$12:$C$3751,"AC1") -> 0 | J108: =E108-G108 -> 0 | K108: =IFERROR(G108/E108,"%") -> %
B109: AC2 Maquinaria (Equipo Menor) | E109: =SUMIF('Indirect Costs'!$A$11:$A$138,"AC2",'Indirect Costs'!$I$11:$I$138)+SUMIF('Costo Directo'!$B$14:$B$247,"AC2",'Costo Directo'!$J$14:$J$247) -> 0 | F109: =SUMIF('Indirect Costs'!$A$11:$A$138,"AC2",'Indirect Costs'!$I$11:$I$138)+SUMIF('Costo Directo'!$B$14:$B$247,"AC2",'Costo Directo'!$J$14:$J$247)-B109 -> #VALUE! | G109: =SUMIFS(Imput!$I$12:$I$3751,Imput!$C$12:$C$3751,"AC2") -> 171278.88 | J109: =E109-G109 -> -171278.88 | K109: =IFERROR(G109/E109,"%") -> %
B110: AC3 Maquinaria (Equipo Mayor) | E110: =SUMIF('Indirect Costs'!$A$11:$A$138,"AC3",'Indirect Costs'!$I$11:$I$138)+SUMIF('Costo Directo'!$B$14:$B$247,"AC3",'Costo Directo'!$J$14:$J$247) -> 0 | F110: =SUMIF('Indirect Costs'!$A$11:$A$138,"AC3",'Indirect Costs'!$I$11:$I$138)+SUMIF('Costo Directo'!$B$14:$B$247,"AC3",'Costo Directo'!$J$14:$J$247)-B110 -> #VALUE! | G110: =SUMIFS(Imput!$I$12:$I$3751,Imput!$C$12:$C$3751,"AC3") -> 26500 | J110: =E110-G110 -> -26500 | K110: =IFERROR(G110/E110,"%") -> %
B111: AC4 Mobiliario campamentos | E111: =SUMIF('Indirect Costs'!$A$11:$A$138,"AC4",'Indirect Costs'!$I$11:$I$138)+SUMIF('Costo Directo'!$B$14:$B$247,"AC4",'Costo Directo'!$J$14:$J$247) -> 0 | F111: =SUMIF('Indirect Costs'!$A$11:$A$138,"AC4",'Indirect Costs'!$I$11:$I$138)+SUMIF('Costo Directo'!$B$14:$B$247,"AC4",'Costo Directo'!$J$14:$J$247)-B111 -> #VALUE! | G111: =SUMIFS(Imput!$I$12:$I$3751,Imput!$C$12:$C$3751,"AC4") -> 0 | J111: =E111-G111 -> 0 | K111: =IFERROR(G111/E111,"%") -> %
B112: AC5 Mobiliario y equipamiento obra | E112: =SUMIF('Indirect Costs'!$A$11:$A$138,"AC5",'Indirect Costs'!$I$11:$I$138)+SUMIF('Costo Directo'!$B$14:$B$247,"AC5",'Costo Directo'!$J$14:$J$247) -> 0 | F112: =SUMIF('Indirect Costs'!$A$11:$A$138,"AC5",'Indirect Costs'!$I$11:$I$138)+SUMIF('Costo Directo'!$B$14:$B$247,"AC5",'Costo Directo'!$J$14:$J$247)-B112 -> #VALUE! | G112: =SUMIFS(Imput!$I$12:$I$3751,Imput!$C$12:$C$3751,"AC5") -> 0 | J112: =E112-G112 -> 0 | K112: =IFERROR(G112/E112,"%") -> %
B113: AC6 Vehículos utilitarios | E113: =SUMIF('Indirect Costs'!$A$11:$A$138,"AC6",'Indirect Costs'!$I$11:$I$138)+SUMIF('Costo Directo'!$B$14:$B$247,"AC6",'Costo Directo'!$J$14:$J$247) -> 0 | F113: =SUMIF('Indirect Costs'!$A$11:$A$138,"AC6",'Indirect Costs'!$I$11:$I$138)+SUMIF('Costo Directo'!$B$14:$B$247,"AC6",'Costo Directo'!$J$14:$J$247)-B113 -> #VALUE! | G113: =SUMIFS(Imput!$I$12:$I$3751,Imput!$C$12:$C$3751,"AC6") -> 0 | J113: =E113-G113 -> 0 | K113: =IFERROR(G113/E113,"%") -> %

Sheet Imput
C3: CONTROL DE COSTOS | N3: Tipo de Cambio (MXN / USD): | P3: 20
C4: =CONCATENATE('Resumen Ejecutivo'!C2," ",'Resumen Ejecutivo'!D2) -> PROYECTO: CONSTRUCCIÓN DE 50 PILAS DE CONCRETO ARMADO PARA PMI'S EN EL ESTADO DE TAMAULIPAS (TAMPICO Y MANTE)
C5: =CONCATENATE('Resumen Ejecutivo'!C3," ",'Resumen Ejecutivo'!D3) -> CLIENTE: SYM KABAT | K5: Total C/COD IMPUT | L5: =Resultado!E13 -> 3533925.1 | N5: FECHA: | P5: =TODAY() -> 46076
B8: PERIODO Imp. | C8: C. Imp. | D8: Datos de Empresa | F8: Datos de Compra | P8: Datos Facturación | U8: CHEK LIST | V8: CUENTA CONTABLE | Y8: OBSERVACIONES | Z8: OBSERVACION ADICIONAL | AB8: Acreedor
D9: R.F.C. | E9: RAZON SOCIAL | F9: Descripcion concepto | G9: Cantidad | H9: Precio Unitario | I9: Sub total | J9: IVA | K9: Retención / Descuento | L9: Importe Neto | M9: Importe Neto por Factura | N9: Doc | O9: Tipo de Cambio USD | P9: Folio (UUID) o (SUA) | Q9: Folio | R9: Fecha | S9: Tipo de Pago | T9: Fecha de Pago (transferencias) | W9: SUBCUENTA
I10: =SUBTOTAL(9,Imput[Sub total]) -> 6463521.1 | J10: =SUBTOTAL(9,Imput[IVA]) -> 611525.37 | K10: =SUBTOTAL(9,Imput[Retención / IEPS / Descuento]) -> 17700.802 | L10: =SUBTOTAL(9,Imput[Importe Neto]) -> 7057345.7 | M10: =SUBTOTAL(9,Imput[Columna8]) -> 7057345.7
B11: PERIODO Imp. | C11: C. Imp. | D11: RFC | E11: RAZON SOCIAL | F11: Descripcion concepto | G11: Cantidad | H11: Precio Unitario | I11: Sub total | J11: IVA | K11: Retención / IEPS / Descuento | L11: Importe Neto | M11: Columna8 | N11: Documento | O11: Tipo de Cambio USD | P11: Folio (UUID) | Q11: Folio | R11: Fecha | S11: Tipo de Pago | T11: Estatus de Pago | U11: CHEK LIST | V11: Columna5 | W11: Columna6 | X11: Columna7 | Y11: Columna3 | Z11: Observaciones | AA11: Columna1 | AB11: Columna2
B12: JUN 2025 Q2 | C12: C3-5 | D12: ANA050518RL1 | E12: =IFERROR(IF(_xlfn.XLOOKUP(Imput[[#This Row],[RFC]],'Alta Proveedor'!D:D,'Alta Proveedor'!E:E)=0,"",_xlfn.XLOOKUP(Imput[[#This Row],[RFC]],'Alta Proveedor'!D:D,'Alta Proveedor'!E:E)),"") -> AEROENLACES NACIONALES (VUELOS) | F12: VUELOS - TARIFA AEREA PNR: PY4P6C | G12: 1 | H12: 2577.02 | I12: =Imput[[#This Row],[Cantidad]]*Imput[[#This Row],[Precio Unitario]] -> 2577.02 | J12: =Imput[[#This Row],[Sub total]]*0.159999 -> 412.32062 | K12: 0 | L12: =Imput[[#This Row],[Sub total]]+Imput[[#This Row],[IVA]]-Imput[[#This Row],[Retención / IEPS / Descuento]] -> 2989.3406 | M12: 4262.3446 | N12: Factura | P12: 858a58f4-390e-4a04-b8bc-7707d88b7d01 | Q12: B 130063376 | R12: 45686 | S12: 04.- TDC | V12: VIATICOS | W12: TRASLADO
B13: JUN 2025 Q2 | C13: C3-5 | D13: ANA050518RL1 | E13: =IFERROR(IF(_xlfn.XLOOKUP(Imput[[#This Row],[RFC]],'Alta Proveedor'!D:D,'Alta Proveedor'!E:E)=0,"",_xlfn.XLOOKUP(Imput[[#This Row],[RFC]],'Alta Proveedor'!D:D,'Alta Proveedor'!E:E)),"") -> AEROENLACES NACIONALES (VUELOS) | F13: VUELOS - SERVICIOS ADICIONALES | G13: 1 | H13: 14.15 | I13: =Imput[[#This Row],[Cantidad]]*Imput[[#This Row],[Precio Unitario]] -> 14.15 | J13: =Imput[[#This Row],[Sub total]]*0.159999 -> 2.2639859 | K13: 0 | L13: =Imput[[#This Row],[Sub total]]+Imput[[#This Row],[IVA]]-Imput[[#This Row],[Retención / IEPS / Descuento]] -> 16.413986 | M13: 0 | N13: Factura | P13: 858a58f4-390e-4a04-b8bc-7707d88b7d01 | Q13: B 130063376 | R13: 45686 | S13: 04.- TDC | V13: VIATICOS | W13: TRASLADO
B14: JUN 2025 Q2 | C14: C3-5 | D14: ANA050518RL1 | E14: =IFERROR(IF(_xlfn.XLOOKUP(Imput[[#This Row],[RFC]],'Alta Proveedor'!D:D,'Alta Proveedor'!E:E)=0,"",_xlfn.XLOOKUP(Imput[[#This Row],[RFC]],'Alta Proveedor'!D:D,'Alta Proveedor'!E:E)),"") -> AEROENLACES NACIONALES (VUELOS) | F14: VUELOS - CARGOS AEROPORTUARIOS | G14: 1 | H14: 1256.59 | I14: =Imput[[#This Row],[Cantidad]]*Imput[[#This Row],[Precio Unitario]] -> 1256.59 | J14: 0 | K14: 0 | L14: =Imput[[#This Row],[Sub total]]+Imput[[#This Row],[IVA]]-Imput[[#This Row],[Retención / IEPS / Descuento]] -> 1256.59 | M14: 0 | N14: Factura | P14: 858a58f4-390e-4a04-b8bc-7707d88b7d01 | Q14: B 130063376 | R14: 45686 | S14: 04.- TDC | V14: VIATICOS | W14: TRASLADO
B15: JUN 2025 Q2 | C15: C4-6 | D15: CAHE700209ATA | E15: =IFERROR(IF(_xlfn.XLOOKUP(Imput[[#This Row],[RFC]],'Alta Proveedor'!D:D,'Alta Proveedor'!E:E)=0,"",_xlfn.XLOOKUP(Imput[[#This Row],[RFC]],'Alta Proveedor'!D:D,'Alta Proveedor'!E:E)),"") -> ELVIA CABRERA HUERTA "MI PUEBLITO, MMM… QUE SABOR" (RESTAURANTE) | F15: RESTAURANTE - FAJIITA CON QUESO HARINA | G15: 1 | H15: 38.79 | I15: =Imput[[#This Row],[Cantidad]]*Imput[[#This Row],[Precio Unitario]] -> 38.79 | J15: =Imput[[#This Row],[Sub total]]*0.16 -> 6.2064 | K15: 0 | L15: =Imput[[#This Row],[Sub total]]+Imput[[#This Row],[IVA]]-Imput[[#This Row],[Retención / IEPS / Descuento]] -> 44.9964 | M15: 246.00584 | N15: Factura | P15: 273F2A11-F7FE-4321-8DCB-CE6BC96C18A1 | Q15: C3742 | R15: 45831 | S15: 28.- TDD | V15: VIATICOS | W15: ALIMENTOS
B16: JUN 2025 Q2 | C16: C4-6 | D16: CAHE700209ATA | E16: =IFERROR(IF(_xlfn.XLOOKUP(Imput[[#This Row],[RFC]],'Alta Proveedor'!D:D,'Alta Proveedor'!E:E)=0,"",_xlfn.XLOOKUP(Imput[[#This Row],[RFC]],'Alta Proveedor'!D:D,'Alta Proveedor'!E:E)),"") -> ELVIA CABRERA HUERTA "MI PUEBLITO, MMM… QUE SABOR" (RESTAURANTE) | F16: RESTAURANTE - HORCHATA 1 LITRO | G16: 1 | H16: 38.79 | I16: =Imput[[#This Row],[Cantidad]]*Imput[[#This Row],[Precio Unitario]] -> 38.79 | J16: =Imput[[#This Row],[Sub total]]*0.16 -> 6.2064 | K16: 0 | L16: =Imput[[#This Row],[Sub total]]+Imput[[#This Row],[IVA]]-Imput[[#This Row],[Retención / IEPS / Descuento]] -> 44.9964 | M16: 0 | N16: Factura | P16: 273F2A11-F7FE-4321-8DCB-CE6BC96C18A1 | Q16: C3742 | R16: 45831 | S16: 28.- TDD | V16: VIATICOS | W16: ALIMENTOS
B17: JUN 2025 Q2 | C17: C4-6 | D17: CAHE700209ATA | E17: =IFERROR(IF(_xlfn.XLOOKUP(Imput[[#This Row],[RFC]],'Alta Proveedor'!D:D,'Alta Proveedor'!E:E)=0,"",_xlfn.XLOOKUP(Imput[[#This Row],[RFC]],'Alta Proveedor'!D:D,'Alta Proveedor'!E:E)),"") -> ELVIA CABRERA HUERTA "MI PUEBLITO, MMM… QUE SABOR" (RESTAURANTE) | F17: RESTAURANTE - COCAS | G17: 1 | H17: 25.86 | I17: =Imput[[#This Row],[Cantidad]]*Imput[[#This Row],[Precio Unitario]] -> 25.86 | J17: =Imput[[#This Row],[Sub total]]*0.16 -> 4.1376 | K17: 0 | L17: =Imput[[#This Row],[Sub total]]+Imput[[#This Row],[IVA]]-Imput[[#This Row],[Retención / IEPS / Descuento]] -> 29.9976 | M17: 0 | N17: Factura | P17: 273F2A11-F7FE-4321-8DCB-CE6BC96C18A1 | Q17: C3742 | R17: 45831 | S17: 28.- TDD | V17: VIATICOS | W17: ALIMENTOS
B18: JUN 2025 Q2 | C18: C4-6 | D18: CAHE700209ATA | E18: =IFERROR(IF(_xlfn.XLOOKUP(Imput[[#This Row],[RFC]],'Alta Proveedor'!D:D,'Alta Proveedor'!E:E)=0,"",_xlfn.XLOOKUP(Imput[[#This Row],[RFC]],'Alta Proveedor'!D:D,'Alta Proveedor'!E:E)),"") -> ELVIA CABRERA HUERTA "MI PUEBLITO, MMM… QUE SABOR" (RESTAURANTE) | F18: RESTAURANTE - CHULETA CON QUESO HARINA | G18: 1 | H18: 36.21 | I18: =Imput[[#This Row],[Cantidad]]*Imput[[#This Row],[Precio Unitario]] -> 36.21 | J18: =Imput[[#This Row],[Sub total]]*0.16 -> 5.7936 | K18: 0 | L18: =Imput[[#This Row],[Sub total]]+Imput[[#This Row],[IVA]]-Imput[[#This Row],[Retención / IEPS / Descuento]] -> 42.0036 | M18: 0 | N18: Factura | P18: 273F2A11-F7FE-4321-8DCB-CE6BC96C18A1 | Q18: C3742 | R18: 45831 | S18: 28.- TDD | V18: VIATICOS | W18: ALIMENTOS
B19: JUN 2025 Q2 | C19: C4-6 | D19: CAHE700209ATA | E19: =IFERROR(IF(_xlfn.XLOOKUP(Imput[[#This Row],[RFC]],'Alta Proveedor'!D:D,'Alta Proveedor'!E:E)=0,"",_xlfn.XLOOKUP(Imput[[#This Row],[RFC]],'Alta Proveedor'!D:D,'Alta Proveedor'!E:E)),"") -> ELVIA CABRERA HUERTA "MI PUEBLITO, MMM… QUE SABOR" (RESTAURANTE) | F19: RESTAURANTE - CHULETA CON QUESO HARINA | G19: 2 | H19: 36.212 | I19: =Imput[[#This Row],[Cantidad]]*Imput[[#This Row],[Precio Unitario]] -> 72.424 | J19: =Imput[[#This Row],[Sub total]]*0.16 -> 11.58784 | K19: 0 | L19: =Imput[[#This Row],[Sub total]]+Imput[[#This Row],[IVA]]-Imput[[#This Row],[Retención / IEPS / Descuento]] -> 84.01184 | M19: 0 | N19: Factura | P19: 273F2A11-F7FE-4321-8DCB-CE6BC96C18A1 | Q19: C3742 | R19: 45831 | S19: 28.- TDD | V19: VIATICOS | W19: ALIMENTOS
B20: JUN 2025 Q2 | C20: C2-7 | D20: SSA010807N4A | E20: =IFERROR(IF(_xlfn.XLOOKUP(Imput[[#This Row],[RFC]],'Alta Proveedor'!D:D,'Alta Proveedor'!E:E)=0,"",_xlfn.XLOOKUP(Imput[[#This Row],[RFC]],'Alta Proveedor'!D:D,'Alta Proveedor'!E:E)),"") -> SERVICIO SAROGAR "NEXUM" (COMBUSTIBLES) | F20: COMBUSTIBLE - PREMIUM (2790780) | G20: 53.329913 | H20: 21.940725 | I20: =Imput[[#This Row],[Cantidad]]*Imput[[#This Row],[Precio Unitario]] -> 1170.097 | J20: 181.28 | K20: 0 | L20: =Imput[[#This Row],[Sub total]]+Imput[[#This Row],[IVA]]-Imput[[#This Row],[Retención / IEPS / Descuento]] -> 1351.377 | M20: 1351.377 | N20: Factura | P20: FC80EB46-3066-427F-8BC4-74B93B207014 | Q20: SSAFE - 85053 | R20: 45831 | S20: 04.- TDC | V20: COMBUSTIBLES | W20: GASOLINA
B21: JUN 2025 Q2 | C21: C4-6 | D21: POAJ841027D66 | E21: =IFERROR(IF(_xlfn.XLOOKUP(Imput[[#This Row],[RFC]],'Alta Proveedor'!D:D,'Alta Proveedor'!E:E)=0,"",_xlfn.XLOOKUP(Imput[[#This Row],[RFC]],'Alta Proveedor'!D:D,'Alta Proveedor'!E:E)),"") -> JONATHAN AZAEL PORTILLO ALEJO "EL MADERENSE MARISQUERIA" (RESTAURANTE) | F21: RESTAURANTE - CONSUMO DE ALIMENTOS Y BEBIDAS | G21: 1 | H21: =496.73+57 -> 553.73 | I21: =Imput[[#This Row],[Cantidad]]*Imput[[#This Row],[Precio Unitario]] -> 553.73 | J21: =(Imput[[#This Row],[Sub total]]-57)*0.16 -> 79.4768 | K21: 6.21 | L21: =Imput[[#This Row],[Sub total]]+Imput[[#This Row],[IVA]]-Imput[[#This Row],[Retención / IEPS / Descuento]] -> 626.9968 | M21: 626.9968 | N21: Factura | P21: C9962DA0-0F24-4E39-AB09-A4E4E83DB95D | Q21: A521 | R21: 45832 | S21: 04.- TDC | V21: VIATICOS | W21: ALIMENTOS
B22: JUN 2025 Q2 | C22: C2-8 | D22: CFC110121742 | E22: =IFERROR(IF(_xlfn.XLOOKUP(Imput[[#This Row],[RFC]],'Alta Proveedor'!D:D,'Alta Proveedor'!E:E)=0,"",_xlfn.XLOOKUP(Imput[[#This Row],[RFC]],'Alta Proveedor'!D:D,'Alta Proveedor'!E:E)),"") -> COMERCIALIZADORA FARMACEUTICA DE CHIAPAS | F22: PEAJES - TAG PASE PORTATIL BLIST 8851 | G22: 1 | H22: 129.31 | I22: =Imput[[#This Row],[Cantidad]]*Imput[[#This Row],[Precio Unitario]] -> 129.31 | J22: =Imput[[#This Row],[Sub total]]*0.16 -> 20.6896 | K22: 0 | L22: =Imput[[#This Row],[Sub total]]+Imput[[#This Row],[IVA]]-Imput[[#This Row],[Retención / IEPS / Descuento]] -> 149.9996 | M22: 149.9996 | N22: Factura | P22: 9F6AA786-45F6-4405-9F1C-E3EF43A818C0 | Q22: 9F6AA786 | R22: 45832 | S22: 04.- TDC | V22: VIATICOS | W22: PEAJES
B23: JUN 2025 Q2 | C23: C2-2 | D23: RUVL810825597 | E23: =IFERROR(IF(_xlfn.XLOOKUP(Imput[[#This Row],[RFC]],'Alta Proveedor'!D:D,'Alta Proveedor'!E:E)=0,"",_xlfn.XLOOKUP(Imput[[#This Row],[RFC]],'Alta Proveedor'!D:D,'Alta Proveedor'!E:E)),"") -> LUISA MARIA RUIZ VARGAS "MATRIX PASION POR TU AUTO" | F23: SERVICIO DE ALINEACION DELANTERA | G23: 1 | H23: 172.4149 | I23: =Imput[[#This Row],[Cantidad]]*Imput[[#This Row],[Precio Unitario]] -> 172.4149 | J23: =Imput[[#This Row],[Sub total]]*0.16 -> 27.586384 | K23: 0 | L23: =Imput[[#This Row],[Sub total]]+Imput[[#This Row],[IVA]]-Imput[[#This Row],[Retención / IEPS / Descuento]] -> 200.00128 | M23: 12000.002 | N23: Factura | P23: CA1ACE20-1B70-507A-8A63-A4D529FBC89C | Q23: FACTTAP2AARIA-1 | R23: 45832 | S23: 28.- TDD | V23: EQUIPO | W23: LLANTAS
B24: JUN 2025 Q2 | C24: C2-2 | D24: RUVL810825597 | E24: =IFERROR(IF(_xlfn.XLOOKUP(Imput[[#This Row],[RFC]],'Alta Proveedor'!D:D,'Alta Proveedor'!E:E)=0,"",_xlfn.XLOOKUP(Imput[[#This Row],[RFC]],'Alta Proveedor'!D:D,'Alta Proveedor'!E:E)),"") -> LUISA MARIA RUIZ VARGAS "MATRIX PASION POR TU AUTO" | F24: NEUMATICOS - 425/75/16 |LINK PENTERRA R/T AUTO 111Q | G24: 4 | H24: =10172.414/4 -> 2543.1035 | I24: =Imput[[#This Row],[Cantidad]]*Imput[[#This Row],[Precio Unitario]] -> 10172.414 | J24: =Imput[[#This Row],[Sub total]]*0.16 -> 1627.5862 | K24: 0 | L24: =Imput[[#This Row],[Sub total]]+Imput[[#This Row],[IVA]]-Imput[[#This Row],[Retención / IEPS / Descuento]] -> 11800 | M24: 0 | N24: Factura | P24: CA1ACE20-1B70-507A-8A63-A4D529FBC89C | Q24: FACTTAP2AARIA-1 | R24: 45832 | S24: 28.- TDD | V24: EQUIPO | W24: LLANTAS
B25: JUN 2025 Q2 | C25: C2-2 | D25: ROGM701116LV6 | E25: =IFERROR(IF(_xlfn.XLOOKUP(Imput[[#This Row],[RFC]],'Alta Proveedor'!D:D,'Alta Proveedor'!E:E)=0,"",_xlfn.XLOOKUP(Imput[[#This Row],[RFC]],'Alta Proveedor'!D:D,'Alta Proveedor'!E:E)),"") -> MIGUEL ANGEL ROCHA GARCIA | F25: VENTA E INSTALACION DE AUTOESTEREO | G25: 1 | H25: 2000 | I25: =Imput[[#This Row],[Cantidad]]*Imput[[#This Row],[Precio Unitario]] -> 2000 | J25: =Imput[[#This Row],[Sub total]]*0.16 -> 320 | K25: 25 | L25: =Imput[[#This Row],[Sub total]]+Imput[[#This Row],[IVA]]-Imput[[#This Row],[Retención / IEPS / Descuento]] -> 2295 | M25: 2295 | N25: Factura | P25: 8938DE0F-DB7C-43AF-AF01-2203691A7DE2 | Q25: 25 | R25: 45833 | S25: 03.- Transferencia | V25: EQUIPO | W25: ESTEREO
B26: JUN 2025 Q2 | C26: C4-6 | D26: LOZ170722KGA | E26: =IFERROR(IF(_xlfn.XLOOKUP(Imput[[#This Row],[RFC]],'Alta Proveedor'!D:D,'Alta Proveedor'!E:E)=0,"",_xlfn.XLOOKUP(Imput[[#This Row],[RFC]],'Alta Proveedor'!D:D,'Alta Proveedor'!E:E)),"") -> EL LINDERO DE OZULUAMA (RESTAURANTE) | F26: RESTAURANTE - CONSUMO DE ALIMENTOS Y BEBIDAS | G26: 1 | H26: 780.17 | I26: =Imput[[#This Row],[Cantidad]]*Imput[[#This Row],[Precio Unitario]] -> 780.17 | J26: =Imput[[#This Row],[Sub total]]*0.16 -> 124.8272 | K26: -91 | L26: =Imput[[#This Row],[Sub total]]+Imput[[#This Row],[IVA]]-Imput[[#This Row],[Retención / IEPS / Descuento]] -> 995.9972 | M26: 995.9972 | N26: Factura | P26: 34B4401D-17B3-4812-B93C-A9F3F78362E4 | Q26: A25504 | R26: 45834 | S26: 04.- TDC | V26: VIATICOS | W26: ALIMENTOS
B27: JUN 2025 Q2 | C27: C2-7 | D27: ROBL4512274I1 | E27: =IFERROR(IF(_xlfn.XLOOKUP(Imput[[#This Row],[RFC]],'Alta Proveedor'!D:D,'Alta Proveedor'!E:E)=0,"",_xlfn.XLOOKUP(Imput[[#This Row],[RFC]],'Alta Proveedor'!D:D,'Alta Proveedor'!E:E)),"") -> Estacion de servicio No. 6580 JOSE LUIS RODRIGUEZ BERLANGA (COMBUSTIBLES) | F27: COMBUSTIBLE - SUPERIOR (2568444) | G27: 40 | H27: 21.05725 | I27: =Imput[[#This Row],[Cantidad]]*Imput[[#This Row],[Precio Unitario]] -> 842.29 | J27: 130.51 | K27: 0 | L27: =Imput[[#This Row],[Sub total]]+Imput[[#This Row],[IVA]]-Imput[[#This Row],[Retención / IEPS / Descuento]] -> 972.8 | M27: 972.8 | N27: Factura | P27: 1D2F8ECD-2A80-4538-A399-1624FA1F055D | Q27: AL 41,793 | R27: 45834 | S27: 04.- TDC | V27: COMBUSTIBLES | W27: GASOLINA
B28: JUN 2025 Q2 | C28: C4-6 | D28: MASR990207BB1 | E28: =IFERROR(IF(_xlfn.XLOOKUP(Imput[[#This Row],[RFC]],'Alta Proveedor'!D:D,'Alta Proveedor'!E:E)=0,"",_xlfn.XLOOKUP(Imput[[#This Row],[RFC]],'Alta Proveedor'!D:D,'Alta Proveedor'!E:E)),"") -> RICARDO MARTINEZ SALAZAR (RESTAURANTE) | F28: RESTAURANTE - CONSUMO DE ALIMENTOS | G28: 1 | H28: 222.21 | I28: =Imput[[#This Row],[Cantidad]]*Imput[[#This Row],[Precio Unitario]] -> 222.21 | J28: =Imput[[#This Row],[Sub total]]*0.16 -> 35.5536 | K28: 2.76 | L28: =Imput[[#This Row],[Sub total]]+Imput[[#This Row],[IVA]]-Imput[[#This Row],[Retención / IEPS / Descuento]] -> 255.0036 | M28: 255.0036 | N28: Factura | P28: FC034230-6E26-4268-A931-30F92C1A5B2E | Q28: FC034230 | R28: 45834 | S28: 04.- TDC | V28: VIATICOS | W28: ALIMENTOS
B29: JUN 2025 Q2 | C29: C4-6 | D29: GUCA670908V23 | E29: =IFERROR(IF(_xlfn.XLOOKUP(Imput[[#This Row],[RFC]],'Alta Proveedor'!D:D,'Alta Proveedor'!E:E)=0,"",_xlfn.XLOOKUP(Imput[[#This Row],[RFC]],'Alta Proveedor'!D:D,'Alta Proveedor'!E:E)),"") -> AUGUSTO EDUARDO GUERRERO CRUZ (RESTAURANTE) | F29: RESTAURANTE - CONSUMO DE ALIMENTOS Y BEBIDAS | G29: 1 | H29: 275.86 | I29: =Imput[[#This Row],[Cantidad]]*Imput[[#This Row],[Precio Unitario]] -> 275.86 | J29: =Imput[[#This Row],[Sub total]]*0.16 -> 44.1376 | K29: 0 | L29: =Imput[[#This Row],[Sub total]]+Imput[[#This Row],[IVA]]-Imput[[#This Row],[Retención / IEPS / Descuento]] -> 319.9976 | M29: 319.9976 | N29: Factura | P29: ADC076A2-81A0-4ED6-8F21-2674B7727006 | Q29: C36051 | R29: 45835 | S29: 28.- TDD | V29: VIATICOS | W29: ALIMENTOS
B30: JUN 2025 Q2 | C30: C4-6 | D30: MAS0810247C0 | E30: =IFERROR(IF(_xlfn.XLOOKUP(Imput[[#This Row],[RFC]],'Alta Proveedor'!D:D,'Alta Proveedor'!E:E)=0,"",_xlfn.XLOOKUP(Imput[[#This Row],[RFC]],'Alta Proveedor'!D:D,'Alta Proveedor'!E:E)),"") -> POPAT BAZAR SA DE CV "BUFFALITAS, BUFFALO WINGS, BURGUERS Y RIBS" (RESTAURANTE) | F30: RESTAURANTE - CONSUMO DE ALIMENTOS | G30: 1 | H30: 468.1 | I30: =Imput[[#This Row],[Cantidad]]*Imput[[#This Row],[Precio Unitario]] -> 468.1 | J30: =Imput[[#This Row],[Sub total]]*0.16 -> 74.896 | K30: 0 | L30: =Imput[[#This Row],[Sub total]]+Imput[[#This Row],[IVA]]-Imput[[#This Row],[Retención / IEPS / Descuento]] -> 542.996 | M30: 542.996 | N30: Factura | P30: 09CC0777-4F02-4EDB-92C4-C5C3B4C68612 | Q30: B 12748 | R30: 45835 | V30: VIATICOS | W30: ALIMENTOS
B31: JUN 2025 Q2 | C31: TAM-P1-5 | D31: Nomina-OPERACIÓN | E31: =IFERROR(IF(_xlfn.XLOOKUP(Imput[[#This Row],[RFC]],'Alta Proveedor'!D:D,'Alta Proveedor'!E:E)=0,"",_xlfn.XLOOKUP(Imput[[#This Row],[RFC]],'Alta Proveedor'!D:D,'Alta Proveedor'!E:E)),"") -> Nomina-OPERACIÓN | F31: MARIA ISABEL DE ANGEL | ANTICIPO EXCAVACION | G31: 1 | H31: 40000 | I31: =Imput[[#This Row],[Cantidad]]*Imput[[#This Row],[Precio Unitario]] -> 40000 | J31: =Imput[[#This Row],[Sub total]]*0.08 -> 3200 | K31: 0 | L31: =Imput[[#This Row],[Sub total]]+Imput[[#This Row],[IVA]]-Imput[[#This Row],[Retención / IEPS / Descuento]] -> 43200 | M31: 43200 | R31: 45835 | S31: 03.- Transferencia | U31: GASTOS SIN FACTURA | V31: NOMINA | W31: EXCAVACIÓN
B32: JUN 2025 Q2 | C32: TAM-P4-10 | D32: HDM001017AS1 THD-8730 TAMPICO | E32: =IFERROR(IF(_xlfn.XLOOKUP(Imput[[#This Row],[RFC]],'Alta Proveedor'!D:D,'Alta Proveedor'!E:E)=0,"",_xlfn.XLOOKUP(Imput[[#This Row],[RFC]],'Alta Proveedor'!D:D,'Alta Proveedor'!E:E)),"") -> HOME DEPOT MEXICO SUCURSAL THD-8730 TAMPICO | F32: SEGURIDAD - MALLA DE CONSTRUCCION PERIMETRAL 30 | G32: 1 | H32: 244.14 | I32: =Imput[[#This Row],[Cantidad]]*Imput[[#This Row],[Precio Unitario]] -> 244.14 | J32: =Imput[[#This Row],[Sub total]]*0.16 -> 39.0624 | K32: 0 | L32: =Imput[[#This Row],[Sub total]]+Imput[[#This Row],[IVA]]-Imput[[#This Row],[Retención / IEPS / Descuento]] -> 283.2024 | M32: 283.2024 | N32: Factura | P32: 507470aa-9f63-4a0a-a207-ca155033901a | Q32: 4HGCJI 424199 | R32: 45836 | S32: 04.- TDC | V32: MATERIAL | W32: MATERIAL CONSTRUCCIÓN
B33: JUN 2025 Q2 | C33: C2-7 | D33: CLG130128KA0 | E33: =IFERROR(IF(_xlfn.XLOOKUP(Imput[[#This Row],[RFC]],'Alta Proveedor'!D:D,'Alta Proveedor'!E:E)=0,"",_xlfn.XLOOKUP(Imput[[#This Row],[RFC]],'Alta Proveedor'!D:D,'Alta Proveedor'!E:E)),"") -> E12196 COMBUSTIBLES Y LUBRICANTES GHN (COMBUSTIBLES) | F33: COMBUSTIBLE - PREMIUM (nota 2493616-0) | G33: 30.897 | H33: 22.423483 | I33: =Imput[[#This Row],[Cantidad]]*Imput[[#This Row],[Precio Unitario]] -> 692.81835 | J33: 107.41 | K33: 0 | L33: =Imput[[#This Row],[Sub total]]+Imput[[#This Row],[IVA]]-Imput[[#This Row],[Retención / IEPS / Descuento]] -> 800.22835 | M33: 800.22835 | N33: Factura | P33: 9291d69b-13bb-4ebc-8011-3a781f4f9635 | Q33: LW 20834 | R33: 45836 | S33: 04.- TDC | V33: COMBURSTIBLES | W33: GASOLINA
B34: JUN 2025 Q2 | C34: TAM-P4-17 | D34: MAS991101DH9 | E34: =IFERROR(IF(_xlfn.XLOOKUP(Imput[[#This Row],[RFC]],'Alta Proveedor'!D:D,'Alta Proveedor'!E:E)=0,"",_xlfn.XLOOKUP(Imput[[#This Row],[RFC]],'Alta Proveedor'!D:D,'Alta Proveedor'!E:E)),"") -> MASYFERR (FERRETERIA) | F34: MATERIAL - VARILLA CORRUGADA CON NORMA, AR-42 19MM=3/4"X12M | G34: 65 | H34: 443.9655 | I34: =Imput[[#This Row],[Cantidad]]*Imput[[#This Row],[Precio Unitario]] -> 28857.757 | J34: =Imput[[#This Row],[Sub total]]*0.16 -> 4617.2412 | K34: 0 | L34: =Imput[[#This Row],[Sub total]]+Imput[[#This Row],[IVA]]-Imput[[#This Row],[Retención / IEPS / Descuento]] -> 33474.999 | M34: 40280.395 | N34: Factura | P34: 28E77138-2279-47FA-AA83-52165F350500 | Q34: M-0451984 | R34: 45836 | S34: 04.- TDC | V34: MATERIAL | W34: MATERIAL CONSTRUCCIÓN
B35: JUN 2025 Q2 | C35: TAM-P4-4 | D35: MAS991101DH9 | E35: =IFERROR(IF(_xlfn.XLOOKUP(Imput[[#This Row],[RFC]],'Alta Proveedor'!D:D,'Alta Proveedor'!E:E)=0,"",_xlfn.XLOOKUP(Imput[[#This Row],[RFC]],'Alta Proveedor'!D:D,'Alta Proveedor'!E:E)),"") -> MASYFERR (FERRETERIA) | F35: MATERIAL - ALAMBRE QUEMADO BOBINA | G35: 50 | H35: 20.2586 | I35: =Imput[[#This Row],[Cantidad]]*Imput[[#This Row],[Precio Unitario]] -> 1012.93 | J35: =Imput[[#This Row],[Sub total]]*0.16 -> 162.0688 | K35: 0 | L35: =Imput[[#This Row],[Sub total]]+Imput[[#This Row],[IVA]]-Imput[[#This Row],[Retención / IEPS / Descuento]] -> 1174.9988 | M35: 0 | N35: Factura | P35: 28E77138-2279-47FA-AA83-52165F350500 | Q35: M-0451984 | R35: 45836 | S35: 04.- TDC | V35: MATERIAL | W35: MATERIAL CONSTRUCCIÓN
B36: JUN 2025 Q2 | C36: TAM-P4-16 | D36: MAS991101DH9 | E36: =IFERROR(IF(_xlfn.XLOOKUP(Imput[[#This Row],[RFC]],'Alta Proveedor'!D:D,'Alta Proveedor'!E:E)=0,"",_xlfn.XLOOKUP(Imput[[#This Row],[RFC]],'Alta Proveedor'!D:D,'Alta Proveedor'!E:E)),"") -> MASYFERR (FERRETERIA) | F36: MATERIAL - VARILLA CORRUGADA CON NORMA, AR-42 10MM=3/8"X12M | G36: 46 | H36: 105.5172 | I36: =Imput[[#This Row],[Cantidad]]*Imput[[#This Row],[Precio Unitario]] -> 4853.7912 | J36: =Imput[[#This Row],[Sub total]]*0.16 -> 776.60659 | K36: 0 | L36: =Imput[[#This Row],[Sub total]]+Imput[[#This Row],[IVA]]-Imput[[#This Row],[Retención / IEPS / Descuento]] -> 5630.3978 | M36: 0 | N36: Factura | P36: 28E77138-2279-47FA-AA83-52165F350500 | Q36: M-0451984 | R36: 45836 | S36: 04.- TDC | V36: MATERIAL | W36: MATERIAL CONSTRUCCIÓN
B37: JUN 2025 Q2 | C37: TAM-P4-17 | D37: MAS991101DH9 | E37: =IFERROR(IF(_xlfn.XLOOKUP(Imput[[#This Row],[RFC]],'Alta Proveedor'!D:D,'Alta Proveedor'!E:E)=0,"",_xlfn.XLOOKUP(Imput[[#This Row],[RFC]],'Alta Proveedor'!D:D,'Alta Proveedor'!E:E)),"") -> MASYFERR (FERRETERIA) | F37: MATERIAL - BONIFICACION EN PRECIO | G37: =-1/3 -> -0.33333333 | H37: 253.79 | I37: =Imput[[#This Row],[Cantidad]]*Imput[[#This Row],[Precio Unitario]] -> -84.596667 | J37: =Imput[[#This Row],[Sub total]]*0.16 -> -13.535467 | K37: 0 | L37: =Imput[[#This Row],[Sub total]]+Imput[[#This Row],[IVA]]-Imput[[#This Row],[Retención / IEPS / Descuento]] -> -98.132133 | M37: -294.3964 | N37: Nota de Crédito | P37: CC11F747-27C0-4143-A3B5-9B5C96219A58 | Q37: ME-0022968 | R37: 45836 | S37: 04.- TDC | V37: MATERIAL | W37: MATERIAL CONSTRUCCIÓN
B38: JUN 2025 Q2 | C38: TAM-P4-4 | D38: MAS991101DH9 | E38: =IFERROR(IF(_xlfn.XLOOKUP(Imput[[#This Row],[RFC]],'Alta Proveedor'!D:D,'Alta Proveedor'!E:E)=0,"",_xlfn.XLOOKUP(Imput[[#This Row],[RFC]],'Alta Proveedor'!D:D,'Alta Proveedor'!E:E)),"") -> MASYFERR (FERRETERIA) | F38: MATERIAL - BONIFICACION EN PRECIO | G38: =-1/3 -> -0.33333333 | H38: 253.79 | I38: =Imput[[#This Row],[Cantidad]]*Imput[[#This Row],[Precio Unitario]] -> -84.596667 | J38: =Imput[[#This Row],[Sub total]]*0.16 -> -13.535467 | K38: 0 | L38: =Imput[[#This Row],[Sub total]]+Imput[[#This Row],[IVA]]-Imput[[#This Row],[Retención / IEPS / Descuento]] -> -98.132133 | M38: 0 | N38: Nota de Crédito | P38: CC11F747-27C0-4143-A3B5-9B5C96219A58 | Q38: ME-0022968 | R38: 45836 | S38: 04.- TDC | V38: MATERIAL | W38: MATERIAL CONSTRUCCIÓN
B39: JUN 2025 Q2 | C39: TAM-P4-16 | D39: MAS991101DH9 | E39: =IFERROR(IF(_xlfn.XLOOKUP(Imput[[#This Row],[RFC]],'Alta Proveedor'!D:D,'Alta Proveedor'!E:E)=0,"",_xlfn.XLOOKUP(Imput[[#This Row],[RFC]],'Alta Proveedor'!D:D,'Alta Proveedor'!E:E)),"") -> MASYFERR (FERRETERIA) | F39: MATERIAL - BONIFICACION EN PRECIO | G39: =-1/3 -> -0.33333333 | H39: 253.79 | I39: =Imput[[#This Row],[Cantidad]]*Imput[[#This Row],[Precio Unitario]] -> -84.596667 | J39: =Imput[[#This Row],[Sub total]]*0.16 -> -13.535467 | K39: 0 | L39: =Imput[[#This Row],[Sub total]]+Imput[[#This Row],[IVA]]-Imput[[#This Row],[Retención / IEPS / Descuento]] -> -98.132133 | M39: 0 | N39: Nota de Crédito | P39: CC11F747-27C0-4143-A3B5-9B5C96219A58 | Q39: ME-0022968 | R39: 45836 | S39: 04.- TDC | V39: MATERIAL | W39: MATERIAL CONSTRUCCIÓN
B40: JUN 2025 Q2 | C40: C4-6 | D40: GUCA670908V23 | E40: =IFERROR(IF(_xlfn.XLOOKUP(Imput[[#This Row],[RFC]],'Alta Proveedor'!D:D,'Alta Proveedor'!E:E)=0,"",_xlfn.XLOOKUP(Imput[[#This Row],[RFC]],'Alta Proveedor'!D:D,'Alta Proveedor'!E:E)),"") -> AUGUSTO EDUARDO GUERRERO CRUZ (RESTAURANTE) | F40: RESTAURANTE - CONSUMO DE ALIMENTOS Y BEBIDAS | G40: 1 | H40: 185.344 | I40: =Imput[[#This Row],[Cantidad]]*Imput[[#This Row],[Precio Unitario]] -> 185.344 | J40: =Imput[[#This Row],[Sub total]]*0.16 -> 29.65504 | K40: 0 | L40: =Imput[[#This Row],[Sub total]]+Imput[[#This Row],[IVA]]-Imput[[#This Row],[Retención / IEPS / Descuento]] -> 214.99904 | M40: 214.99904 | N40: Factura | P40: 179D7540-D9E6-479B-BC61-1FFC4D745199 | Q40: C36106 | R40: 45837 | S40: 04.- TDC | V40: VIATICOS | W40: ALIMENTOS
B41: JUN 2025 Q2 | C41: TAM-P1-5 | D41: Nomina-OPERACIÓN | E41: =IFERROR(IF(_xlfn.XLOOKUP(Imput[[#This Row],[RFC]],'Alta Proveedor'!D:D,'Alta Proveedor'!E:E)=0,"",_xlfn.XLOOKUP(Imput[[#This Row],[RFC]],'Alta Proveedor'!D:D,'Alta Proveedor'!E:E)),"") -> Nomina-OPERACIÓN | F41: EDGAR FRANCISCO FRANCO | PAGO 10% | G41: 1 | H41: 15000 | I41: =Imput[[#This Row],[Cantidad]]*Imput[[#This Row],[Precio Unitario]] -> 15000 | J41: =Imput[[#This Row],[Sub total]]*0.08 -> 1200 | K41: 0 | L41: =Imput[[#This Row],[Sub total]]+Imput[[#This Row],[IVA]]-Imput[[#This Row],[Retención / IEPS / Descuento]] -> 16200 | M41: 16200 | R41: 45837 | S41: 03.- Transferencia | U41: GASTOS SIN FACTURA | V41: NOMINA | W41: EXCAVACIÓN
B42: JUN 2025 Q2 | C42: C4-6 | D42: DLI931201MI9 | E42: =IFERROR(IF(_xlfn.XLOOKUP(Imput[[#This Row],[RFC]],'Alta Proveedor'!D:D,'Alta Proveedor'!E:E)=0,"",_xlfn.XLOOKUP(Imput[[#This Row],[RFC]],'Alta Proveedor'!D:D,'Alta Proveedor'!E:E)),"") -> DISTRIBUIDORA LIVERPOOL | F42: RESTAURANTE - CONSUMO RESTAURANTE | G42: 1 | H42: 275 | I42: =Imput[[#This Row],[Cantidad]]*Imput[[#This Row],[Precio Unitario]] -> 275 | J42: =Imput[[#This Row],[Sub total]]*0.16 -> 44 | K42: 0 | L42: =Imput[[#This Row],[Sub total]]+Imput[[#This Row],[IVA]]-Imput[[#This Row],[Retención / IEPS / Descuento]] -> 319 | M42: 319 | N42: Factura | P42: AC3CF806-DF84-5ED4-9EC5-3D0A6934EF17 | Q42: LWIU 455938 | R42: 45838 | S42: 04.- TDC | V42: VIATICOS | W42: ALIMENTOS
B43: JUN 2025 Q2 | C43: TAM-P4-9 | D43: UAGG890111FP7 | E43: =IFERROR(IF(_xlfn.XLOOKUP(Imput[[#This Row],[RFC]],'Alta Proveedor'!D:D,'Alta Proveedor'!E:E)=0,"",_xlfn.XLOOKUP(Imput[[#This Row],[RFC]],'Alta Proveedor'!D:D,'Alta Proveedor'!E:E)),"") -> GUILLERMO UMAÑA GONZALEZ | F43: MATERIAL - 11121616 ‐ Madera de pino MADERA 2X4X10 | G43: 4 | H43: 129.31 | I43: =Imput[[#This Row],[Cantidad]]*Imput[[#This Row],[Precio Unitario]] -> 517.24 | J43: =Imput[[#This Row],[Sub total]]*0.16 -> 82.7584 | K43: 0 | L43: =Imput[[#This Row],[Sub total]]+Imput[[#This Row],[IVA]]-Imput[[#This Row],[Retención / IEPS / Descuento]] -> 599.9984 | M43: 1680.0048 | N43: Factura | P43: E5677537‐B090‐46EB‐BDFA‐92F852D2C812 | Q43: F ‐ 5664 | R43: 45838 | S43: 04.- TDC | V43: MATERIAL | W43: MATERIAL CONSTRUCCIÓN
B44: JUN 2025 Q2 | C44: TAM-P4-9 | D44: UAGG890111FP7 | E44: =IFERROR(IF(_xlfn.XLOOKUP(Imput[[#This Row],[RFC]],'Alta Proveedor'!D:D,'Alta Proveedor'!E:E)=0,"",_xlfn.XLOOKUP(Imput[[#This Row],[RFC]],'Alta Proveedor'!D:D,'Alta Proveedor'!E:E)),"") -> GUILLERMO UMAÑA GONZALEZ | F44: MATERIAL - 11121616 ‐ Madera de pino 2X8X8 | G44: 2 | H44: 224.14 | I44: =Imput[[#This Row],[Cantidad]]*Imput[[#This Row],[Precio Unitario]] -> 448.28 | J44: =Imput[[#This Row],[Sub total]]*0.16 -> 71.7248 | K44: 0 | L44: =Imput[[#This Row],[Sub total]]+Imput[[#This Row],[IVA]]-Imput[[#This Row],[Retención / IEPS / Descuento]] -> 520.0048 | M44: 0 | N44: Factura | P44: E5677537‐B090‐46EB‐BDFA‐92F852D2C812 | Q44: F ‐ 5664 | R44: 45838 | S44: 04.- TDC | V44: MATERIAL | W44: MATERIAL CONSTRUCCIÓN
B45: JUN 2025 Q2 | C45: TAM-P4-9 | D45: UAGG890111FP7 | E45: =IFERROR(IF(_xlfn.XLOOKUP(Imput[[#This Row],[RFC]],'Alta Proveedor'!D:D,'Alta Proveedor'!E:E)=0,"",_xlfn.XLOOKUP(Imput[[#This Row],[RFC]],'Alta Proveedor'!D:D,'Alta Proveedor'!E:E)),"") -> GUILLERMO UMAÑA GONZALEZ | F45: MATERIAL - 11121616 ‐ Madera de pino 4X4X8 | G45: 2 | H45: 215.52 | I45: =Imput[[#This Row],[Cantidad]]*Imput[[#This Row],[Precio Unitario]] -> 431.04 | J45: =Imput[[#This Row],[Sub total]]*0.16 -> 68.9664 | K45: 0 | L45: =Imput[[#This Row],[Sub total]]+Imput[[#This Row],[IVA]]-Imput[[#This Row],[Retención / IEPS / Descuento]] -> 500.0064 | M45: 0 | N45: Factura | P45: E5677537‐B090‐46EB‐BDFA‐92F852D2C812 | Q45: F ‐ 5664 | R45: 45838 | S45: 04.- TDC | V45: MATERIAL | W45: MATERIAL CONSTRUCCIÓN
B46: JUN 2025 Q2 | C46: TAM-P4-18 | D46: UAGG890111FP7 | E46: =IFERROR(IF(_xlfn.XLOOKUP(Imput[[#This Row],[RFC]],'Alta Proveedor'!D:D,'Alta Proveedor'!E:E)=0,"",_xlfn.XLOOKUP(Imput[[#This Row],[RFC]],'Alta Proveedor'!D:D,'Alta Proveedor'!E:E)),"") -> GUILLERMO UMAÑA GONZALEZ | F46: MATERIAL CONSUMIBLE - 31162004 ‐ Clavos de mampostería CLAVO PARA MADERA 4" | G46: 1 | H46: 51.72 | I46: =Imput[[#This Row],[Cantidad]]*Imput[[#This Row],[Precio Unitario]] -> 51.72 | J46: =Imput[[#This Row],[Sub total]]*0.16 -> 8.2752 | K46: 0 | L46: =Imput[[#This Row],[Sub total]]+Imput[[#This Row],[IVA]]-Imput[[#This Row],[Retención / IEPS / Descuento]] -> 59.9952 | M46: 0 | N46: Factura | P46: E5677537‐B090‐46EB‐BDFA‐92F852D2C812 | Q46: F ‐ 5664 | R46: 45838 | S46: 04.- TDC | V46: MATERIAL | W46: MATERIAL CONSTRUCCIÓN
B47: JUN 2025 Q2 | C47: TAM-P9-1 | D47: MAS991101DH9 | E47: =IFERROR(IF(_xlfn.XLOOKUP(Imput[[#This Row],[RFC]],'Alta Proveedor'!D:D,'Alta Proveedor'!E:E)=0,"",_xlfn.XLOOKUP(Imput[[#This Row],[RFC]],'Alta Proveedor'!D:D,'Alta Proveedor'!E:E)),"") -> MASYFERR (FERRETERIA) | F47: EPP - GUANTES DE CARNAZA UNITALLA CORTO PAR 19AH023578 | G47: 1 | H47: 73.1897 | I47: =Imput[[#This Row],[Cantidad]]*Imput[[#This Row],[Precio Unitario]] -> 73.1897 | J47: =Imput[[#This Row],[Sub total]]*0.16 -> 11.710352 | K47: 0 | L47: =Imput[[#This Row],[Sub total]]+Imput[[#This Row],[IVA]]-Imput[[#This Row],[Retención / IEPS / Descuento]] -> 84.900052 | M47: 633.89998 | N47: Factura | P47: F0AD6AD8-4964-4ECD-9A4D-3A95F0EBC166 | Q47: M-0452113 | R47: 45838 | S47: 04.- TDC | V47: MATERIAL | W47: EPP
B48: JUN 2025 Q2 | C48: TAM-P9-1 | D48: MAS991101DH9 | E48: =IFERROR(IF(_xlfn.XLOOKUP(Imput[[#This Row],[RFC]],'Alta Proveedor'!D:D,'Alta Proveedor'!E:E)=0,"",_xlfn.XLOOKUP(Imput[[#This Row],[RFC]],'Alta Proveedor'!D:D,'Alta Proveedor'!E:E)),"") -> MASYFERR (FERRETERIA) | F48: EPP - ZZ*CASCO DE SEGURIDAD INDUSTRIAL NARANJA 4 PUNTOS WW-2002ANK | G48: 6 | H48: 78.8793 | I48: =Imput[[#This Row],[Cantidad]]*Imput[[#This Row],[Precio Unitario]] -> 473.2758 | J48: =Imput[[#This Row],[Sub total]]*0.16 -> 75.724128 | K48: 0 | L48: =Imput[[#This Row],[Sub total]]+Imput[[#This Row],[IVA]]-Imput[[#This Row],[Retención / IEPS / Descuento]] -> 548.99993 | M48: 0 | N48: Factura | P48: F0AD6AD8-4964-4ECD-9A4D-3A95F0EBC166 | Q48: M-0452113 | R48: 45838 | S48: 04.- TDC | V48: MATERIAL | W48: EPP
B49: JUN 2025 Q2 | C49: TAM-P4-9 | D49: PFL981207AX5 | E49: =IFERROR(IF(_xlfn.XLOOKUP(Imput[[#This Row],[RFC]],'Alta Proveedor'!D:D,'Alta Proveedor'!E:E)=0,"",_xlfn.XLOOKUP(Imput[[#This Row],[RFC]],'Alta Proveedor'!D:D,'Alta Proveedor'!E:E)),"") -> PERFILES DE FIERRO Y LAMINA ATIYE "ACEROTAM" | F49: MATERIAL - LAMINA NEGRA 4 X 10 CAL 1/8 | G49: 91 | H49: 20.76 | I49: =Imput[[#This Row],[Cantidad]]*Imput[[#This Row],[Precio Unitario]] -> 1889.16 | J49: =Imput[[#This Row],[Sub total]]*0.16 -> 302.2656 | K49: 0 | L49: =Imput[[#This Row],[Sub total]]+Imput[[#This Row],[IVA]]-Imput[[#This Row],[Retención / IEPS / Descuento]] -> 2191.4256 | M49: 2191.4256 | N49: Factura | P49: E3D87202-C393-4F57-9987-B5A94C7077BA | Q49: PFL 585599 | R49: 45838 | S49: 04.- TDC | V49: MATERIAL | W49: MATERIAL CONSTRUCCIÓN
B50: JUN 2025 Q2 | C50: C3-1 | D50: GASTOS SIN FACTURA | E50: =IFERROR(IF(_xlfn.XLOOKUP(Imput[[#This Row],[RFC]],'Alta Proveedor'!D:D,'Alta Proveedor'!E:E)=0,"",_xlfn.XLOOKUP(Imput[[#This Row],[RFC]],'Alta Proveedor'!D:D,'Alta Proveedor'!E:E)),"") -> GASTOS SIN FACTURA | F50: JAIME LOPEZ | RENTA CASA MES 1 | G50: 1 | H50: 7700 | I50: =Imput[[#This Row],[Cantidad]]*Imput[[#This Row],[Precio Unitario]] -> 7700 | J50: =Imput[[#This Row],[Sub total]]*0.08 -> 616 | K50: 0 | L50: =Imput[[#This Row],[Sub total]]+Imput[[#This Row],[IVA]]-Imput[[#This Row],[Retención / IEPS / Descuento]] -> 8316 | M50: 8316 | R50: 45838 | S50: 03.- Transferencia | U50: GASTOS SIN FACTURA | V50: VIATICOS | W50: CAMPAMENTO
B51: JUL 2025 Q1 | C51: MAN-P4-17 | D51: MNG8612308V8 | E51: =IFERROR(IF(_xlfn.XLOOKUP(Imput[[#This Row],[RFC]],'Alta Proveedor'!D:D,'Alta Proveedor'!E:E)=0,"",_xlfn.XLOOKUP(Imput[[#This Row],[RFC]],'Alta Proveedor'!D:D,'Alta Proveedor'!E:E)),"") -> M.N. DEL GOLFO "HOME CENTER TU ASESOR CONFIABLE" | F51: MATERIAL - VARILLA RECTA #6 3/4X12 M AR-42 | G51: 77 | H51: =63551.2/152 -> 418.1 | I51: =Imput[[#This Row],[Cantidad]]*Imput[[#This Row],[Precio Unitario]] -> 32193.7 | J51: =((Imput[[#This Row],[Sub total]])*0.16) -> 5150.992 | K51: 0 | L51: =Imput[[#This Row],[Sub total]]+Imput[[#This Row],[IVA]]-Imput[[#This Row],[Retención / IEPS / Descuento]] -> 37344.692 | M51: 86595.392 | N51: Factura | P51: 711A0F15-A5A1-4481-84E5-5FB2756E09D8 | Q51: S004TPV40330034794 | R51: 45841 | S51: 04.- TDC | V51: MATERIAL | W51: MATERIAL CONSTRUCCIÓN
B52: JUL 2025 Q1 | C52: TAM-P4-17 | D52: MNG8612308V8 | E52: =IFERROR(IF(_xlfn.XLOOKUP(Imput[[#This Row],[RFC]],'Alta Proveedor'!D:D,'Alta Proveedor'!E:E)=0,"",_xlfn.XLOOKUP(Imput[[#This Row],[RFC]],'Alta Proveedor'!D:D,'Alta Proveedor'!E:E)),"") -> M.N. DEL GOLFO "HOME CENTER TU ASESOR CONFIABLE" | F52: MATERIAL - VARILLA RECTA #6 3/4X12 M AR-42 | G52: =152-77 -> 75 | H52: =63551.2/152 -> 418.1 | I52: =Imput[[#This Row],[Cantidad]]*Imput[[#This Row],[Precio Unitario]] -> 31357.5 | J52: =((Imput[[#This Row],[Sub total]])*0.16) -> 5017.2 | K52: 0 | L52: =Imput[[#This Row],[Sub total]]+Imput[[#This Row],[IVA]]-Imput[[#This Row],[Retención / IEPS / Descuento]] -> 36374.7 | M52: 0 | N52: Factura | P52: 711A0F15-A5A1-4481-84E5-5FB2756E09D8 | Q52: S004TPV40330034794 | R52: 45841 | S52: 04.- TDC | V52: MATERIAL | W52: MATERIAL CONSTRUCCIÓN
B53: JUL 2025 Q1 | C53: MAN-P4-16 | D53: MNG8612308V8 | E53: =IFERROR(IF(_xlfn.XLOOKUP(Imput[[#This Row],[RFC]],'Alta Proveedor'!D:D,'Alta Proveedor'!E:E)=0,"",_xlfn.XLOOKUP(Imput[[#This Row],[RFC]],'Alta Proveedor'!D:D,'Alta Proveedor'!E:E)),"") -> M.N. DEL GOLFO "HOME CENTER TU ASESOR CONFIABLE" | F53: MATERIAL - VARILLA RECTA #3 3/8X12 M AR-42 | G53: 42 | H53: =11100/111 -> 100 | I53: =Imput[[#This Row],[Cantidad]]*Imput[[#This Row],[Precio Unitario]] -> 4200 | J53: =((Imput[[#This Row],[Sub total]])*0.16) -> 672 | K53: 0 | L53: =Imput[[#This Row],[Sub total]]+Imput[[#This Row],[IVA]]-Imput[[#This Row],[Retención / IEPS / Descuento]] -> 4872 | M53: 0 | N53: Factura | P53: 711A0F15-A5A1-4481-84E5-5FB2756E09D8 | Q53: S004TPV40330034794 | R53: 45841 | S53: 04.- TDC | V53: MATERIAL | W53: MATERIAL CONSTRUCCIÓN
B54: JUL 2025 Q1 | C54: TAM-P4-16 | D54: MNG8612308V8 | E54: =IFERROR(IF(_xlfn.XLOOKUP(Imput[[#This Row],[RFC]],'Alta Proveedor'!D:D,'Alta Proveedor'!E:E)=0,"",_xlfn.XLOOKUP(Imput[[#This Row],[RFC]],'Alta Proveedor'!D:D,'Alta Proveedor'!E:E)),"") -> M.N. DEL GOLFO "HOME CENTER TU ASESOR CONFIABLE" | F54: MATERIAL - VARILLA RECTA #3 3/8X12 M AR-42 | G54: =111-42 -> 69 | H54: =11100/111 -> 100 | I54: =Imput[[#This Row],[Cantidad]]*Imput[[#This Row],[Precio Unitario]] -> 6900 | J54: =((Imput[[#This Row],[Sub total]])*0.16) -> 1104 | K54: 0 | L54: =Imput[[#This Row],[Sub total]]+Imput[[#This Row],[IVA]]-Imput[[#This Row],[Retención / IEPS / Descuento]] -> 8004 | M54: 0 | N54: Factura | P54: 711A0F15-A5A1-4481-84E5-5FB2756E09D8 | Q54: S004TPV40330034794 | R54: 45841 | S54: 04.- TDC | V54: MATERIAL | W54: MATERIAL CONSTRUCCIÓN
B55: JUL 2025 Q1 | C55: TAM-P4-9 | D55: UAGG890111FP7 | E55: =IFERROR(IF(_xlfn.XLOOKUP(Imput[[#This Row],[RFC]],'Alta Proveedor'!D:D,'Alta Proveedor'!E:E)=0,"",_xlfn.XLOOKUP(Imput[[#This Row],[RFC]],'Alta Proveedor'!D:D,'Alta Proveedor'!E:E)),"") -> GUILLERMO UMAÑA GONZALEZ | F55: MATERIAL - 11121616 ‐ Madera de pino 4X4X8 | G55: 2 | H55: 206.895 | I55: =Imput[[#This Row],[Cantidad]]*Imput[[#This Row],[Precio Unitario]] -> 413.79 | J55: =Imput[[#This Row],[Sub total]]*0.16 -> 66.2064 | K55: 0 | L55: =Imput[[#This Row],[Sub total]]+Imput[[#This Row],[IVA]]-Imput[[#This Row],[Retención / IEPS / Descuento]] -> 479.9964 | M55: 479.9964 | N55: Factura | P55: 9A193E9E‐0154‐4F8B‐8161‐1AB0A37AF7F2 | Q55: F ‐ 5692 | R55: 45842 | S55: 04.- TDC | V55: MATERIAL | W55: MATERIAL CONSTRUCCIÓN
B56: JUL 2025 Q1 | C56: TAM-P1-5 | D56: Nomina-OPERACIÓN | E56: =IFERROR(IF(_xlfn.XLOOKUP(Imput[[#This Row],[RFC]],'Alta Proveedor'!D:D,'Alta Proveedor'!E:E)=0,"",_xlfn.XLOOKUP(Imput[[#This Row],[RFC]],'Alta Proveedor'!D:D,'Alta Proveedor'!E:E)),"") -> Nomina-OPERACIÓN | F56: MARIA ISABEL DE ANGEL | PAGO EXCAVACION | G56: 1 | H56: 15000 | I56: =Imput[[#This Row],[Cantidad]]*Imput[[#This Row],[Precio Unitario]] -> 15000 | J56: =Imput[[#This Row],[Sub total]]*0.08 -> 1200 | K56: 0 | L56: =Imput[[#This Row],[Sub total]]+Imput[[#This Row],[IVA]]-Imput[[#This Row],[Retención / IEPS / Descuento]] -> 16200 | M56: 16200 | R56: 45842 | U56: GASTOS SIN FACTURA | V56: NOMINA | W56: EXCAVACIÓN
B57: JUL 2025 Q1 | C57: C1-2 | D57: GASTOS SIN FACTURA | E57: =IFERROR(IF(_xlfn.XLOOKUP(Imput[[#This Row],[RFC]],'Alta Proveedor'!D:D,'Alta Proveedor'!E:E)=0,"",_xlfn.XLOOKUP(Imput[[#This Row],[RFC]],'Alta Proveedor'!D:D,'Alta Proveedor'!E:E)),"") -> GASTOS SIN FACTURA | F57: RAFAEL RODRIGUEZ | | G57: 1 | H57: 25000 | I57: =Imput[[#This Row],[Cantidad]]*Imput[[#This Row],[Precio Unitario]] -> 25000 | J57: =Imput[[#This Row],[Sub total]]*0.08 -> 2000 | K57: 0 | L57: =Imput[[#This Row],[Sub total]]+Imput[[#This Row],[IVA]]-Imput[[#This Row],[Retención / IEPS / Descuento]] -> 27000 | M57: 27000 | R57: 45842 | U57: GASTOS SIN FACTURA | V57: PROVEEDORES | W57: GESTIÓN OBRA
B58: JUL 2025 Q1 | C58: TAM-P9-2 | D58: VARR890902TI7 | E58: =IFERROR(IF(_xlfn.XLOOKUP(Imput[[#This Row],[RFC]],'Alta Proveedor'!D:D,'Alta Proveedor'!E:E)=0,"",_xlfn.XLOOKUP(Imput[[#This Row],[RFC]],'Alta Proveedor'!D:D,'Alta Proveedor'!E:E)),"") -> ROSA FRANCISCA VAZQUEZ RODRIGUEZ | F58: HERRAMIENTA - [7501206613030] PALA REDONDA PUÑO Y PRETUL 22502 | G58: 1 | H58: 188.79 | I58: =Imput[[#This Row],[Cantidad]]*Imput[[#This Row],[Precio Unitario]] -> 188.79 | J58: =Imput[[#This Row],[Sub total]]*0.16 -> 30.2064 | K58: 0 | L58: =Imput[[#This Row],[Sub total]]+Imput[[#This Row],[IVA]]-Imput[[#This Row],[Retención / IEPS / Descuento]] -> 218.9964 | M58: 294.9996 | N58: Factura | P58: 80B8CDD6-60BA-4EB5-8CF1-96104ADC9218 | Q58: 233 | R58: 45845 | S58: 04.- TDC | V58: MATERIAL | W58: MATERIAL CONSTRUCCIÓN
B59: JUL 2025 Q1 | C59: TAM-P9-2 | D59: VARR890902TI7 | E59: =IFERROR(IF(_xlfn.XLOOKUP(Imput[[#This Row],[RFC]],'Alta Proveedor'!D:D,'Alta Proveedor'!E:E)=0,"",_xlfn.XLOOKUP(Imput[[#This Row],[RFC]],'Alta Proveedor'!D:D,'Alta Proveedor'!E:E)),"") -> ROSA FRANCISCA VAZQUEZ RODRIGUEZ | F59: HERRAMIENTA - [7501206684979] ESMALTE EN AEROSOL AZUL ULTRAMAR TRUPER 19041 | G59: 1 | H59: 65.52 | I59: =Imput[[#This Row],[Cantidad]]*Imput[[#This Row],[Precio Unitario]] -> 65.52 | J59: =Imput[[#This Row],[Sub total]]*0.16 -> 10.4832 | K59: 0 | L59: =Imput[[#This Row],[Sub total]]+Imput[[#This Row],[IVA]]-Imput[[#This Row],[Retención / IEPS / Descuento]] -> 76.0032 | M59: 0 | N59: Factura | P59: 80B8CDD6-60BA-4EB5-8CF1-96104ADC9218 | Q59: 233 | R59: 45845 | S59: 04.- TDC | V59: MATERIAL | W59: MATERIAL CONSTRUCCIÓN
B60: JUL 2025 Q1 | C60: TAM-P9-2 | D60: HDM001017AS1 THD-8730 TAMPICO | E60: =IFERROR(IF(_xlfn.XLOOKUP(Imput[[#This Row],[RFC]],'Alta Proveedor'!D:D,'Alta Proveedor'!E:E)=0,"",_xlfn.XLOOKUP(Imput[[#This Row],[RFC]],'Alta Proveedor'!D:D,'Alta Proveedor'!E:E)),"") -> HOME DEPOT MEXICO SUCURSAL THD-8730 TAMPICO | F60: HERRAMIENTA - COMBO ROTO SDS + MINIESMERIL BOSCH (DAÑADO Y DESCONTADO) | G60: 1 | H60: 3885.36 | I60: =Imput[[#This Row],[Cantidad]]*Imput[[#This Row],[Precio Unitario]] -> 3885.36 | J60: =Imput[[#This Row],[Sub total]]*0.16 -> 621.6576 | K60: 0 | L60: =Imput[[#This Row],[Sub total]]+Imput[[#This Row],[IVA]]-Imput[[#This Row],[Retención / IEPS / Descuento]] -> 4507.0176 | M60: 8543.9336 | N60: Factura | P60: 28da0cdb-7571-4923-b7e7-2ee9a8ef96d6 | Q60: 4HGCJI 428444 | R60: 45845 | S60: 04.- TDC | V60: MATERIAL | W60: MATERIAL CONSTRUCCIÓN
B61: JUL 2025 Q1 | C61: TAM-P9-2 | D61: HDM001017AS1 THD-8730 TAMPICO | E61: =IFERROR(IF(_xlfn.XLOOKUP(Imput[[#This Row],[RFC]],'Alta Proveedor'!D:D,'Alta Proveedor'!E:E)=0,"",_xlfn.XLOOKUP(Imput[[#This Row],[RFC]],'Alta Proveedor'!D:D,'Alta Proveedor'!E:E)),"") -> HOME DEPOT MEXICO SUCURSAL THD-8730 TAMPICO | F61: TERMO THD 5 GALONES (EXTRAVIADO) | G61: 1 | H61: 717.26 | I61: =Imput[[#This Row],[Cantidad]]*Imput[[#This Row],[Precio Unitario]] -> 717.26 | J61: =Imput[[#This Row],[Sub total]]*0.16 -> 114.7616 | K61: 0 | L61: =Imput[[#This Row],[Sub total]]+Imput[[#This Row],[IVA]]-Imput[[#This Row],[Retención / IEPS / Descuento]] -> 832.0216 | M61: 0 | N61: Factura | P61: 28da0cdb-7571-4923-b7e7-2ee9a8ef96d6 | Q61: 4HGCJI 428444 | R61: 45845 | S61: 04.- TDC | V61: MATERIAL | W61: COCINA
B62: JUL 2025 Q1 | C62: MAN-P9-2 | D62: HDM001017AS1 THD-8730 TAMPICO | E62: =IFERROR(IF(_xlfn.XLOOKUP(Imput[[#This Row],[RFC]],'Alta Proveedor'!D:D,'Alta Proveedor'!E:E)=0,"",_xlfn.XLOOKUP(Imput[[#This Row],[RFC]],'Alta Proveedor'!D:D,'Alta Proveedor'!E:E)),"") -> HOME DEPOT MEXICO SUCURSAL THD-8730 TAMPICO | F62: HERRAMIENTA - TERMO THD 5 GALONES | G62: 1 | H62: 717.26 | I62: =Imput[[#This Row],[Cantidad]]*Imput[[#This Row],[Precio Unitario]] -> 717.26 | J62: =Imput[[#This Row],[Sub total]]*0.16 -> 114.7616 | K62: 0 | L62: =Imput[[#This Row],[Sub total]]+Imput[[#This Row],[IVA]]-Imput[[#This Row],[Retención / IEPS / Descuento]] -> 832.0216 | M62: 0 | N62: Factura | P62: 28da0cdb-7571-4923-b7e7-2ee9a8ef96d6 | Q62: 4HGCJI 428444 | R62: 45845 | S62: 04.- TDC | V62: MATERIAL | W62: COCINA
B63: JUL 2025 Q1 | C63: TAM-P9-2 | D63: HDM001017AS1 THD-8730 TAMPICO | E63: =IFERROR(IF(_xlfn.XLOOKUP(Imput[[#This Row],[RFC]],'Alta Proveedor'!D:D,'Alta Proveedor'!E:E)=0,"",_xlfn.XLOOKUP(Imput[[#This Row],[RFC]],'Alta Proveedor'!D:D,'Alta Proveedor'!E:E)),"") -> HOME DEPOT MEXICO SUCURSAL THD-8730 TAMPICO | F63: HERRAMIENTA - NIVEL 48 PULG DEWALT | G63: 1 | H63: 1144.74 | I63: =Imput[[#This Row],[Cantidad]]*Imput[[#This Row],[Precio Unitario]] -> 1144.74 | J63: =Imput[[#This Row],[Sub total]]*0.16 -> 183.1584 | K63: 0 | L63: =Imput[[#This Row],[Sub total]]+Imput[[#This Row],[IVA]]-Imput[[#This Row],[Retención / IEPS / Descuento]] -> 1327.8984 | M63: 0 | N63: Factura | P63: 28da0cdb-7571-4923-b7e7-2ee9a8ef96d6 | Q63: 4HGCJI 428444 | R63: 45845 | S63: 04.- TDC | V63: MATERIAL | W63: MATERIAL CONSTRUCCIÓN
B64: JUL 2025 Q1 | C64: TAM-P9-2 | D64: HDM001017AS1 THD-8730 TAMPICO | E64: =IFERROR(IF(_xlfn.XLOOKUP(Imput[[#This Row],[RFC]],'Alta Proveedor'!D:D,'Alta Proveedor'!E:E)=0,"",_xlfn.XLOOKUP(Imput[[#This Row],[RFC]],'Alta Proveedor'!D:D,'Alta Proveedor'!E:E)),"") -> HOME DEPOT MEXICO SUCURSAL THD-8730 TAMPICO | F64: HERRAMIENTA - MARRO TRUPER DE 4 LBS MD-4M | G64: 1 | H64: 258.75 | I64: =Imput[[#This Row],[Cantidad]]*Imput[[#This Row],[Precio Unitario]] -> 258.75 | J64: =Imput[[#This Row],[Sub total]]*0.16 -> 41.4 | K64: 0 | L64: =Imput[[#This Row],[Sub total]]+Imput[[#This Row],[IVA]]-Imput[[#This Row],[Retención / IEPS / Descuento]] -> 300.15 | M64: 0 | N64: Factura | P64: 28da0cdb-7571-4923-b7e7-2ee9a8ef96d6 | Q64: 4HGCJI 428444 | R64: 45845 | S64: 04.- TDC | V64: MATERIAL | W64: MATERIAL CONSTRUCCIÓN
B65: JUL 2025 Q1 | C65: TAM-P9-2 | D65: HDM001017AS1 THD-8730 TAMPICO | E65: =IFERROR(IF(_xlfn.XLOOKUP(Imput[[#This Row],[RFC]],'Alta Proveedor'!D:D,'Alta Proveedor'!E:E)=0,"",_xlfn.XLOOKUP(Imput[[#This Row],[RFC]],'Alta Proveedor'!D:D,'Alta Proveedor'!E:E)),"") -> HOME DEPOT MEXICO SUCURSAL THD-8730 TAMPICO | F65: HERRAMIENTA - EXTENSIÓN USO RUDO 3X16 6m | G65: 1 | H65: 210.36 | I65: =Imput[[#This Row],[Cantidad]]*Imput[[#This Row],[Precio Unitario]] -> 210.36 | J65: =Imput[[#This Row],[Sub total]]*0.16 -> 33.6576 | K65: 0 | L65: =Imput[[#This Row],[Sub total]]+Imput[[#This Row],[IVA]]-Imput[[#This Row],[Retención / IEPS / Descuento]] -> 244.0176 | M65: 0 | N65: Factura | P65: 28da0cdb-7571-4923-b7e7-2ee9a8ef96d6 | Q65: 4HGCJI 428444 | R65: 45845 | S65: 04.- TDC | V65: MATERIAL | W65: MATERIAL CONSTRUCCIÓN
B66: JUL 2025 Q1 | C66: TAM-P9-2 | D66: HDM001017AS1 THD-8730 TAMPICO | E66: =IFERROR(IF(_xlfn.XLOOKUP(Imput[[#This Row],[RFC]],'Alta Proveedor'!D:D,'Alta Proveedor'!E:E)=0,"",_xlfn.XLOOKUP(Imput[[#This Row],[RFC]],'Alta Proveedor'!D:D,'Alta Proveedor'!E:E)),"") -> HOME DEPOT MEXICO SUCURSAL THD-8730 TAMPICO | F66: HERRAMIENTA - PALA REDONDA MGO MADERA 45 HOME DEP | G66: 1 | H66: 162.93 | I66: =Imput[[#This Row],[Cantidad]]*Imput[[#This Row],[Precio Unitario]] -> 162.93 | J66: =(Imput[[#This Row],[Sub total]]-17.24)*0.16 -> 23.3104 | K66: 17.24 | L66: =Imput[[#This Row],[Sub total]]+Imput[[#This Row],[IVA]]-Imput[[#This Row],[Retención / IEPS / Descuento]] -> 169.0004 | M66: 0 | N66: Factura | P66: 28da0cdb-7571-4923-b7e7-2ee9a8ef96d6 | Q66: 4HGCJI 428444 | R66: 45845 | S66: 04.- TDC | V66: MATERIAL | W66: MATERIAL CONSTRUCCIÓN
B67: JUL 2025 Q1 | C67: TAM-P9-2 | D67: HDM001017AS1 THD-8730 TAMPICO | E67: =IFERROR(IF(_xlfn.XLOOKUP(Imput[[#This Row],[RFC]],'Alta Proveedor'!D:D,'Alta Proveedor'!E:E)=0,"",_xlfn.XLOOKUP(Imput[[#This Row],[RFC]],'Alta Proveedor'!D:D,'Alta Proveedor'!E:E)),"") -> HOME DEPOT MEXICO SUCURSAL THD-8730 TAMPICO | F67: HERRAMIENTA - NIVEL TRUPER 18 3 GOTA C/TRN NP-18 | G67: 1 | H67: 108.62 | I67: =Imput[[#This Row],[Cantidad]]*Imput[[#This Row],[Precio Unitario]] -> 108.62 | J67: =Imput[[#This Row],[Sub total]]*0.16 -> 17.3792 | K67: 0 | L67: =Imput[[#This Row],[Sub total]]+Imput[[#This Row],[IVA]]-Imput[[#This Row],[Retención / IEPS / Descuento]] -> 125.9992 | M67: 0 | N67: Factura | P67: 28da0cdb-7571-4923-b7e7-2ee9a8ef96d6 | Q67: 4HGCJI 428444 | R67: 45845 | S67: 04.- TDC | V67: MATERIAL | W67: MATERIAL CONSTRUCCIÓN
B68: JUL 2025 Q1 | C68: TAM-P9-2 | D68: HDM001017AS1 THD-8730 TAMPICO | E68: =IFERROR(IF(_xlfn.XLOOKUP(Imput[[#This Row],[RFC]],'Alta Proveedor'!D:D,'Alta Proveedor'!E:E)=0,"",_xlfn.XLOOKUP(Imput[[#This Row],[RFC]],'Alta Proveedor'!D:D,'Alta Proveedor'!E:E)),"") -> HOME DEPOT MEXICO SUCURSAL THD-8730 TAMPICO | F68: HERRAMIENTA - BROCA BLUE GRANITE 3/8 X 4 X 6 | G68: 1 | H68: 97.16 | I68: =Imput[[#This Row],[Cantidad]]*Imput[[#This Row],[Precio Unitario]] -> 97.16 | J68: =Imput[[#This Row],[Sub total]]*0.16 -> 15.5456 | K68: 0 | L68: =Imput[[#This Row],[Sub total]]+Imput[[#This Row],[IVA]]-Imput[[#This Row],[Retención / IEPS / Descuento]] -> 112.7056 | M68: 0 | N68: Factura | P68: 28da0cdb-7571-4923-b7e7-2ee9a8ef96d6 | Q68: 4HGCJI 428444 | R68: 45845 | S68: 04.- TDC | V68: MATERIAL | W68: MATERIAL CONSTRUCCIÓN
B69: JUL 2025 Q1 | C69: TAM-P4-18 | D69: HDM001017AS1 THD-8730 TAMPICO | E69: =IFERROR(IF(_xlfn.XLOOKUP(Imput[[#This Row],[RFC]],'Alta Proveedor'!D:D,'Alta Proveedor'!E:E)=0,"",_xlfn.XLOOKUP(Imput[[#This Row],[RFC]],'Alta Proveedor'!D:D,'Alta Proveedor'!E:E)),"") -> HOME DEPOT MEXICO SUCURSAL THD-8730 TAMPICO | F69: MATERIAL CONSUMIBLE - PIOLA NYLON TORCIDO 5/64 #36 (99 | G69: 1 | H69: 80.26 | I69: =Imput[[#This Row],[Cantidad]]*Imput[[#This Row],[Precio Unitario]] -> 80.26 | J69: =Imput[[#This Row],[Sub total]]*0.16 -> 12.8416 | K69: 0 | L69: =Imput[[#This Row],[Sub total]]+Imput[[#This Row],[IVA]]-Imput[[#This Row],[Retención / IEPS / Descuento]] -> 93.1016 | M69: 0 | N69: Factura | P69: 28da0cdb-7571-4923-b7e7-2ee9a8ef96d6 | Q69: 4HGCJI 428444 | R69: 45845 | S69: 04.- TDC | V69: MATERIAL | W69: MATERIAL CONSTRUCCIÓN
B70: JUL 2025 Q1 | C70: TAM-P4-4 | D70: MNG8612308V8 | E70: =IFERROR(IF(_xlfn.XLOOKUP(Imput[[#This Row],[RFC]],'Alta Proveedor'!D:D,'Alta Proveedor'!E:E)=0,"",_xlfn.XLOOKUP(Imput[[#This Row],[RFC]],'Alta Proveedor'!D:D,'Alta Proveedor'!E:E)),"") -> M.N. DEL GOLFO "HOME CENTER TU ASESOR CONFIABLE" | F70: MATERIAL - ALAMBRE AMARRE RECOCIDO CAL 16 | G70: 50 | H70: 21.55 | I70: =Imput[[#This Row],[Cantidad]]*Imput[[#This Row],[Precio Unitario]] -> 1077.5 | J70: =((Imput[[#This Row],[Sub total]])*0.16) -> 172.4 | K70: 0 | L70: =Imput[[#This Row],[Sub total]]+Imput[[#This Row],[IVA]]-Imput[[#This Row],[Retención / IEPS / Descuento]] -> 1249.9 | M70: 1249.9 | N70: Factura | P70: EC2D7ECB-EECC-4B53-AEB6-EF2FBDCF7AD4 | Q70: S003TPV30320053526 | R70: 45845 | S70: 04.- TDC | V70: MATERIAL | W70: MATERIAL CONSTRUCCIÓN
B71: JUL 2025 Q1 | C71: C6-13 | D71: FCU220209NQ1 | E71: =IFERROR(IF(_xlfn.XLOOKUP(Imput[[#This Row],[RFC]],'Alta Proveedor'!D:D,'Alta Proveedor'!E:E)=0,"",_xlfn.XLOOKUP(Imput[[#This Row],[RFC]],'Alta Proveedor'!D:D,'Alta Proveedor'!E:E)),"") -> FERRETERIA CUERVO SA DE CV | F71: SEGURIDAD - CONO DE SEGURIDAD 45 CM | G71: 4 | H71: 150.97 | I71: =Imput[[#This Row],[Cantidad]]*Imput[[#This Row],[Precio Unitario]] -> 603.88 | J71: =Imput[[#This Row],[Sub total]]*0.16 -> 96.6208 | K71: 0 | L71: =Imput[[#This Row],[Sub total]]+Imput[[#This Row],[IVA]]-Imput[[#This Row],[Retención / IEPS / Descuento]] -> 700.5008 | M71: 1062.4904 | N71: Factura | P71: A4CFACE6‐996F‐40E1‐972E‐46F562367E81 | Q71: A ‐ 6166 | R71: 45846 | S71: 04.- TDC | V71: MATERIAL | W71: EPP
B72: JUL 2025 Q1 | C72: TAM-P4-18 | D72: FCU220209NQ1 | E72: =IFERROR(IF(_xlfn.XLOOKUP(Imput[[#This Row],[RFC]],'Alta Proveedor'!D:D,'Alta Proveedor'!E:E)=0,"",_xlfn.XLOOKUP(Imput[[#This Row],[RFC]],'Alta Proveedor'!D:D,'Alta Proveedor'!E:E)),"") -> FERRETERIA CUERVO SA DE CV | F72: MATERIAL CONSUMIBLE - MARCADOR DE VALVULA FIELTRO AMARILLO | G72: 4 | H72: 66.59 | I72: =Imput[[#This Row],[Cantidad]]*Imput[[#This Row],[Precio Unitario]] -> 266.36 | J72: =Imput[[#This Row],[Sub total]]*0.16 -> 42.6176 | K72: 0 | L72: =Imput[[#This Row],[Sub total]]+Imput[[#This Row],[IVA]]-Imput[[#This Row],[Retención / IEPS / Descuento]] -> 308.9776 | M72: 0 | N72: Factura | P72: A4CFACE6‐996F‐40E1‐972E‐46F562367E81 | Q72: A ‐ 6166 | R72: 45846 | S72: 04.- TDC | V72: MATERIAL | W72: MATERIAL CONSTRUCCIÓN
B73: JUL 2025 Q1 | C73: TAM-P4-18 | D73: FCU220209NQ1 | E73: =IFERROR(IF(_xlfn.XLOOKUP(Imput[[#This Row],[RFC]],'Alta Proveedor'!D:D,'Alta Proveedor'!E:E)=0,"",_xlfn.XLOOKUP(Imput[[#This Row],[RFC]],'Alta Proveedor'!D:D,'Alta Proveedor'!E:E)),"") -> FERRETERIA CUERVO SA DE CV | F73: MATERIAL CONSUMIBLE - MARCADOR PARA METAL "TIZA" BASE JABON | G73: 5 | H73: 9.14 | I73: =Imput[[#This Row],[Cantidad]]*Imput[[#This Row],[Precio Unitario]] -> 45.7 | J73: =Imput[[#This Row],[Sub total]]*0.16 -> 7.312 | K73: 0 | L73: =Imput[[#This Row],[Sub total]]+Imput[[#This Row],[IVA]]-Imput[[#This Row],[Retención / IEPS / Descuento]] -> 53.012 | M73: 0 | N73: Factura | P73: A4CFACE6‐996F‐40E1‐972E‐46F562367E81 | Q73: A ‐ 6166 | R73: 45846 | S73: 04.- TDC | V73: MATERIAL | W73: MATERIAL CONSTRUCCIÓN
B74: JUL 2025 Q1 | C74: TAM-P4-10 | D74: HDM001017AS1 THD-8730 TAMPICO | E74: =IFERROR(IF(_xlfn.XLOOKUP(Imput[[#This Row],[RFC]],'Alta Proveedor'!D:D,'Alta Proveedor'!E:E)=0,"",_xlfn.XLOOKUP(Imput[[#This Row],[RFC]],'Alta Proveedor'!D:D,'Alta Proveedor'!E:E)),"") -> HOME DEPOT MEXICO SUCURSAL THD-8730 TAMPICO | F74: SEGURIDAD - MALLA DE CONSTRUCCION PERIMETRAL 30 | G74: 7 | H74: 244.138 | I74: =Imput[[#This Row],[Cantidad]]*Imput[[#This Row],[Precio Unitario]] -> 1708.966 | J74: =Imput[[#This Row],[Sub total]]*0.16 -> 273.43456 | K74: 0 | L74: =Imput[[#This Row],[Sub total]]+Imput[[#This Row],[IVA]]-Imput[[#This Row],[Retención / IEPS / Descuento]] -> 1982.4006 | M74: 2705.3961 | N74: Factura | P74: 6bd44d61-d9f1-49b3-9e2d-1ca40ed5ee83 | Q74: 4HGCJI 428986 | R74: 45847 | S74: 04.- TDC | V74: MATERIAL | W74: MATERIAL CONSTRUCCIÓN
B75: JUL 2025 Q1 | C75: TAM-P9-2 | D75: HDM001017AS1 THD-8730 TAMPICO | E75: =IFERROR(IF(_xlfn.XLOOKUP(Imput[[#This Row],[RFC]],'Alta Proveedor'!D:D,'Alta Proveedor'!E:E)=0,"",_xlfn.XLOOKUP(Imput[[#This Row],[RFC]],'Alta Proveedor'!D:D,'Alta Proveedor'!E:E)),"") -> HOME DEPOT MEXICO SUCURSAL THD-8730 TAMPICO | F75: HERRAMIENTA - BARRETA HEXAGONAL PUNTA 1 X 1.5 MT | G75: 1 | H75: 445.472 | I75: =Imput[[#This Row],[Cantidad]]*Imput[[#This Row],[Precio Unitario]] -> 445.472 | J75: =Imput[[#This Row],[Sub total]]*0.16 -> 71.27552 | K75: 0 | L75: =Imput[[#This Row],[Sub total]]+Imput[[#This Row],[IVA]]-Imput[[#This Row],[Retención / IEPS / Descuento]] -> 516.74752 | M75: 0 | N75: Factura | P75: 6bd44d61-d9f1-49b3-9e2d-1ca40ed5ee83 | Q75: 4HGCJI 428986 | R75: 45847 | S75: 04.- TDC | V75: MATERIAL | W75: MATERIAL CONSTRUCCIÓN
B76: JUL 2025 Q1 | C76: TAM-P9-2 | D76: HDM001017AS1 THD-8730 TAMPICO | E76: =IFERROR(IF(_xlfn.XLOOKUP(Imput[[#This Row],[RFC]],'Alta Proveedor'!D:D,'Alta Proveedor'!E:E)=0,"",_xlfn.XLOOKUP(Imput[[#This Row],[RFC]],'Alta Proveedor'!D:D,'Alta Proveedor'!E:E)),"") -> HOME DEPOT MEXICO SUCURSAL THD-8730 TAMPICO | F76: HERRAMIENTA - BARRA HEX UNA 3/4 X 0.75 MT BU-75 | G76: 1 | H76: 177.8 | I76: =Imput[[#This Row],[Cantidad]]*Imput[[#This Row],[Precio Unitario]] -> 177.8 | J76: =Imput[[#This Row],[Sub total]]*0.16 -> 28.448 | K76: 0 | L76: =Imput[[#This Row],[Sub total]]+Imput[[#This Row],[IVA]]-Imput[[#This Row],[Retención / IEPS / Descuento]] -> 206.248 | M76: 0 | N76: Factura | P76: 6bd44d61-d9f1-49b3-9e2d-1ca40ed5ee83 | Q76: 4HGCJI 428986 | R76: 45847 | S76: 04.- TDC | V76: MATERIAL | W76: MATERIAL CONSTRUCCIÓN
B77: JUL 2025 Q1 | C77: C2-7 | D77: GCT9902117L0 | E77: =IFERROR(IF(_xlfn.XLOOKUP(Imput[[#This Row],[RFC]],'Alta Proveedor'!D:D,'Alta Proveedor'!E:E)=0,"",_xlfn.XLOOKUP(Imput[[#This Row],[RFC]],'Alta Proveedor'!D:D,'Alta Proveedor'!E:E)),"") -> GASOLINERA DE COLONIAS DE TAMPICO E05695 (COMBUSTIBLES) | F77: COMBUSTIBLE - MAGNA | G77: 21.834 | H77: 19.820005 | I77: =Imput[[#This Row],[Cantidad]]*Imput[[#This Row],[Precio Unitario]] -> 432.75 | J77: 67.25 | K77: 0 | L77: =Imput[[#This Row],[Sub total]]+Imput[[#This Row],[IVA]]-Imput[[#This Row],[Retención / IEPS / Descuento]] -> 500 | M77: 500 | N77: Factura | P77: b51a8294-bcb8-48a4-890c-bfde0a7290a6 | Q77: CLNC 53981 | R77: 45847 | S77: 04.- TDC | V77: COMBUSTIBLES | W77: GASOLINA
B78: JUL 2025 Q1 | C78: TAM-P2-2 | D78: MAPM55011994A | E78: =IFERROR(IF(_xlfn.XLOOKUP(Imput[[#This Row],[RFC]],'Alta Proveedor'!D:D,'Alta Proveedor'!E:E)=0,"",_xlfn.XLOOKUP(Imput[[#This Row],[RFC]],'Alta Proveedor'!D:D,'Alta Proveedor'!E:E)),"") -> MARIO MARIN PERALES "FABRICACIONES METALICAS ESPECIALES" | F78: RENTAS - 4 DIAS DE RENTA DE GENERADOR CON ROMPEDORA | G78: 1 | H78: 3200 | I78: =Imput[[#This Row],[Cantidad]]*Imput[[#This Row],[Precio Unitario]] -> 3200 | J78: =Imput[[#This Row],[Sub total]]*0.16 -> 512 | K78: 0 | L78: =Imput[[#This Row],[Sub total]]+Imput[[#This Row],[IVA]]-Imput[[#This Row],[Retención / IEPS / Descuento]] -> 3712 | M78: 6670 | N78: Factura | P78: 774701C9-42E7-4BC4-B69D-FF4BF9BE41CE | Q78: F 1002 | R78: 45847 | S78: 03.- Transferencia | V78: PROVEEDORES | W78: MAQUINARIA
B79: JUL 2025 Q1 | C79: TAM-P2-1 | D79: MAPM55011994A | E79: =IFERROR(IF(_xlfn.XLOOKUP(Imput[[#This Row],[RFC]],'Alta Proveedor'!D:D,'Alta Proveedor'!E:E)=0,"",_xlfn.XLOOKUP(Imput[[#This Row],[RFC]],'Alta Proveedor'!D:D,'Alta Proveedor'!E:E)),"") -> MARIO MARIN PERALES "FABRICACIONES METALICAS ESPECIALES" | F79: RENTAS - 3 DIAS DE RENTA DE CORTADORA DE CONCRETO | G79: 1 | H79: 2550 | I79: =Imput[[#This Row],[Cantidad]]*Imput[[#This Row],[Precio Unitario]] -> 2550 | J79: =Imput[[#This Row],[Sub total]]*0.16 -> 408 | K79: 0 | L79: =Imput[[#This Row],[Sub total]]+Imput[[#This Row],[IVA]]-Imput[[#This Row],[Retención / IEPS / Descuento]] -> 2958 | M79: 0 | N79: Factura | P79: 774701C9-42E7-4BC4-B69D-FF4BF9BE41CE | Q79: F 1002 | R79: 45847 | S79: 03.- Transferencia | V79: PROVEEDORES | W79: MAQUINARIA
B80: JUL 2025 Q1 | C80: TAM-P4-12 | D80: HDM001017AS1 THD-8730 TAMPICO | E80: =IFERROR(IF(_xlfn.XLOOKUP(Imput[[#This Row],[RFC]],'Alta Proveedor'!D:D,'Alta Proveedor'!E:E)=0,"",_xlfn.XLOOKUP(Imput[[#This Row],[RFC]],'Alta Proveedor'!D:D,'Alta Proveedor'!E:E)),"") -> HOME DEPOT MEXICO SUCURSAL THD-8730 TAMPICO | F80: SEGURIDAD - CONO REFORZADO DE 71 CMS | G80: 6 | H80: =1701.72/6 -> 283.62 | I80: =Imput[[#This Row],[Cantidad]]*Imput[[#This Row],[Precio Unitario]] -> 1701.72 | J80: =((Imput[[#This Row],[Sub total]])*(0.16)) -> 272.2752 | K80: 0 | L80: =Imput[[#This Row],[Sub total]]+Imput[[#This Row],[IVA]]-Imput[[#This Row],[Retención / IEPS / Descuento]] -> 1973.9952 | M80: 5398.002 | N80: Factura | P80: 24e079f6-2228-4154-ba48-fa703db17c50 | Q80: 4HGCJI 429803 | R80: 45848 | S80: 04.- TDC | V80: MATERIAL | W80: EPP
B81: JUL 2025 Q1 | C81: TAM-P9-2 | D81: HDM001017AS1 THD-8730 TAMPICO | E81: =IFERROR(IF(_xlfn.XLOOKUP(Imput[[#This Row],[RFC]],'Alta Proveedor'!D:D,'Alta Proveedor'!E:E)=0,"",_xlfn.XLOOKUP(Imput[[#This Row],[RFC]],'Alta Proveedor'!D:D,'Alta Proveedor'!E:E)),"") -> HOME DEPOT MEXICO SUCURSAL THD-8730 TAMPICO | F81: HERRAMIENTA - CAVADOR REFORZADO TRUPER CA-38F | G81: 2 | H81: =1474.14/2 -> 737.07 | I81: =Imput[[#This Row],[Cantidad]]*Imput[[#This Row],[Precio Unitario]] -> 1474.14 | J81: =((Imput[[#This Row],[Sub total]])*(0.16)) -> 235.8624 | K81: 0 | L81: =Imput[[#This Row],[Sub total]]+Imput[[#This Row],[IVA]]-Imput[[#This Row],[Retención / IEPS / Descuento]] -> 1710.0024 | M81: 0 | N81: Factura | P81: 24e079f6-2228-4154-ba48-fa703db17c50 | Q81: 4HGCJI 429803 | R81: 45848 | S81: 04.- TDC | V81: MATERIAL | W81: MATERIAL CONSTRUCCIÓN
B82: JUL 2025 Q1 | C82: TAM-P9-2 | D82: HDM001017AS1 THD-8730 TAMPICO | E82: =IFERROR(IF(_xlfn.XLOOKUP(Imput[[#This Row],[RFC]],'Alta Proveedor'!D:D,'Alta Proveedor'!E:E)=0,"",_xlfn.XLOOKUP(Imput[[#This Row],[RFC]],'Alta Proveedor'!D:D,'Alta Proveedor'!E:E)),"") -> HOME DEPOT MEXICO SUCURSAL THD-8730 TAMPICO | F82: HERRAMIENTA - LUMINARIO EMERGENCIA PANIC 1+24 LED | G82: 2 | H82: =1377.59/2 -> 688.795 | I82: =Imput[[#This Row],[Cantidad]]*Imput[[#This Row],[Precio Unitario]] -> 1377.59 | J82: =((Imput[[#This Row],[Sub total]])*(0.16)) -> 220.4144 | K82: 0 | L82: =Imput[[#This Row],[Sub total]]+Imput[[#This Row],[IVA]]-Imput[[#This Row],[Retención / IEPS / Descuento]] -> 1598.0044 | M82: 0 | N82: Factura | P82: 24e079f6-2228-4154-ba48-fa703db17c50 | Q82: 4HGCJI 429803 | R82: 45848 | S82: 04.- TDC | V82: MATERIAL | W82: EPP
B83: JUL 2025 Q1 | C83: TAM-P4-18 | D83: HDM001017AS1 THD-8730 TAMPICO | E83: =IFERROR(IF(_xlfn.XLOOKUP(Imput[[#This Row],[RFC]],'Alta Proveedor'!D:D,'Alta Proveedor'!E:E)=0,"",_xlfn.XLOOKUP(Imput[[#This Row],[RFC]],'Alta Proveedor'!D:D,'Alta Proveedor'!E:E)),"") -> HOME DEPOT MEXICO SUCURSAL THD-8730 TAMPICO | F83: MATERIAL CONSUMIBLE - CINCHO PARA CABLE DE 3.5 X 100 MM B | G83: 4 | H83: =100/4 -> 25 | I83: =Imput[[#This Row],[Cantidad]]*Imput[[#This Row],[Precio Unitario]] -> 100 | J83: =((Imput[[#This Row],[Sub total]])*(0.16)) -> 16 | K83: 0 | L83: =Imput[[#This Row],[Sub total]]+Imput[[#This Row],[IVA]]-Imput[[#This Row],[Retención / IEPS / Descuento]] -> 116 | M83: 0 | N83: Factura | P83: 24e079f6-2228-4154-ba48-fa703db17c50 | Q83: 4HGCJI 429803 | R83: 45848 | S83: 04.- TDC | V83: MATERIAL | W83: MATERIAL CONSTRUCCIÓN
B84: JUL 2025 Q1 | C84: TAM-P4-7 | D84: CHU841123AR6 | E84: =IFERROR(IF(_xlfn.XLOOKUP(Imput[[#This Row],[RFC]],'Alta Proveedor'!D:D,'Alta Proveedor'!E:E)=0,"",_xlfn.XLOOKUP(Imput[[#This Row],[RFC]],'Alta Proveedor'!D:D,'Alta Proveedor'!E:E)),"") -> CONCRETOS HUASTECA | F84: MATERIAL - CONCRETO | G84: 1 | H84: 15138 | I84: =Imput[[#This Row],[Cantidad]]*Imput[[#This Row],[Precio Unitario]] -> 15138 | J84: 0 | K84: 0 | L84: =Imput[[#This Row],[Sub total]]+Imput[[#This Row],[IVA]]-Imput[[#This Row],[Retención / IEPS / Descuento]] -> 15138 | M84: 15138 | P84: =Imput[[#This Row],[Folio]] -> 8762 | Q84: 8762 | R84: 45849 | U84: ARCHIVO BRENDA NO TENGO FACTURA | V84: MATERIAL | W84: MATERIAL CONSTRUCCIÓN
B85: JUL 2025 Q1 | C85: C2-7 | D85: SSO151204615 | E85: =IFERROR(IF(_xlfn.XLOOKUP(Imput[[#This Row],[RFC]],'Alta Proveedor'!D:D,'Alta Proveedor'!E:E)=0,"",_xlfn.XLOOKUP(Imput[[#This Row],[RFC]],'Alta Proveedor'!D:D,'Alta Proveedor'!E:E)),"") -> SERVICIOS SOLEY "EXELGAS" (COMBUSTIBLES) | F85: COMBUSTIBLE - MAGNA | G85: 22.855 | H85: 20.337344 | I85: =Imput[[#This Row],[Cantidad]]*Imput[[#This Row],[Precio Unitario]] -> 464.81 | J85: 72.28 | K85: 0 | L85: =Imput[[#This Row],[Sub total]]+Imput[[#This Row],[IVA]]-Imput[[#This Row],[Retención / IEPS / Descuento]] -> 537.09 | M85: 537.09 | N85: Factura | P85: 8D740ED6-A107-410A-9CB0-79BC8D864C26 | Q85: X9W - 6628 | R85: 45849 | S85: 04.- TDC | V85: COMBUSTIBLES | W85: GASOLINA
B86: JUL 2025 Q1 | C86: TAM-P1-5 | D86: Nomina-OPERACIÓN | E86: =IFERROR(IF(_xlfn.XLOOKUP(Imput[[#This Row],[RFC]],'Alta Proveedor'!D:D,'Alta Proveedor'!E:E)=0,"",_xlfn.XLOOKUP(Imput[[#This Row],[RFC]],'Alta Proveedor'!D:D,'Alta Proveedor'!E:E)),"") -> Nomina-OPERACIÓN | F86: EDGAR FRANCISCO FRANCO | ABONO ESTIMACION 1 | G86: 1 | H86: 3000 | I86: =Imput[[#This Row],[Cantidad]]*Imput[[#This Row],[Precio Unitario]] -> 3000 | J86: =Imput[[#This Row],[Sub total]]*0.08 -> 240 | K86: 0 | L86: =Imput[[#This Row],[Sub total]]+Imput[[#This Row],[IVA]]-Imput[[#This Row],[Retención / IEPS / Descuento]] -> 3240 | M86: 3240 | R86: 45849 | U86: GASTOS SIN FACTURA | V86: NOMINA | W86: EXCAVACIÓN
B87: JUL 2025 Q1 | C87: TAM-P9-2 | D87: HDM001017AS1 THD-8730 TAMPICO | E87: =IFERROR(IF(_xlfn.XLOOKUP(Imput[[#This Row],[RFC]],'Alta Proveedor'!D:D,'Alta Proveedor'!E:E)=0,"",_xlfn.XLOOKUP(Imput[[#This Row],[RFC]],'Alta Proveedor'!D:D,'Alta Proveedor'!E:E)),"") -> HOME DEPOT MEXICO SUCURSAL THD-8730 TAMPICO | F87: HERRAMIENTA - SIERRA CIRCULAR BOSCH 7 1/4 (EXTRAVIADA) | G87: 1 | H87: 2307.09 | I87: =Imput[[#This Row],[Cantidad]]*Imput[[#This Row],[Precio Unitario]] -> 2307.09 | J87: =Imput[[#This Row],[Sub total]]*0.16 -> 369.1344 | K87: 0 | L87: =Imput[[#This Row],[Sub total]]+Imput[[#This Row],[IVA]]-Imput[[#This Row],[Retención / IEPS / Descuento]] -> 2676.2244 | M87: 5790.488 | N87: Factura | P87: 25a1f408-390d-46dd-add0-69eb95df3a19 | Q87: 4HGCJI 430521 | R87: 45850 | S87: 04.- TDC | V87: MATERIAL | W87: MATERIAL CONSTRUCCIÓN
B88: JUL 2025 Q1 | C88: TAM-P4-9 | D88: HDM001017AS1 THD-8730 TAMPICO | E88: =IFERROR(IF(_xlfn.XLOOKUP(Imput[[#This Row],[RFC]],'Alta Proveedor'!D:D,'Alta Proveedor'!E:E)=0,"",_xlfn.XLOOKUP(Imput[[#This Row],[RFC]],'Alta Proveedor'!D:D,'Alta Proveedor'!E:E)),"") -> HOME DEPOT MEXICO SUCURSAL THD-8730 TAMPICO | F88: MATERIAL - POLIN DE PINO PARA CIMBRA | G88: 12 | H88: =1294.24/12 -> 107.85333 | I88: =Imput[[#This Row],[Cantidad]]*Imput[[#This Row],[Precio Unitario]] -> 1294.24 | J88: =Imput[[#This Row],[Sub total]]*0.16 -> 207.0784 | K88: 0 | L88: =Imput[[#This Row],[Sub total]]+Imput[[#This Row],[IVA]]-Imput[[#This Row],[Retención / IEPS / Descuento]] -> 1501.3184 | M88: 0 | N88: Factura | P88: 25a1f408-390d-46dd-add0-69eb95df3a19 | Q88: 4HGCJI 430521 | R88: 45850 | S88: 04.- TDC | V88: MATERIAL | W88: MATERIAL CONSTRUCCIÓN
B89: JUL 2025 Q1 | C89: TAM-P9-2 | D89: HDM001017AS1 THD-8730 TAMPICO | E89: =IFERROR(IF(_xlfn.XLOOKUP(Imput[[#This Row],[RFC]],'Alta Proveedor'!D:D,'Alta Proveedor'!E:E)=0,"",_xlfn.XLOOKUP(Imput[[#This Row],[RFC]],'Alta Proveedor'!D:D,'Alta Proveedor'!E:E)),"") -> HOME DEPOT MEXICO SUCURSAL THD-8730 TAMPICO | F89: HERRAMIENTA - AMARRE MATRACA 8.2M X 1511KG PLANO | G89: 3 | H89: =799.14/3 -> 266.38 | I89: =Imput[[#This Row],[Cantidad]]*Imput[[#This Row],[Precio Unitario]] -> 799.14 | J89: =((Imput[[#This Row],[Sub total]]-243.11)*0.16) -> 88.9648 | K89: 243.11 | L89: =Imput[[#This Row],[Sub total]]+Imput[[#This Row],[IVA]]-Imput[[#This Row],[Retención / IEPS / Descuento]] -> 644.9948 | M89: 0 | N89: Factura | P89: 25a1f408-390d-46dd-add0-69eb95df3a19 | Q89: 4HGCJI 430521 | R89: 45850 | S89: 04.- TDC | V89: MATERIAL | W89: MATERIAL CONSTRUCCIÓN
B90: JUL 2025 Q1 | C90: TAM-P9-2 | D90: HDM001017AS1 THD-8730 TAMPICO | E90: =IFERROR(IF(_xlfn.XLOOKUP(Imput[[#This Row],[RFC]],'Alta Proveedor'!D:D,'Alta Proveedor'!E:E)=0,"",_xlfn.XLOOKUP(Imput[[#This Row],[RFC]],'Alta Proveedor'!D:D,'Alta Proveedor'!E:E)),"") -> HOME DEPOT MEXICO SUCURSAL THD-8730 TAMPICO | F90: HERRAMIENTA - DISCO PARA SIERRA P/MADERA 7 1/4 4 | G90: 1 | H90: 367.5 | I90: =Imput[[#This Row],[Cantidad]]*Imput[[#This Row],[Precio Unitario]] -> 367.5 | J90: =Imput[[#This Row],[Sub total]]*0.16 -> 58.8 | K90: 0 | L90: =Imput[[#This Row],[Sub total]]+Imput[[#This Row],[IVA]]-Imput[[#This Row],[Retención / IEPS / Descuento]] -> 426.3 | M90: 0 | N90: Factura | P90: 25a1f408-390d-46dd-add0-69eb95df3a19 | Q90: 4HGCJI 430521 | R90: 45850 | S90: 04.- TDC | V90: MATERIAL | W90: MATERIAL CONSTRUCCIÓN
B91: JUL 2025 Q1 | C91: TAM-P9-2 | D91: HDM001017AS1 THD-8730 TAMPICO | E91: =IFERROR(IF(_xlfn.XLOOKUP(Imput[[#This Row],[RFC]],'Alta Proveedor'!D:D,'Alta Proveedor'!E:E)=0,"",_xlfn.XLOOKUP(Imput[[#This Row],[RFC]],'Alta Proveedor'!D:D,'Alta Proveedor'!E:E)),"") -> HOME DEPOT MEXICO SUCURSAL THD-8730 TAMPICO | F91: HERRAMIENTA - AMARRE MATRACA 8.2M X 1511KG JJ | G91: 1 | H91: 300.86 | I91: =Imput[[#This Row],[Cantidad]]*Imput[[#This Row],[Precio Unitario]] -> 300.86 | J91: =((Imput[[#This Row],[Sub total]]-89.65)*0.16) -> 33.7936 | K91: 89.65 | L91: =Imput[[#This Row],[Sub total]]+Imput[[#This Row],[IVA]]-Imput[[#This Row],[Retención / IEPS / Descuento]] -> 245.0036 | M91: 0 | N91: Factura | P91: 25a1f408-390d-46dd-add0-69eb95df3a19 | Q91: 4HGCJI 430521 | R91: 45850 | S91: 04.- TDC | V91: MATERIAL | W91: MATERIAL CONSTRUCCIÓN
B92: JUL 2025 Q1 | C92: TAM-P4-18 | D92: HDM001017AS1 THD-8730 TAMPICO | E92: =IFERROR(IF(_xlfn.XLOOKUP(Imput[[#This Row],[RFC]],'Alta Proveedor'!D:D,'Alta Proveedor'!E:E)=0,"",_xlfn.XLOOKUP(Imput[[#This Row],[RFC]],'Alta Proveedor'!D:D,'Alta Proveedor'!E:E)),"") -> HOME DEPOT MEXICO SUCURSAL THD-8730 TAMPICO | F92: MATERIAL CONSUMIBLE - CLAVO 4 PARA MADERA 10kg | G92: 1 | H92: 255.73 | I92: =Imput[[#This Row],[Cantidad]]*Imput[[#This Row],[Precio Unitario]] -> 255.73 | J92: =Imput[[#This Row],[Sub total]]*0.16 -> 40.9168 | K92: 0 | L92: =Imput[[#This Row],[Sub total]]+Imput[[#This Row],[IVA]]-Imput[[#This Row],[Retención / IEPS / Descuento]] -> 296.6468 | M92: 0 | N92: Factura | P92: 25a1f408-390d-46dd-add0-69eb95df3a19 | Q92: 4HGCJI 430521 | R92: 45850 | S92: 04.- TDC | V92: MATERIAL | W92: MATERIAL CONSTRUCCIÓN
B93: JUL 2025 Q1 | C93: TAM-P1-4 | D93: Nomina-OPERACIÓN | E93: =IFERROR(IF(_xlfn.XLOOKUP(Imput[[#This Row],[RFC]],'Alta Proveedor'!D:D,'Alta Proveedor'!E:E)=0,"",_xlfn.XLOOKUP(Imput[[#This Row],[RFC]],'Alta Proveedor'!D:D,'Alta Proveedor'!E:E)),"") -> Nomina-OPERACIÓN | F93: YULIANA DEL ANGEL FONG | NOMINA FIERREROS | G93: 1 | H93: 24500 | I93: =Imput[[#This Row],[Cantidad]]*Imput[[#This Row],[Precio Unitario]] -> 24500 | J93: =Imput[[#This Row],[Sub total]]*0.08 -> 1960 | K93: 0 | L93: =Imput[[#This Row],[Sub total]]+Imput[[#This Row],[IVA]]-Imput[[#This Row],[Retención / IEPS / Descuento]] -> 26460 | M93: 26460 | R93: 45850 | U93: GASTOS SIN FACTURA | V93: NOMINA | W93: FIERREROS
B94: JUL 2025 Q1 | C94: TAM-P1-5 | D94: Nomina-OPERACIÓN | E94: =IFERROR(IF(_xlfn.XLOOKUP(Imput[[#This Row],[RFC]],'Alta Proveedor'!D:D,'Alta Proveedor'!E:E)=0,"",_xlfn.XLOOKUP(Imput[[#This Row],[RFC]],'Alta Proveedor'!D:D,'Alta Proveedor'!E:E)),"") -> Nomina-OPERACIÓN | F94: YULIANA DEL ANGEL FONG | EXCAVACION | G94: 1 | H94: 2400 | I94: =Imput[[#This Row],[Cantidad]]*Imput[[#This Row],[Precio Unitario]] -> 2400 | J94: =Imput[[#This Row],[Sub total]]*0.08 -> 192 | K94: 0 | L94: =Imput[[#This Row],[Sub total]]+Imput[[#This Row],[IVA]]-Imput[[#This Row],[Retención / IEPS / Descuento]] -> 2592 | M94: 2592 | R94: 45850 | U94: GASTOS SIN FACTURA | V94: NOMINA | W94: EXCAVACIÓN
B95: JUL 2025 Q1 | C95: TAM-P1-5 | D95: Nomina-OPERACIÓN | E95: =IFERROR(IF(_xlfn.XLOOKUP(Imput[[#This Row],[RFC]],'Alta Proveedor'!D:D,'Alta Proveedor'!E:E)=0,"",_xlfn.XLOOKUP(Imput[[#This Row],[RFC]],'Alta Proveedor'!D:D,'Alta Proveedor'!E:E)),"") -> Nomina-OPERACIÓN | F95: MARIA ISABEL DE ANGEL | ABONO 2 | G95: 1 | H95: 5000 | I95: =Imput[[#This Row],[Cantidad]]*Imput[[#This Row],[Precio Unitario]] -> 5000 | J95: =Imput[[#This Row],[Sub total]]*0.08 -> 400 | K95: 0 | L95: =Imput[[#This Row],[Sub total]]+Imput[[#This Row],[IVA]]-Imput[[#This Row],[Retención / IEPS / Descuento]] -> 5400 | M95: 5400 | R95: 45850 | U95: GASTOS SIN FACTURA | V95: NOMINA | W95: EXCAVACIÓN
B96: JUL 2025 Q1 | C96: TAM-P1-5 | D96: Nomina-OPERACIÓN | E96: =IFERROR(IF(_xlfn.XLOOKUP(Imput[[#This Row],[RFC]],'Alta Proveedor'!D:D,'Alta Proveedor'!E:E)=0,"",_xlfn.XLOOKUP(Imput[[#This Row],[RFC]],'Alta Proveedor'!D:D,'Alta Proveedor'!E:E)),"") -> Nomina-OPERACIÓN | F96: EDGAR FRANCISCO FRANCO | ABONO 2 ESTIMACION 1 | G96: 1 | H96: 1600 | I96: =Imput[[#This Row],[Cantidad]]*Imput[[#This Row],[Precio Unitario]] -> 1600 | J96: =Imput[[#This Row],[Sub total]]*0.08 -> 128 | K96: 0 | L96: =Imput[[#This Row],[Sub total]]+Imput[[#This Row],[IVA]]-Imput[[#This Row],[Retención / IEPS / Descuento]] -> 1728 | M96: 1728 | R96: 45850 | U96: GASTOS SIN FACTURA | V96: NOMINA | W96: EXCAVACIÓN
B97: JUL 2025 Q1 | C97: TAM-P1-5 | D97: Nomina-OPERACIÓN | E97: =IFERROR(IF(_xlfn.XLOOKUP(Imput[[#This Row],[RFC]],'Alta Proveedor'!D:D,'Alta Proveedor'!E:E)=0,"",_xlfn.XLOOKUP(Imput[[#This Row],[RFC]],'Alta Proveedor'!D:D,'Alta Proveedor'!E:E)),"") -> Nomina-OPERACIÓN | F97: MARIA ISABEL DE ANGEL | ABONO 3 | G97: 1 | H97: 20000 | I97: =Imput[[#This Row],[Cantidad]]*Imput[[#This Row],[Precio Unitario]] -> 20000 | J97: =Imput[[#This Row],[Sub total]]*0.08 -> 1600 | K97: 0 | L97: =Imput[[#This Row],[Sub total]]+Imput[[#This Row],[IVA]]-Imput[[#This Row],[Retención / IEPS / Descuento]] -> 21600 | M97: 21600 | R97: 45851 | U97: GASTOS SIN FACTURA | V97: NOMINA | W97: EXCAVACIÓN
B98: JUL 2025 Q1 | C98: C2-9 | D98: CCO8605231N4 | E98: =IFERROR(IF(_xlfn.XLOOKUP(Imput[[#This Row],[RFC]],'Alta Proveedor'!D:D,'Alta Proveedor'!E:E)=0,"",_xlfn.XLOOKUP(Imput[[#This Row],[RFC]],'Alta Proveedor'!D:D,'Alta Proveedor'!E:E)),"") -> CADENA COMERCIAL OXXO | F98: GASTOS ** - AGUA MINERAL TOPO CHICO 600 ML BOTELLA NO RETORNABLE | G98: 2 | H98: 15.95 | I98: =Imput[[#This Row],[Cantidad]]*Imput[[#This Row],[Precio Unitario]] -> 31.9 | J98: =Imput[[#This Row],[Sub total]]*0.16 -> 5.104 | K98: 0 | L98: =Imput[[#This Row],[Sub total]]+Imput[[#This Row],[IVA]]-Imput[[#This Row],[Retención / IEPS / Descuento]] -> 37.004 | M98: 228.00017 | N98: Factura | P98: 45fe39c2-603a-498e-a3f7-c74f663cd6ed | Q98: 312120250714173353727 | R98: 45852 | S98: 04.- TDC | V98: VIATICOS | W98: ALIMENTOS
B99: JUL 2025 Q1 | C99: C2-9 | D99: CCO8605231N4 | E99: =IFERROR(IF(_xlfn.XLOOKUP(Imput[[#This Row],[RFC]],'Alta Proveedor'!D:D,'Alta Proveedor'!E:E)=0,"",_xlfn.XLOOKUP(Imput[[#This Row],[RFC]],'Alta Proveedor'!D:D,'Alta Proveedor'!E:E)),"") -> CADENA COMERCIAL OXXO | F99: GASTOS ** - BOLSA BIOPLASTICA OXXO 1PZ | G99: 1 | H99: 1.72 | I99: =Imput[[#This Row],[Cantidad]]*Imput[[#This Row],[Precio Unitario]] -> 1.72 | J99: =Imput[[#This Row],[Sub total]]*0.16 -> 0.2752 | K99: 0 | L99: =Imput[[#This Row],[Sub total]]+Imput[[#This Row],[IVA]]-Imput[[#This Row],[Retención / IEPS / Descuento]] -> 1.9952 | M99: 0 | N99: Factura | P99: 45fe39c2-603a-498e-a3f7-c74f663cd6ed | Q99: 312120250714173353727 | R99: 45852 | S99: 04.- TDC | V99: VIATICOS | W99: ALIMENTOS
B100: JUL 2025 Q1 | C100: C2-9 | D100: CCO8605231N4 | E100: =IFERROR(IF(_xlfn.XLOOKUP(Imput[[#This Row],[RFC]],'Alta Proveedor'!D:D,'Alta Proveedor'!E:E)=0,"",_xlfn.XLOOKUP(Imput[[#This Row],[RFC]],'Alta Proveedor'!D:D,'Alta Proveedor'!E:E)),"") -> CADENA COMERCIAL OXXO | F100: GASTOS ** - COCACOLA ORIGINAL LATA 355 ML NR SLEEK CAN | G100: 2 | H100: 18.5349 | I100: =Imput[[#This Row],[Cantidad]]*Imput[[#This Row],[Precio Unitario]] -> 37.0698 | J100: =Imput[[#This Row],[Sub total]]*0.16 -> 5.931168 | K100: 0 | L100: =Imput[[#This Row],[Sub total]]+Imput[[#This Row],[IVA]]-Imput[[#This Row],[Retención / IEPS / Descuento]] -> 43.000968 | M100: 0 | N100: Factura | P100: 45fe39c2-603a-498e-a3f7-c74f663cd6ed | Q100: 312120250714173353727 | R100: 45852 | S100: 04.- TDC | V100: VIATICOS | W100: ALIMENTOS
B101: JUL 2025 Q1 | C101: C2-9 | D101: CCO8605231N4 | E101: =IFERROR(IF(_xlfn.XLOOKUP(Imput[[#This Row],[RFC]],'Alta Proveedor'!D:D,'Alta Proveedor'!E:E)=0,"",_xlfn.XLOOKUP(Imput[[#This Row],[RFC]],'Alta Proveedor'!D:D,'Alta Proveedor'!E:E)),"") -> CADENA COMERCIAL OXXO | F101: GASTOS ** - ELECTROLIT FRESA 625ML | G101: 1 | H101: 27.25 | I101: =Imput[[#This Row],[Cantidad]]*Imput[[#This Row],[Precio Unitario]] -> 27.25 | J101: 0 | K101: 0 | L101: =Imput[[#This Row],[Sub total]]+Imput[[#This Row],[IVA]]-Imput[[#This Row],[Retención / IEPS / Descuento]] -> 27.25 | M101: 0 | N101: Factura | P101: 45fe39c2-603a-498e-a3f7-c74f663cd6ed | Q101: 312120250714173353727 | R101: 45852 | S101: 04.- TDC | V101: VIATICOS | W101: ALIMENTOS
B102: JUL 2025 Q1 | C102: C2-9 | D102: CCO8605231N4 | E102: =IFERROR(IF(_xlfn.XLOOKUP(Imput[[#This Row],[RFC]],'Alta Proveedor'!D:D,'Alta Proveedor'!E:E)=0,"",_xlfn.XLOOKUP(Imput[[#This Row],[RFC]],'Alta Proveedor'!D:D,'Alta Proveedor'!E:E)),"") -> CADENA COMERCIAL OXXO | F102: GASTOS ** - ELECTROLIT LIMA LIMON 625ML | G102: 1 | H102: 27.25 | I102: =Imput[[#This Row],[Cantidad]]*Imput[[#This Row],[Precio Unitario]] -> 27.25 | J102: 0 | K102: 0 | L102: =Imput[[#This Row],[Sub total]]+Imput[[#This Row],[IVA]]-Imput[[#This Row],[Retención / IEPS / Descuento]] -> 27.25 | M102: 0 | N102: Factura | P102: 45fe39c2-603a-498e-a3f7-c74f663cd6ed | Q102: 312120250714173353727 | R102: 45852 | S102: 04.- TDC | V102: VIATICOS | W102: ALIMENTOS
B103: JUL 2025 Q1 | C103: C2-9 | D103: CCO8605231N4 | E103: =IFERROR(IF(_xlfn.XLOOKUP(Imput[[#This Row],[RFC]],'Alta Proveedor'!D:D,'Alta Proveedor'!E:E)=0,"",_xlfn.XLOOKUP(Imput[[#This Row],[RFC]],'Alta Proveedor'!D:D,'Alta Proveedor'!E:E)),"") -> CADENA COMERCIAL OXXO | F103: GASTOS ** - ELECTROLIT FRESA KIWI 625ML | G103: 1 | H103: 37 | I103: =Imput[[#This Row],[Cantidad]]*Imput[[#This Row],[Precio Unitario]] -> 37 | J103: 0 | K103: 0 | L103: =Imput[[#This Row],[Sub total]]+Imput[[#This Row],[IVA]]-Imput[[#This Row],[Retención / IEPS / Descuento]] -> 37 | M103: 0 | N103: Factura | P103: 45fe39c2-603a-498e-a3f7-c74f663cd6ed | Q103: 312120250714173353727 | R103: 45852 | S103: 04.- TDC | V103: VIATICOS | W103: ALIMENTOS
B104: JUL 2025 Q1 | C104: C2-9 | D104: CCO8605231N4 | E104: =IFERROR(IF(_xlfn.XLOOKUP(Imput[[#This Row],[RFC]],'Alta Proveedor'!D:D,'Alta Proveedor'!E:E)=0,"",_xlfn.XLOOKUP(Imput[[#This Row],[RFC]],'Alta Proveedor'!D:D,'Alta Proveedor'!E:E)),"") -> CADENA COMERCIAL OXXO | F104: GASTOS ** - ELECTROLIT MORA AZUL 625ML | G104: 1 | H104: 27.25 | I104: =Imput[[#This Row],[Cantidad]]*Imput[[#This Row],[Precio Unitario]] -> 27.25 | J104: 0 | K104: 0 | L104: =Imput[[#This Row],[Sub total]]+Imput[[#This Row],[IVA]]-Imput[[#This Row],[Retención / IEPS / Descuento]] -> 27.25 | M104: 0 | N104: Factura | P104: 45fe39c2-603a-498e-a3f7-c74f663cd6ed | Q104: 312120250714173353727 | R104: 45852 | S104: 04.- TDC | V104: VIATICOS | W104: ALIMENTOS
...

Sheet Alta Proveedor
B2: No. | D2: Datos de Empresa
D3: RFC | E3: RAZON SOCIAL
B4: 1 | D4: MAS991101DH9 | E4: MASYFERR (FERRETERIA)
B5: =B4+1 -> 2 | D5: ANA050518RL1 | E5: AEROENLACES NACIONALES (VUELOS)
B6: =B5+1 -> 3 | D6: CFC110121742 | E6: COMERCIALIZADORA FARMACEUTICA DE CHIAPAS
B7: =B6+1 -> 4 | D7: CLG130128KA0 | E7: E12196 COMBUSTIBLES Y LUBRICANTES GHN (COMBUSTIBLES)
B8: =B7+1 -> 5 | D8: DLI931201MI9 | E8: DISTRIBUIDORA LIVERPOOL
B9: =B8+1 -> 6 | D9: FCU220209NQ1 | E9: FERRETERIA CUERVO SA DE CV
B10: =B9+1 -> 7 | D10: CAHE700209ATA | E10: ELVIA CABRERA HUERTA "MI PUEBLITO, MMM… QUE SABOR" (RESTAURANTE)
B11: =B10+1 -> 8 | D11: GUCA670908V23 | E11: AUGUSTO EDUARDO GUERRERO CRUZ (RESTAURANTE)
B12: =B11+1 -> 9 | D12: HDM001017AS1 THD-8730 TAMPICO | E12: HOME DEPOT MEXICO SUCURSAL THD-8730 TAMPICO
B13: =B12+1 -> 10 | D13: LOZ170722KGA | E13: EL LINDERO DE OZULUAMA (RESTAURANTE)
B14: =B13+1 -> 11 | D14: MASR990207BB1 | E14: RICARDO MARTINEZ SALAZAR (RESTAURANTE)
B15: =B14+1 -> 12 | D15: MAS0810247C0 | E15: POPAT BAZAR SA DE CV "BUFFALITAS, BUFFALO WINGS, BURGUERS Y RIBS" (RESTAURANTE)
B16: =B15+1 -> 13 | D16: PFL981207AX5 | E16: PERFILES DE FIERRO Y LAMINA ATIYE "ACEROTAM"
... B230: =B229+1 -> 227 | D230: AUSV591108T12 | E230: TORNILLOS SAN CRISTOBAL (VICTORINO DELFINO AGUILAR SANCHEZ)
B231: =B230+1 -> 228
B232: =B231+1 -> 229
B233: =B232+1 -> 230
B234: =B233+1 -> 231
B235: =B234+1 -> 232
B236: =B235+1 -> 233
B237: =B236+1 -> 234
B238: =B237+1 -> 235
B239: =B238+1 -> 236
B240: =B239+1 -> 237
B241: =B240+1 -> 238
B242: =B241+1 -> 239
... B303: =B302+1 -> 300

Sheet Hoja Auxiliar
C2: PERIODO Imp. | D2: COMPRENDE | G2: C. Imp. | H2: Familia | J2: Tipo de Pago | L2: Estatus de Pago | N2: Tipo | P2: APLICA
D3: DESDE | E3: HASTA
G4: C. Imp. | H4: Familia
B5: 1 | C5: JUN 2025 Q1 | D5: 45809 | E5: =D6-1 -> 45823 | G5: ='Indirect Costs'!C11 -> C1 | H5: =_xlfn.XLOOKUP(G5,'Indirect Costs'!C:C,'Indirect Costs'!D:D) -> PERSONAL | J5: 01.- Efectivo | L5: Atrasado | N5: Cancelación | P5: AMORT. ANTICIPO
B6: 2 | C6: JUN 2025 Q2 | D6: 45824 | E6: =D7-1 -> 45838 | G6: ='Indirect Costs'!C13 -> C1-1 | H6: =_xlfn.XLOOKUP(G6,'Indirect Costs'!C:C,'Indirect Costs'!D:D) -> Gerente de Proyecto | J6: 03.- Transferencia | L6: Pagado | N6: Comprobante de pago | P6: ANTICIPO
B7: 3 | C7: JUL 2025 Q1 | D7: 45839 | E7: =D8-1 -> 45853 | G7: ='Indirect Costs'!C14 -> C1-2 | H7: =_xlfn.XLOOKUP(G7,'Indirect Costs'!C:C,'Indirect Costs'!D:D) -> Gerente Estratégico | J7: 04.- TDC | L7: Pendiente | N7: Factura | P7: DEDUCTIVA
B8: 4 | C8: JUL 2025 Q2 | D8: 45854 | E8: =D9-1 -> 45869 | G8: ='Indirect Costs'!C15 -> C1-3 | H8: =_xlfn.XLOOKUP(G8,'Indirect Costs'!C:C,'Indirect Costs'!D:D) -> Gerente Administración | J8: 06.- Dinero Electrónico | L8: Sobrepagado | N8: Nota de Crédito | P8: ESTIMACION
B9: 5 | C9: AGO 2025 Q1 | D9: 45870 | E9: =D10-1 -> 45884 | G9: ='Indirect Costs'!C16 -> C1-4 | H9: =_xlfn.XLOOKUP(G9,'Indirect Costs'!C:C,'Indirect Costs'!D:D) -> Técnico de compras/ control de Costos | J9: 15.- Condonación | N9: Provisión | P9: RETENCION 5%
B10: 6 | C10: AGO 2025 Q2 | D10: 45885 | E10: =D11-1 -> 45900 | G10: ='Indirect Costs'!C17 -> C1-5 | H10: =_xlfn.XLOOKUP(G10,'Indirect Costs'!C:C,'Indirect Costs'!D:D) -> Aux. Administrativo | J10: 27.- A Satisfaccion del Acreedor | N10: Recibo
B11: 7 | C11: SEP 2025 Q1 | D11: 45901 | E11: =D12-1 -> 45915 | G11: ='Indirect Costs'!C19 -> C1-6 | H11: =_xlfn.XLOOKUP(G11,'Indirect Costs'!C:C,'Indirect Costs'!D:D) -> Superintendente | J11: 28.- TDD | N11: Prefactura
B12: 8 | C12: SEP 2025 Q2 | D12: 45916 | E12: =D13-1 -> 45930 | G12: ='Indirect Costs'!C20 -> C1-7 | H12: =_xlfn.XLOOKUP(G12,'Indirect Costs'!C:C,'Indirect Costs'!D:D) -> Jefe de Producción | J12: 30.- Aplicación de Anticipos | N12: Comprobante de Ingresos
B13: 9 | C13: OCT 2025 Q1 | D13: 45931 | E13: =D14-1 -> 45945 | G13: ='Indirect Costs'!C21 -> C1-8 | H13: =_xlfn.XLOOKUP(G13,'Indirect Costs'!C:C,'Indirect Costs'!D:D) -> Supervisor 1 | J13: 31.- Intermediario Pagos | N13: CAJA CHICA
B14: 10 | C14: OCT 2025 Q2 | D14: 45946 | E14: =D15-1 -> 45961 | G14: ='Indirect Costs'!C22 -> C1-9 | H14: =_xlfn.XLOOKUP(G14,'Indirect Costs'!C:C,'Indirect Costs'!D:D) -> Supervisor 2 | J14: 99.- Por Definir
B15: 11 | C15: NOV 2025 Q1 | D15: 45962 | E15: =D16-1 -> 45976 | G15: ='Indirect Costs'!C23 -> C1-10 | H15: =_xlfn.XLOOKUP(G15,'Indirect Costs'!C:C,'Indirect Costs'!D:D) -> Supervisor 3 | J15: PPD.- Pago en parcialidades o diferido
B16: 12 | C16: NOV 2025 Q2 | D16: 45977 | E16: =D17-1 -> 45991 | G16: ='Indirect Costs'!C25 -> C1-11 | H16: =_xlfn.XLOOKUP(G16,'Indirect Costs'!C:C,'Indirect Costs'!D:D) -> Ingeniero de Diseño (Responsable del Proyecto)
B17: 13 | C17: DIC 2025 Q1 | D17: 45992 | E17: =D18-1 -> 46006 | G17: ='Indirect Costs'!C26 -> C1-12 | H17: =_xlfn.XLOOKUP(G17,'Indirect Costs'!C:C,'Indirect Costs'!D:D) -> Coordinador BIM
B18: 14 | C18: DIC 2025 Q2 | D18: 46007 | E18: =D19-1 -> 46022 | G18: ='Indirect Costs'!C27 -> C1-13 | H18: =_xlfn.XLOOKUP(G18,'Indirect Costs'!C:C,'Indirect Costs'!D:D) -> Especialista de Disciplina BIM
B19: 15 | C19: ENE 2026 Q1 | D19: 46023 | E19: =D20-1 -> 46037 | G19: ='Indirect Costs'!C28 -> C1-14 | H19: =_xlfn.XLOOKUP(G19,'Indirect Costs'!C:C,'Indirect Costs'!D:D) -> Gestor de Información BIM
B20: 16 | C20: ENE 2026 Q2 | D20: 46038 | E20: =D21-1 -> 46053 | G20: ='Indirect Costs'!C29 -> C1-15 | H20: =_xlfn.XLOOKUP(G20,'Indirect Costs'!C:C,'Indirect Costs'!D:D) -> Jefe de Topografía y Oficina Técnica
B21: 17 | C21: FEB 2026 Q1 | D21: 46054 | E21: =D22-1 -> 46068 | G21: ='Indirect Costs'!C30 -> C1-16 | H21: =_xlfn.XLOOKUP(G21,'Indirect Costs'!C:C,'Indirect Costs'!D:D) -> Topógrafo
B22: 18 | C22: FEB 2026 Q2 | D22: 46069 | E22: =D23-1 -> 46081 | G22: ='Indirect Costs'!C31 -> C1-17 | H22: =_xlfn.XLOOKUP(G22,'Indirect Costs'!C:C,'Indirect Costs'!D:D) -> Brigada Topografia (3 personas)
B23: 19 | C23: MAR 2026 Q1 | D23: 46082 | E23: =D24-1 -> 46096 | G23: ='Indirect Costs'!C32 -> C1-18 | H23: =_xlfn.XLOOKUP(G23,'Indirect Costs'!C:C,'Indirect Costs'!D:D) -> Jefe Estimaciones
B24: 20 | C24: MAR 2026 Q2 | D24: 46097 | E24: =D25-1 -> 46112 | G24: ='Indirect Costs'!C33 -> C1-19 | H24: =_xlfn.XLOOKUP(G24,'Indirect Costs'!C:C,'Indirect Costs'!D:D) -> Técnico Estimaciones
B25: 21 | C25: ABR 2026 Q1 | D25: 46113 | E25: =D26-1 -> 46127 | G25: ='Indirect Costs'!C35 -> C1-20 | H25: =_xlfn.XLOOKUP(G25,'Indirect Costs'!C:C,'Indirect Costs'!D:D) -> Jefe Seguridad e Higiene y Vialidad
B26: 22 | C26: ABR 2026 Q2 | D26: 46128 | E26: =D27-1 -> 46152 | G26: ='Indirect Costs'!C36 -> C1-21 | H26: =_xlfn.XLOOKUP(G26,'Indirect Costs'!C:C,'Indirect Costs'!D:D) -> Técnico Seguridad
B27: 23 | C27: MAY 2026 Q1 | D27: 46153 | E27: =D28-1 -> 46157 | G27: ='Indirect Costs'!C37 -> C1-22 | H27: =_xlfn.XLOOKUP(G27,'Indirect Costs'!C:C,'Indirect Costs'!D:D) -> Jefe Calidad y Medioambiente
B28: 24 | C28: MAY 2026 Q2 | D28: 46158 | E28: 46022 | G28: ='Indirect Costs'!C38 -> C1-23 | H28: =_xlfn.XLOOKUP(G28,'Indirect Costs'!C:C,'Indirect Costs'!D:D) -> Técnico Calidad y Medioambiente
B29: 25 | C29: JUN 2026 Q1 | D29: 46174 | E29: =D30-1 -> 46188 | G29: ='Indirect Costs'!C39 -> C1-24 | H29: =_xlfn.XLOOKUP(G29,'Indirect Costs'!C:C,'Indirect Costs'!D:D) -> Brigada Prevención (3 personas)
B30: 26 | C30: JUN 2026 Q2 | D30: 46189 | E30: =D31-1 -> 46203 | G30: ='Indirect Costs'!C41 -> C1-25 | H30: =_xlfn.XLOOKUP(G30,'Indirect Costs'!C:C,'Indirect Costs'!D:D) -> Jefe Planificación y Costes
B31: 27 | C31: JUL 2026 Q1 | D31: 46204 | E31: =D32-1 -> 46218 | G31: ='Indirect Costs'!C42 -> C1-26 | H31: =_xlfn.XLOOKUP(G31,'Indirect Costs'!C:C,'Indirect Costs'!D:D) -> Técnico Control Costes
B32: 28 | C32: JUL 2026 Q2 | D32: 46219 | E32: =D33-1 -> 46234 | G32: ='Indirect Costs'!C43 -> C1-27 | H32: =_xlfn.XLOOKUP(G32,'Indirect Costs'!C:C,'Indirect Costs'!D:D) -> Técnico Compras
B33: 29 | C33: AGO 2026 Q1 | D33: 46235 | E33: =D34-1 -> 46249 | G33: ='Indirect Costs'!C44 -> C1-28 | H33: =_xlfn.XLOOKUP(G33,'Indirect Costs'!C:C,'Indirect Costs'!D:D) -> Jefe Administración y Personal
B34: 30 | C34: AGO 2026 Q2 | D34: 46250 | E34: =D35-1 -> 46265 | G34: ='Indirect Costs'!C45 -> C1-29 | H34: =_xlfn.XLOOKUP(G34,'Indirect Costs'!C:C,'Indirect Costs'!D:D) -> RRHH
B35: 31 | C35: SEP 2026 Q1 | D35: 46266 | E35: =D36-1 -> 46280 | G35: ='Indirect Costs'!C46 -> C1-30 | H35: =_xlfn.XLOOKUP(G35,'Indirect Costs'!C:C,'Indirect Costs'!D:D) -> Contador
B36: 32 | C36: SEP 2026 Q2 | D36: 46281 | E36: =D37-1 -> 46295 | G36: ='Indirect Costs'!C47 -> C1-31 | H36: =_xlfn.XLOOKUP(G36,'Indirect Costs'!C:C,'Indirect Costs'!D:D) -> Jefe Almacen
B37: 33 | C37: OCT 2026 Q1 | D37: 46296 | E37: =D38-1 -> 46310 | G37: ='Indirect Costs'!C48 -> C1-32 | H37: =_xlfn.XLOOKUP(G37,'Indirect Costs'!C:C,'Indirect Costs'!D:D) -> Brigada Vigilancia armada (3 personas)
B38: 34 | C38: OCT 2026 Q2 | D38: 46311 | E38: =D39-1 -> 46326 | G38: ='Indirect Costs'!C49 -> C1-33 | H38: =_xlfn.XLOOKUP(G38,'Indirect Costs'!C:C,'Indirect Costs'!D:D) -> Brigada Vigilancia (3 personas)
B39: 35 | C39: NOV 2026 Q1 | D39: 46327 | E39: =D40-1 -> 46341 | G39: ='Indirect Costs'!C50 -> C1-34 | H39: =_xlfn.XLOOKUP(G39,'Indirect Costs'!C:C,'Indirect Costs'!D:D) -> Limpieza
B40: 36 | C40: NOV 2026 Q2 | D40: 46342 | E40: =D41-1 -> 46356 | G40: ='Indirect Costs'!C51 -> C1-35 | H40: =_xlfn.XLOOKUP(G40,'Indirect Costs'!C:C,'Indirect Costs'!D:D) -> Chófer transporte personal
B41: 37 | C41: DIC 2026 Q1 | D41: 46357 | E41: =D42-1 -> 46371 | G41: ='Indirect Costs'!C52 -> C2 | H41: =_xlfn.XLOOKUP(G41,'Indirect Costs'!C:C,'Indirect Costs'!D:D) -> EQUIPAMIENTO PARA PERSONAL DE OBRA
... B51: 47 | C51: MAY 2027 Q1 | D51: 46508 | E51: =D52-1 -> 46522 | G51: ='Indirect Costs'!C62 -> C2-10 | H51: =_xlfn.XLOOKUP(G51,'Indirect Costs'!C:C,'Indirect Costs'!D:D) -> Papelería
B52: 48 | C52: MAY 2027 Q2 | D52: 46523 | E52: 46538 | G52: ='Indirect Costs'!C63 -> C3 | H52: =_xlfn.XLOOKUP(G52,'Indirect Costs'!C:C,'Indirect Costs'!D:D) -> TRASLADOS Y HOSPEDAJES
G53: ='Indirect Costs'!C64 -> C3-1 | H53: =_xlfn.XLOOKUP(G53,'Indirect Costs'!C:C,'Indirect Costs'!D:D) -> Casa Ingenieros de Obra
G54: ='Indirect Costs'!C65 -> C3-2 | H54: =_xlfn.XLOOKUP(G54,'Indirect Costs'!C:C,'Indirect Costs'!D:D) -> Casa Personal de obra
G55: ='Indirect Costs'!C66 -> C3-3 | H55: =_xlfn.XLOOKUP(G55,'Indirect Costs'!C:C,'Indirect Costs'!D:D) -> Patio de armado
G56: ='Indirect Costs'!C67 -> C3-4 | H56: =_xlfn.XLOOKUP(G56,'Indirect Costs'!C:C,'Indirect Costs'!D:D) -> Hoteles
G57: ='Indirect Costs'!C68 -> C3-5 | H57: =_xlfn.XLOOKUP(G57,'Indirect Costs'!C:C,'Indirect Costs'!D:D) -> Vuelos
G58: ='Indirect Costs'!C69 -> C3-6 | H58: =_xlfn.XLOOKUP(G58,'Indirect Costs'!C:C,'Indirect Costs'!D:D) -> Taxis
G59: ='Indirect Costs'!C70 -> C3-7 | H59: =_xlfn.XLOOKUP(G59,'Indirect Costs'!C:C,'Indirect Costs'!D:D) -> Depósito en garantía Renta de Casas
G60: ='Indirect Costs'!C71 -> C4 | H60: =_xlfn.XLOOKUP(G60,'Indirect Costs'!C:C,'Indirect Costs'!D:D) -> GASTOS DE OFICINA CENTRAL
G61: ='Indirect Costs'!C72 -> C4-1 | H61: =_xlfn.XLOOKUP(G61,'Indirect Costs'!C:C,'Indirect Costs'!D:D) -> Contabilidad
G62: ='Indirect Costs'!C73 -> C4-2 | H62: =_xlfn.XLOOKUP(G62,'Indirect Costs'!C:C,'Indirect Costs'!D:D) -> Papelería
G63: ='Indirect Costs'!C74 -> C4-3 | H63: =_xlfn.XLOOKUP(G63,'Indirect Costs'!C:C,'Indirect Costs'!D:D) -> Equipos de computación
G64: ='Indirect Costs'!C75 -> C4-4 | H64: =_xlfn.XLOOKUP(G64,'Indirect Costs'!C:C,'Indirect Costs'!D:D) -> Impresoras y equipo auxiliar de oficina
... G127: ='Indirect Costs'!C138 -> C8-6 | H127: =_xlfn.XLOOKUP(G127,'Indirect Costs'!C:C,'Indirect Costs'!D:D) -> Entrega As Built
G128: ='Costo Directo'!D14 -> P1 | H128: ='Costo Directo'!E14 -> SUBCONTRATOS
G129: ='Costo Directo'!D17 -> MAN-P1-1 | H129: ='Costo Directo'!E17 -> COLADO DE CONCRETO CON TUBO TREMIE. TIRO DIRECTO
G130: ='Costo Directo'!D18 -> MAN-P1-2 | H130: ='Costo Directo'!E18 -> COLOCACIÓN DE ARMADO EN EXCAVACIÓN
G131: ='Costo Directo'!D19 -> MAN-P1-3 | H131: ='Costo Directo'!E19 -> FLETES DEL EQUIPO
G132: ='Costo Directo'!D20 -> MAN-P1-4 | H132: ='Costo Directo'!E20 -> HABILITADO DE ACERO CORRUGADO DE CUALQUIER DIÁMETRO
G133: ='Costo Directo'!D21 -> MAN-P1-5 | H133: ='Costo Directo'!E21 -> SUBCONTRATO DE EXCAVACIÓN POR MEDIOS MECÁNICOS
G134: ='Costo Directo'!D22 -> MAN-P1-6 | H134: ='Costo Directo'!E22 -> SUBCONTRATO DE GROUT Y BANQUETA (lote 10 pilas)
G135: ='Costo Directo'!D23 -> MAN-P1-7 | H135: ='Costo Directo'!E23 -> 0
G136: ='Costo Directo'!D24 -> MAN-P1-8 | H136: ='Costo Directo'!E24 -> 0
G137: ='Costo Directo'!D26 -> P2 | H137: ='Costo Directo'!E26 -> MAQUINARIA
G138: ='Costo Directo'!D29 -> MAN-P2-1 | H138: ='Costo Directo'!E29 -> CORTADORA DE CONCRETO
G139: ='Costo Directo'!D30 -> MAN-P2-2 | H139: ='Costo Directo'!E30 -> VIBRADOR DE CONCRETO
G140: ='Costo Directo'!D31 -> MAN-P2-3 | H140: ='Costo Directo'!E31 -> VIBROCOMPACTADOR MANUAL
G141: ='Costo Directo'!D32 -> MAN-P2-4 | H141: ='Costo Directo'!E32 -> 0
G142: ='Costo Directo'!D33 -> MAN-P2-5 | H142: ='Costo Directo'!E33 -> 0
G143: ='Costo Directo'!D34 -> MAN-P2-6 | H143: ='Costo Directo'!E34 -> 0
G144: ='Costo Directo'!D35 -> MAN-P2-7 | H144: ='Costo Directo'!E35 -> 0
G145: ='Costo Directo'!D36 -> MAN-P2-8 | H145: ='Costo Directo'!E36 -> 0
G146: ='Costo Directo'!D37 -> MAN-P2-9 | H146: ='Costo Directo'!E37 -> 0
G147: ='Costo Directo'!D38 -> MAN-P2-10 | H147: ='Costo Directo'!E38 -> 0
G148: ='Costo Directo'!D39 -> MAN-P2-11 | H148: ='Costo Directo'!E39 -> 0
G149: ='Costo Directo'!D40 -> MAN-P2-12 | H149: ='Costo Directo'!E40 -> 0
... G175: ='Costo Directo'!D66 -> MAN-P2-38 | H175: ='Costo Directo'!E66 -> 0
G176: ='Costo Directo'!D68 -> P3 | H176: ='Costo Directo'!E68 -> MANO DE OBRA
G177: ='Costo Directo'!D71 -> MAN-P3-1 | H177: ='Costo Directo'!E71 -> AYUDANTE 01
G178: ='Costo Directo'!D72 -> MAN-P3-2 | H178: ='Costo Directo'!E72 -> AYUDANTE 02
G179: ='Costo Directo'!D73 -> MAN-P3-3 | H179: ='Costo Directo'!E73 -> OFICIAL
G180: ='Costo Directo'!D74 -> MAN-P3-4 | H180: ='Costo Directo'!E74 -> 0
G181: ='Costo Directo'!D75 -> MAN-P3-5 | H181: ='Costo Directo'!E75 -> 0
G182: ='Costo Directo'!D76 -> MAN-P3-6 | H182: ='Costo Directo'!E76 -> 0
G183: ='Costo Directo'!D77 -> MAN-P3-7 | H183: ='Costo Directo'!E77 -> 0
G184: ='Costo Directo'!D78 -> MAN-P3-8 | H184: ='Costo Directo'!E78 -> 0
G185: ='Costo Directo'!D79 -> MAN-P3-9 | H185: ='Costo Directo'!E79 -> 0
G186: ='Costo Directo'!D80 -> MAN-P3-10 | H186: ='Costo Directo'!E80 -> 0
G187: ='Costo Directo'!D81 -> MAN-P3-11 | H187: ='Costo Directo'!E81 -> 0
G188: ='Costo Directo'!D82 -> MAN-P3-12 | H188: ='Costo Directo'!E82 -> 0
... G225: ='Costo Directo'!D119 -> MAN-P3-49 | H225: ='Costo Directo'!E119 -> 0
G226: ='Costo Directo'!D121 -> P4 | H226: ='Costo Directo'!E121 -> MATERIALES
G227: ='Costo Directo'!D124 -> MAN-P4-1 | H227: ='Costo Directo'!E124 -> ADITIVO CURADOR
G228: ='Costo Directo'!D125 -> MAN-P4-2 | H228: ='Costo Directo'!E125 -> ADITIVO DESMOLDANTE SIKA O SIMILAR
G229: ='Costo Directo'!D126 -> MAN-P4-3 | H229: ='Costo Directo'!E126 -> AGUA
G230: ='Costo Directo'!D127 -> MAN-P4-4 | H230: ='Costo Directo'!E127 -> ALAMBRE RECOCIDO
G231: ='Costo Directo'!D128 -> MAN-P4-5 | H231: ='Costo Directo'!E128 -> ARENA
G232: ='Costo Directo'!D129 -> MAN-P4-6 | H232: ='Costo Directo'!E129 -> CEMENTO
G233: ='Costo Directo'!D130 -> MAN-P4-7 | H233: ='Costo Directo'!E130 -> CONCRETO F'C=250 KG/CM2
...

Sheet Costo Directo
F1: Costo supuesto
F2: Ofertado
D3: ='Resumen Ejecutivo'!C2 -> PROYECTO: | E3: =IF('Resumen Ejecutivo'!D2=0,"",'Resumen Ejecutivo'!D2) -> CONSTRUCCIÓN DE 50 PILAS DE CONCRETO ARMADO PARA PMI'S EN EL ESTADO DE TAMAULIPAS (TAMPICO Y MANTE) | I3: Tipo de Cambio (MXN / USD): | J3: 21
D4: ='Resumen Ejecutivo'!C3 -> CLIENTE: | E4: =IF('Resumen Ejecutivo'!D3=0,"",'Resumen Ejecutivo'!D3) -> SYM KABAT
H5: ='Indirect Costs'!G4 -> MESES DE EJECUCIÓN : | J5: 1
H6: Long. total (m) | L6: =L10/2 -> 534307.44 | N6: =N10/2 -> 26254.52 | P6: =P10/2 -> 55107.979 | R6: =R10/2 -> 35442.074
H7: Diesel | J7: =24/1.16 -> 20.689655
L8: PREVISION
C9: Costo Mensual | D9: C. Imp. | E9: - | F9: - | G9: - | H9: Costo/ml | I9: Costo Total Previsto | L9: JUN 2025 Q1 | M9: JUN 2025 Q2 | N9: JUL 2025 Q1 | O9: JUL 2025 Q2 | P9: AGO 2025 Q1 | Q9: AGO 2025 Q2 | R9: SEP 2025 Q1 | S9: SEP 2025 Q2 | T9: OCT 2025 Q1 | U9: OCT 2025 Q2 | V9: NOV 2025 Q1 | W9: NOV 2025 Q2 | X9: DIC 2025 Q1 | Y9: DIC 2025 Q2 | Z9: ENE 2026 Q1 | AA9: ENE 2026 Q2 | AB9: FEB 2026 Q1 | AC9: FEB 2026 Q2 | AD9: MAR 2026 Q1 | AE9: MAR 2026 Q2 | AF9: ABR 2026 Q1 | AG9: ABR 2026 Q2 | AH9: MAY 2026 Q1 | AI9: MAY 2026 Q2 | AJ9: JUN 2026 Q1 | AK9: JUN 2026 Q2 | AL9: JUL 2026 Q1 | AM9: JUL 2026 Q2 | AN9: AGO 2026 Q1 | AO9: AGO 2026 Q2 | AP9: SEP 2026 Q1 | AQ9: SEP 2026 Q2 | AR9: OCT 2026 Q1 | AS9: OCT 2026 Q2 | AT9: NOV 2026 Q1 | AU9: NOV 2026 Q2 | AV9: DIC 2026 Q1 | AW9: DIC 2026 Q2 | AX9: ENE 2027 Q1 | AY9: ENE 2027 Q2 | AZ9: FEB 2027 Q1 | BA9: FEB 2027 Q2 | BB9: MAR 2027 Q1 | BC9: MAR 2027 Q2 | BD9: ABR 2027 Q1 | BE9: ABR 2027 Q2 | BF9: MAY 2027 Q1 | BG9: MAY 2027 Q2 | BJ9: % Imputado | BK9: Imputado Acumulado | BM9: =L9 -> JUN 2025 Q1 | BN9: =M9 -> JUN 2025 Q2 | BO9: =N9 -> JUL 2025 Q1 | BP9: =O9 -> JUL 2025 Q2 | BQ9: =P9 -> AGO 2025 Q1 | BR9: =Q9 -> AGO 2025 Q2 | BS9: =R9 -> SEP 2025 Q1 | BT9: =S9 -> SEP 2025 Q2 | ... DH9: =BG9 -> MAY 2027 Q2
C10: =+J10/SUM(L14:BG14) -> 21.406521 | H10: =IFERROR(+J10/J6,0) -> 0 | J10: =SUBTOTAL(9,J13:J1194) -> 2445044.3 | L10: =SUBTOTAL(9,L13:L1194) -> 1068614.9 | M10: =SUBTOTAL(9,M13:M1194) -> 23088.077 | N10: =SUBTOTAL(9,N13:N1194) -> 52509.04 | O10: =SUBTOTAL(9,O13:O1194) -> 59263.977 | P10: =SUBTOTAL(9,P13:P1194) -> 110215.96 | Q10: =SUBTOTAL(9,Q13:Q1194) -> 23088.077 | R10: =SUBTOTAL(9,R13:R1194) -> 70884.147 | S10: =SUBTOTAL(9,S13:S1194) -> 48236.977 | ... BG10: =SUBTOTAL(9,BG13:BG1194) -> 0 | BJ10: =IFERROR(BK10/J10,0) -> 0.71941307 | BK10: =SUM(BM10:DH10) -> 1758996.8 | BM10: =SUBTOTAL(9,BM13:BM1194) -> 0 | BN10: =SUBTOTAL(9,BN13:BN1194) -> 104895.6 | BO10: =SUBTOTAL(9,BO13:BO1194) -> 253586.14 | BP10: =SUBTOTAL(9,BP13:BP1194) -> 716665.2 | BQ10: =SUBTOTAL(9,BQ13:BQ1194) -> 378985.49 | BR10: =SUBTOTAL(9,BR13:BR1194) -> 253319.92 | BS10: =SUBTOTAL(9,BS13:BS1194) -> 28344.49 | BT10: =SUBTOTAL(9,BT13:BT1194) -> 0 | ... DH10: =SUBTOTAL(9,DH13:DH1194) -> 0
A12: IMPRIMIR | C12: Estado | D12: C. Imp.
A13: =IF(J13>0,"Imprimir","") -> Imprimir | C13: MANTE | J13: =SUBTOTAL(9,J14:J247) -> 302381.54 | L13: =SUBTOTAL(9,L14:L248) -> 137132.47 | M13: =SUBTOTAL(9,M14:M248) -> 3128.3166 | N13: =SUBTOTAL(9,N14:N248) -> 6502.0466 | O13: =SUBTOTAL(9,O14:O248) -> 7970.0866 | P13: =SUBTOTAL(9,P14:P248) -> 14288.783 | Q13: =SUBTOTAL(9,Q14:Q248) -> 3128.3166 | R13: =SUBTOTAL(9,R14:R248) -> 8839.5966 | S13: =SUBTOTAL(9,S14:S248) -> 6470.1866 | ... BG13: =SUBTOTAL(9,BG14:BG248) -> 0 | BK13: =SUBTOTAL(9,BK14:BK247) -> 371644.91 | BM13: =SUBTOTAL(9,BM14:BM247) -> 0 | BN13: =SUBTOTAL(9,BN14:BN247) -> 0 | BO13: =SUBTOTAL(9,BO14:BO247) -> 44644.711 | BP13: =SUBTOTAL(9,BP14:BP247) -> 70050.608 | BQ13: =SUBTOTAL(9,BQ14:BQ247) -> 71831.784 | BR13: =SUBTOTAL(9,BR14:BR247) -> 185117.81 | BS13: =SUBTOTAL(9,BS14:BS247) -> 0 | BT13: =SUBTOTAL(9,BT14:BT247) -> 0 | ... DH13: =SUBTOTAL(9,DH14:DH247) -> 0
A14: =IF(J14>0,"Imprimir","") -> Imprimir | D14: P1 | E14: SUBCONTRATOS | J14: =SUBTOTAL(9,J17:J25) -> 114219.6 | L14: =SUMPRODUCT($J17:$J25,L17:L25) -> 43615.88 | M14: =SUMPRODUCT($J17:$J25,M17:M25) -> 0 | N14: =SUMPRODUCT($J17:$J25,N17:N25) -> 3373.48 | O14: =SUMPRODUCT($J17:$J25,O17:O25) -> 0 | P14: =SUMPRODUCT($J17:$J25,P17:P25) -> 3373.48 | Q14: =SUMPRODUCT($J17:$J25,Q17:Q25) -> 0 | R14: =SUMPRODUCT($J17:$J25,R17:R25) -> 5710.98 | S14: =SUMPRODUCT($J17:$J25,S17:S25) -> 0 | ... BG14: =SUMPRODUCT($J17:$J25,BG17:BG25) -> 0 | BJ14: =IFERROR(BK14/J14,0) -> 1.0405156 | BK14: =SUBTOTAL(9,BK15:BK25) -> 118847.27 | BM14: =SUBTOTAL(9,BM15:BM25) -> 0 | BN14: =SUBTOTAL(9,BN15:BN25) -> 0 | BO14: =SUBTOTAL(9,BO15:BO25) -> 0 | BP14: =SUBTOTAL(9,BP15:BP25) -> 2835.0013 | BQ14: =SUBTOTAL(9,BQ15:BQ25) -> 29455.531 | BR14: =SUBTOTAL(9,BR15:BR25) -> 86556.74 | BS14: =SUBTOTAL(9,BS15:BS25) -> 0 | BT14: =SUBTOTAL(9,BT15:BT25) -> 0 | ... DH14: =SUBTOTAL(9,DH15:DH25) -> 0
A15: =IF(J14>0,"Imprimir","") -> Imprimir | F15: Proveedor | G15: Costo Empresa | H15: Cantidad | I15: Meses | J15: Importe
A16: =IF(J16>0,"Imprimir","") -> Imprimir | J16: =SUBTOTAL(9,J17:J25) -> 114219.6
A17: =IF(J17="","",IF(J17=0,"","Imprimir")) -> Imprimir | D17: MAN-P1-1 | E17: COLADO DE CONCRETO CON TUBO TREMIE. TIRO DIRECTO | G17: 262 | H17: =Producción!G12*1 -> 17 | I17: =IF(E17>0,$J$5,"") -> 1 | J17: =IFERROR(G17*H17*I17,"") -> 4454 | L17: 0.3 | N17: 0.05 | P17: 0.05 | R17: 0.05 | T17: 0.05 | V17: 0.05 | X17: 0.05 | Z17: 0.05 | AB17: 0.05 | AD17: 0.05 | AF17: 0.05 | AH17: 0.05 | AJ17: 0.15 | BJ17: =IFERROR(BK17/J17,0) -> 0 | BK17: =SUM(BM17:DH17) -> 0 | BM17: =SUMIFS(Imput[[Importe Neto]:[Importe Neto]],Imput[[C. Imp.]:[C. Imp.]],$D17,Imput[[PERIODO Imp.]:[PERIODO Imp.]],BM$9) -> 0 | BN17: =SUMIFS(Imput[[Importe Neto]:[Importe Neto]],Imput[[C. Imp.]:[C. Imp.]],$D17,Imput[[PERIODO Imp.]:[PERIODO Imp.]],BN$9) -> 0 | BO17: =SUMIFS(Imput[[Importe Neto]:[Importe Neto]],Imput[[C. Imp.]:[C. Imp.]],$D17,Imput[[PERIODO Imp.]:[PERIODO Imp.]],BO$9) -> 0 | BP17: =SUMIFS(Imput[[Importe Neto]:[Importe Neto]],Imput[[C. Imp.]:[C. Imp.]],$D17,Imput[[PERIODO Imp.]:[PERIODO Imp.]],BP$9) -> 0 | BQ17: =SUMIFS(Imput[[Importe Neto]:[Importe Neto]],Imput[[C. Imp.]:[C. Imp.]],$D17,Imput[[PERIODO Imp.]:[PERIODO Imp.]],BQ$9) -> 0 | BR17: =SUMIFS(Imput[[Importe Neto]:[Importe Neto]],Imput[[C. Imp.]:[C. Imp.]],$D17,Imput[[PERIODO Imp.]:[PERIODO Imp.]],BR$9) -> 0 | BS17: =SUMIFS(Imput[[Importe Neto]:[Importe Neto]],Imput[[C. Imp.]:[C. Imp.]],$D17,Imput[[PERIODO Imp.]:[PERIODO Imp.]],BS$9) -> 0 | BT17: =SUMIFS(Imput[[Importe Neto]:[Importe Neto]],Imput[[C. Imp.]:[C. Imp.]],$D17,Imput[[PERIODO Imp.]:[PERIODO Imp.]],BT$9) -> 0 | ... DH17: =SUMIFS(Imput[[Importe Neto]:[Importe Neto]],Imput[[C. Imp.]:[C. Imp.]],$D17,Imput[[PERIODO Imp.]:[PERIODO Imp.]],DH$9) -> 0
A18: =IF(J18="","",IF(J18=0,"","Imprimir")) -> Imprimir | D18: MAN-P1-2 | E18: COLOCACIÓN DE ARMADO EN EXCAVACIÓN | G18: 170 | H18: =Producción!G12*1 -> 17 | I18: =IF(E18>0,$J$5,"") -> 1 | J18: =IFERROR(G18*H18*I18,"") -> 2890 | L18: 0.3 | N18: 0.05 | P18: 0.05 | R18: 0.05 | T18: 0.05 | V18: 0.05 | X18: 0.05 | Z18: 0.05 | AB18: 0.05 | AD18: 0.05 | AF18: 0.05 | AH18: 0.05 | AJ18: 0.15 | BJ18: =IFERROR(BK18/J18,0) -> 0 | BK18: =SUM(BM18:DH18) -> 0 | BM18: =SUMIFS(Imput[[Importe Neto]:[Importe Neto]],Imput[[C. Imp.]:[C. Imp.]],$D18,Imput[[PERIODO Imp.]:[PERIODO Imp.]],BM$9) -> 0 | BN18: =SUMIFS(Imput[[Importe Neto]:[Importe Neto]],Imput[[C. Imp.]:[C. Imp.]],$D18,Imput[[PERIODO Imp.]:[PERIODO Imp.]],BN$9) -> 0 | BO18: =SUMIFS(Imput[[Importe Neto]:[Importe Neto]],Imput[[C. Imp.]:[C. Imp.]],$D18,Imput[[PERIODO Imp.]:[PERIODO Imp.]],BO$9) -> 0 | BP18: =SUMIFS(Imput[[Importe Neto]:[Importe Neto]],Imput[[C. Imp.]:[C. Imp.]],$D18,Imput[[PERIODO Imp.]:[PERIODO Imp.]],BP$9) -> 0 | BQ18: =SUMIFS(Imput[[Importe Neto]:[Importe Neto]],Imput[[C. Imp.]:[C. Imp.]],$D18,Imput[[PERIODO Imp.]:[PERIODO Imp.]],BQ$9) -> 0 | BR18: =SUMIFS(Imput[[Importe Neto]:[Importe Neto]],Imput[[C. Imp.]:[C. Imp.]],$D18,Imput[[PERIODO Imp.]:[PERIODO Imp.]],BR$9) -> 0 | BS18: =SUMIFS(Imput[[Importe Neto]:[Importe Neto]],Imput[[C. Imp.]:[C. Imp.]],$D18,Imput[[PERIODO Imp.]:[PERIODO Imp.]],BS$9) -> 0 | BT18: =SUMIFS(Imput[[Importe Neto]:[Importe Neto]],Imput[[C. Imp.]:[C. Imp.]],$D18,Imput[[PERIODO Imp.]:[PERIODO Imp.]],BT$9) -> 0 | ... DH18: =SUMIFS(Imput[[Importe Neto]:[Importe Neto]],Imput[[C. Imp.]:[C. Imp.]],$D18,Imput[[PERIODO Imp.]:[PERIODO Imp.]],DH$9) -> 0
A19: =IF(J19="","",IF(J19=0,"","Imprimir")) -> Imprimir | D19: MAN-P1-3 | E19: FLETES DEL EQUIPO | G19: 80000 | H19: =Producción!G12*0.022 -> 0.374 | I19: =IF(E19>0,$J$5,"") -> 1 | J19: =IFERROR(G19*H19*I19,"") -> 29920 | L19: 0.3 | N19: 0.05 | P19: 0.05 | R19: 0.05 | T19: 0.05 | V19: 0.05 | X19: 0.05 | Z19: 0.05 | AB19: 0.05 | AD19: 0.05 | AF19: 0.05 | AH19: 0.05 | AJ19: 0.15 | BJ19: =IFERROR(BK19/J19,0) -> 0 | BK19: =SUM(BM19:DH19) -> 0 | BM19: =SUMIFS(Imput[[Importe Neto]:[Importe Neto]],Imput[[C. Imp.]:[C. Imp.]],$D19,Imput[[PERIODO Imp.]:[PERIODO Imp.]],BM$9) -> 0 | BN19: =SUMIFS(Imput[[Importe Neto]:[Importe Neto]],Imput[[C. Imp.]:[C. Imp.]],$D19,Imput[[PERIODO Imp.]:[PERIODO Imp.]],BN$9) -> 0 | BO19: =SUMIFS(Imput[[Importe Neto]:[Importe Neto]],Imput[[C. Imp.]:[C. Imp.]],$D19,Imput[[PERIODO Imp.]:[PERIODO Imp.]],BO$9) -> 0 | BP19: =SUMIFS(Imput[[Importe Neto]:[Importe Neto]],Imput[[C. Imp.]:[C. Imp.]],$D19,Imput[[PERIODO Imp.]:[PERIODO Imp.]],BP$9) -> 0 | BQ19: =SUMIFS(Imput[[Importe Neto]:[Importe Neto]],Imput[[C. Imp.]:[C. Imp.]],$D19,Imput[[PERIODO Imp.]:[PERIODO Imp.]],BQ$9) -> 0 | BR19: =SUMIFS(Imput[[Importe Neto]:[Importe Neto]],Imput[[C. Imp.]:[C. Imp.]],$D19,Imput[[PERIODO Imp.]:[PERIODO Imp.]],BR$9) -> 0 | BS19: =SUMIFS(Imput[[Importe Neto]:[Importe Neto]],Imput[[C. Imp.]:[C. Imp.]],$D19,Imput[[PERIODO Imp.]:[PERIODO Imp.]],BS$9) -> 0 | BT19: =SUMIFS(Imput[[Importe Neto]:[Importe Neto]],Imput[[C. Imp.]:[C. Imp.]],$D19,Imput[[PERIODO Imp.]:[PERIODO Imp.]],BT$9) -> 0 | ... DH19: =SUMIFS(Imput[[Importe Neto]:[Importe Neto]],Imput[[C. Imp.]:[C. Imp.]],$D19,Imput[[PERIODO Imp.]:[PERIODO Imp.]],DH$9) -> 0
A20: =IF(J20="","",IF(J20=0,"","Imprimir")) -> Imprimir | D20: MAN-P1-4 | E20: HABILITADO DE ACERO CORRUGADO DE CUALQUIER DIÁMETRO | G20: 10 | H20: =Producción!G12*127.68 -> 2170.56 | I20: =IF(E20>0,$J$5,"") -> 1 | J20: =IFERROR(G20*H20*I20,"") -> 21705.6 | L20: 0.3 | N20: 0.05 | P20: 0.05 | R20: 0.05 | T20: 0.05 | V20: 0.05 | X20: 0.05 | Z20: 0.05 | AB20: 0.05 | AD20: 0.05 | AF20: 0.05 | AH20: 0.05 | AJ20: 0.15 | BJ20: =IFERROR(BK20/J20,0) -> 0 | BK20: =SUM(BM20:DH20) -> 0 | BM20: =SUMIFS(Imput[[Importe Neto]:[Importe Neto]],Imput[[C. Imp.]:[C. Imp.]],$D20,Imput[[PERIODO Imp.]:[PERIODO Imp.]],BM$9) -> 0 | BN20: =SUMIFS(Imput[[Importe Neto]:[Importe Neto]],Imput[[C. Imp.]:[C. Imp.]],$D20,Imput[[PERIODO Imp.]:[PERIODO Imp.]],BN$9) -> 0 | BO20: =SUMIFS(Imput[[Importe Neto]:[Importe Neto]],Imput[[C. Imp.]:[C. Imp.]],$D20,Imput[[PERIODO Imp.]:[PERIODO Imp.]],BO$9) -> 0 | BP20: =SUMIFS(Imput[[Importe Neto]:[Importe Neto]],Imput[[C. Imp.]:[C. Imp.]],$D20,Imput[[PERIODO Imp.]:[PERIODO Imp.]],BP$9) -> 0 | BQ20: =SUMIFS(Imput[[Importe Neto]:[Importe Neto]],Imput[[C. Imp.]:[C. Imp.]],$D20,Imput[[PERIODO Imp.]:[PERIODO Imp.]],BQ$9) -> 0 | BR20: =SUMIFS(Imput[[Importe Neto]:[Importe Neto]],Imput[[C. Imp.]:[C. Imp.]],$D20,Imput[[PERIODO Imp.]:[PERIODO Imp.]],BR$9) -> 0 | BS20: =SUMIFS(Imput[[Importe Neto]:[Importe Neto]],Imput[[C. Imp.]:[C. Imp.]],$D20,Imput[[PERIODO Imp.]:[PERIODO Imp.]],BS$9) -> 0 | BT20: =SUMIFS(Imput[[Importe Neto]:[Importe Neto]],Imput[[C. Imp.]:[C. Imp.]],$D20,Imput[[PERIODO Imp.]:[PERIODO Imp.]],BT$9) -> 0 | ... DH20: =SUMIFS(Imput[[Importe Neto]:[Importe Neto]],Imput[[C. Imp.]:[C. Imp.]],$D20,Imput[[PERIODO Imp.]:[PERIODO Imp.]],DH$9) -> 0
A21: =IF(J21="","",IF(J21=0,"","Imprimir")) -> Imprimir | D21: MAN-P1-5 | E21: SUBCONTRATO DE EXCAVACIÓN POR MEDIOS MECÁNICOS | G21: 1100 | H21: =Producción!G12*2.5 -> 42.5 | I21: =IF(E21>0,$J$5,"") -> 1 | J21: =IFERROR(G21*H21*I21,"") -> 46750 | L21: 0.5 | R21: 0.05 | T21: 0.05 | V21: 0.05 | X21: 0.05 | Z21: 0.05 | AB21: 0.05 | AD21: 0.05 | AF21: 0.05 | AJ21: 0.1 | BJ21: =IFERROR(BK21/J21,0) -> 2.3001034 | BK21: =SUM(BM21:DH21) -> 107529.83 | BM21: =SUMIFS(Imput[[Importe Neto]:[Importe Neto]],Imput[[C. Imp.]:[C. Imp.]],$D21,Imput[[PERIODO Imp.]:[PERIODO Imp.]],BM$9) -> 0 | BN21: =SUMIFS(Imput[[Importe Neto]:[Importe Neto]],Imput[[C. Imp.]:[C. Imp.]],$D21,Imput[[PERIODO Imp.]:[PERIODO Imp.]],BN$9) -> 0 | BO21: =SUMIFS(Imput[[Importe Neto]:[Importe Neto]],Imput[[C. Imp.]:[C. Imp.]],$D21,Imput[[PERIODO Imp.]:[PERIODO Imp.]],BO$9) -> 0 | BP21: =SUMIFS(Imput[[Importe Neto]:[Importe Neto]],Imput[[C. Imp.]:[C. Imp.]],$D21,Imput[[PERIODO Imp.]:[PERIODO Imp.]],BP$9) -> 2445.0016 | BQ21: =SUMIFS(Imput[[Importe Neto]:[Importe Neto]],Imput[[C. Imp.]:[C. Imp.]],$D21,Imput[[PERIODO Imp.]:[PERIODO Imp.]],BQ$9) -> 29455.531 | BR21: =SUMIFS(Imput[[Importe Neto]:[Importe Neto]],Imput[[C. Imp.]:[C. Imp.]],$D21,Imput[[PERIODO Imp.]:[PERIODO Imp.]],BR$9) -> 75629.3 | BS21: =SUMIFS(Imput[[Importe Neto]:[Importe Neto]],Imput[[C. Imp.]:[C. Imp.]],$D21,Imput[[PERIODO Imp.]:[PERIODO Imp.]],BS$9) -> 0 | BT21: =SUMIFS(Imput[[Importe Neto]:[Importe Neto]],Imput[[C. Imp.]:[C. Imp.]],$D21,Imput[[PERIODO Imp.]:[PERIODO Imp.]],BT$9) -> 0 | ... DH21: =SUMIFS(Imput[[Importe Neto]:[Importe Neto]],Imput[[C. Imp.]:[C. Imp.]],$D21,Imput[[PERIODO Imp.]:[PERIODO Imp.]],DH$9) -> 0
A22: =IF(J22="","",IF(J22=0,"","Imprimir")) -> Imprimir | D22: MAN-P1-6 | E22: SUBCONTRATO DE GROUT Y BANQUETA (lote 10 pilas) | G22: 5000 | H22: =Producción!G12*0.1 -> 1.7 | I22: =IF(E22>0,$J$5,"") -> 1 | J22: =IFERROR(G22*H22*I22,"") -> 8500 | L22: 0.3 | N22: 0.05 | P22: 0.05 | R22: 0.05 | T22: 0.05 | V22: 0.05 | X22: 0.05 | Z22: 0.05 | AB22: 0.05 | AD22: 0.05 | AF22: 0.05 | AH22: 0.05 | AJ22: 0.15 | BJ22: =IFERROR(BK22/J22,0) -> 1.3314635 | BK22: =SUM(BM22:DH22) -> 11317.44 | BM22: =SUMIFS(Imput[[Importe Neto]:[Importe Neto]],Imput[[C. Imp.]:[C. Imp.]],$D22,Imput[[PERIODO Imp.]:[PERIODO Imp.]],BM$9) -> 0 | BN22: =SUMIFS(Imput[[Importe Neto]:[Importe Neto]],Imput[[C. Imp.]:[C. Imp.]],$D22,Imput[[PERIODO Imp.]:[PERIODO Imp.]],BN$9) -> 0 | BO22: =SUMIFS(Imput[[Importe Neto]:[Importe Neto]],Imput[[C. Imp.]:[C. Imp.]],$D22,Imput[[PERIODO Imp.]:[PERIODO Imp.]],BO$9) -> 0 | BP22: =SUMIFS(Imput[[Importe Neto]:[Importe Neto]],Imput[[C. Imp.]:[C. Imp.]],$D22,Imput[[PERIODO Imp.]:[PERIODO Imp.]],BP$9) -> 389.99973 | BQ22: =SUMIFS(Imput[[Importe Neto]:[Importe Neto]],Imput[[C. Imp.]:[C. Imp.]],$D22,Imput[[PERIODO Imp.]:[PERIODO Imp.]],BQ$9) -> 0 | BR22: =SUMIFS(Imput[[Importe Neto]:[Importe Neto]],Imput[[C. Imp.]:[C. Imp.]],$D22,Imput[[PERIODO Imp.]:[PERIODO Imp.]],BR$9) -> 10927.44 | BS22: =SUMIFS(Imput[[Importe Neto]:[Importe Neto]],Imput[[C. Imp.]:[C. Imp.]],$D22,Imput[[PERIODO Imp.]:[PERIODO Imp.]],BS$9) -> 0 | BT22: =SUMIFS(Imput[[Importe Neto]:[Importe Neto]],Imput[[C. Imp.]:[C. Imp.]],$D22,Imput[[PERIODO Imp.]:[PERIODO Imp.]],BT$9) -> 0 | ... DH22: =SUMIFS(Imput[[Importe Neto]:[Importe Neto]],Imput[[C. Imp.]:[C. Imp.]],$D22,Imput[[PERIODO Imp.]:[PERIODO Imp.]],DH$9) -> 0
A23: =IF(J23="","",IF(J23=0,"","Imprimir")) | D23: MAN-P1-7 | I23: =IF(E23>0,$J$5,"") | J23: =IFERROR(G23*H23*I23,"") | BJ23: =IFERROR(BK23/J23,0) -> 0 | BK23: =SUM(BM23:DH23) -> 0 | BM23: =SUMIFS(Imput[[Importe Neto]:[Importe Neto]],Imput[[C. Imp.]:[C. Imp.]],$D23,Imput[[PERIODO Imp.]:[PERIODO Imp.]],BM$9) -> 0 | BN23: =SUMIFS(Imput[[Importe Neto]:[Importe Neto]],Imput[[C. Imp.]:[C. Imp.]],$D23,Imput[[PERIODO Imp.]:[PERIODO Imp.]],BN$9) -> 0 | BO23: =SUMIFS(Imput[[Importe Neto]:[Importe Neto]],Imput[[C. Imp.]:[C. Imp.]],$D23,Imput[[PERIODO Imp.]:[PERIODO Imp.]],BO$9) -> 0 | BP23: =SUMIFS(Imput[[Importe Neto]:[Importe Neto]],Imput[[C. Imp.]:[C. Imp.]],$D23,Imput[[PERIODO Imp.]:[PERIODO Imp.]],BP$9) -> 0 | BQ23: =SUMIFS(Imput[[Importe Neto]:[Importe Neto]],Imput[[C. Imp.]:[C. Imp.]],$D23,Imput[[PERIODO Imp.]:[PERIODO Imp.]],BQ$9) -> 0 | BR23: =SUMIFS(Imput[[Importe Neto]:[Importe Neto]],Imput[[C. Imp.]:[C. Imp.]],$D23,Imput[[PERIODO Imp.]:[PERIODO Imp.]],BR$9) -> 0 | BS23: =SUMIFS(Imput[[Importe Neto]:[Importe Neto]],Imput[[C. Imp.]:[C. Imp.]],$D23,Imput[[PERIODO Imp.]:[PERIODO Imp.]],BS$9) -> 0 | BT23: =SUMIFS(Imput[[Importe Neto]:[Importe Neto]],Imput[[C. Imp.]:[C. Imp.]],$D23,Imput[[PERIODO Imp.]:[PERIODO Imp.]],BT$9) -> 0 | ... DH23: =SUMIFS(Imput[[Importe Neto]:[Importe Neto]],Imput[[C. Imp.]:[C. Imp.]],$D23,Imput[[PERIODO Imp.]:[PERIODO Imp.]],DH$9) -> 0
A24: =IF(J24="","",IF(J24=0,"","Imprimir")) | D24: MAN-P1-8 | I24: =IF(E24>0,$J$5,"") | J24: =IFERROR(G24*H24*I24,"") | BJ24: =IFERROR(BK24/J24,0) -> 0 | BK24: =SUM(BM24:DH24) -> 0 | BM24: =SUMIFS(Imput[[Importe Neto]:[Importe Neto]],Imput[[C. Imp.]:[C. Imp.]],$D24,Imput[[PERIODO Imp.]:[PERIODO Imp.]],BM$9) -> 0 | BN24: =SUMIFS(Imput[[Importe Neto]:[Importe Neto]],Imput[[C. Imp.]:[C. Imp.]],$D24,Imput[[PERIODO Imp.]:[PERIODO Imp.]],BN$9) -> 0 | BO24: =SUMIFS(Imput[[Importe Neto]:[Importe Neto]],Imput[[C. Imp.]:[C. Imp.]],$D24,Imput[[PERIODO Imp.]:[PERIODO Imp.]],BO$9) -> 0 | BP24: =SUMIFS(Imput[[Importe Neto]:[Importe Neto]],Imput[[C. Imp.]:[C. Imp.]],$D24,Imput[[PERIODO Imp.]:[PERIODO Imp.]],BP$9) -> 0 | BQ24: =SUMIFS(Imput[[Importe Neto]:[Importe Neto]],Imput[[C. Imp.]:[C. Imp.]],$D24,Imput[[PERIODO Imp.]:[PERIODO Imp.]],BQ$9) -> 0 | BR24: =SUMIFS(Imput[[Importe Neto]:[Importe Neto]],Imput[[C. Imp.]:[C. Imp.]],$D24,Imput[[PERIODO Imp.]:[PERIODO Imp.]],BR$9) -> 0 | BS24: =SUMIFS(Imput[[Importe Neto]:[Importe Neto]],Imput[[C. Imp.]:[C. Imp.]],$D24,Imput[[PERIODO Imp.]:[PERIODO Imp.]],BS$9) -> 0 | BT24: =SUMIFS(Imput[[Importe Neto]:[Importe Neto]],Imput[[C. Imp.]:[C. Imp.]],$D24,Imput[[PERIODO Imp.]:[PERIODO Imp.]],BT$9) -> 0 | ... DH24: =SUMIFS(Imput[[Importe Neto]:[Importe Neto]],Imput[[C. Imp.]:[C. Imp.]],$D24,Imput[[PERIODO Imp.]:[PERIODO Imp.]],DH$9) -> 0
A25: =IF(J14>0,"Imprimir","") -> Imprimir
A26: =IF(J26>0,"Imprimir","") -> Imprimir | D26: P2 | E26: MAQUINARIA | J26: =SUBTOTAL(9,J29:J67) -> 4513.5 | L26: =SUMPRODUCT($J29:$J67,L29:L67) -> 1354.05 | M26: =SUMPRODUCT($J29:$J67,M29:M67) -> 0 | N26: =SUMPRODUCT($J29:$J67,N29:N67) -> 0 | O26: =SUMPRODUCT($J29:$J67,O29:O67) -> 0 | P26: =SUMPRODUCT($J29:$J67,P29:P67) -> 1354.05 | Q26: =SUMPRODUCT($J29:$J67,Q29:Q67) -> 0 | R26: =SUMPRODUCT($J29:$J67,R29:R67) -> 0 | S26: =SUMPRODUCT($J29:$J67,S29:S67) -> 0 | ... BG26: =SUMPRODUCT($J29:$J67,BG29:BG67) -> 0 | BJ26: =IFERROR(BK26/J26,0) -> 1.6450648 | BK26: =SUBTOTAL(9,BK27:BK67) -> 7425 | BM26: =SUBTOTAL(9,BM27:BM67) -> 0 | BN26: =SUBTOTAL(9,BN27:BN67) -> 0 | BO26: =SUBTOTAL(9,BO27:BO67) -> 0 | BP26: =SUBTOTAL(9,BP27:BP67) -> 0 | BQ26: =SUBTOTAL(9,BQ27:BQ67) -> 0 | BR26: =SUBTOTAL(9,BR27:BR67) -> 7425 | BS26: =SUBTOTAL(9,BS27:BS67) -> 0 | BT26: =SUBTOTAL(9,BT27:BT67) -> 0 | ... DH26: =SUBTOTAL(9,DH27:DH67) -> 0
A27: =IF(J26>0,"Imprimir","") -> Imprimir | F27: Proveedor | G27: Costo Empresa | H27: Cantidad | I27: Meses | J27: Importe
A28: =IF(J28>0,"Imprimir","") -> Imprimir | J28: =SUBTOTAL(9,J29:J67) -> 4513.5
A29: =IF(J29="","",IF(J29=0,"","Imprimir")) -> Imprimir | D29: MAN-P2-1 | E29: CORTADORA DE CONCRETO | G29: 500 | H29: =Producción!G12*0.275 -> 4.675 | I29: =IF(E29>0,$J$5,"") -> 1 | J29: =IFERROR(G29*H29*I29,"") -> 2337.5 | L29: 0.3 | P29: 0.3 | W29: 0.3 | AE29: 0.1 | BJ29: =IFERROR(BK29/J29,0) -> 3.1764706 | BK29: =SUM(BM29:DH29) -> 7425 | BM29: =SUMIFS(Imput[[Importe Neto]:[Importe Neto]],Imput[[C. Imp.]:[C. Imp.]],$D29,Imput[[PERIODO Imp.]:[PERIODO Imp.]],BM$9) -> 0 | BN29: =SUMIFS(Imput[[Importe Neto]:[Importe Neto]],Imput[[C. Imp.]:[C. Imp.]],$D29,Imput[[PERIODO Imp.]:[PERIODO Imp.]],BN$9) -> 0 | BO29: =SUMIFS(Imput[[Importe Neto]:[Importe Neto]],Imput[[C. Imp.]:[C. Imp.]],$D29,Imput[[PERIODO Imp.]:[PERIODO Imp.]],BO$9) -> 0 | BP29: =SUMIFS(Imput[[Importe Neto]:[Importe Neto]],Imput[[C. Imp.]:[C. Imp.]],$D29,Imput[[PERIODO Imp.]:[PERIODO Imp.]],BP$9) -> 0 | BQ29: =SUMIFS(Imput[[Importe Neto]:[Importe Neto]],Imput[[C. Imp.]:[C. Imp.]],$D29,Imput[[PERIODO Imp.]:[PERIODO Imp.]],BQ$9) -> 0 | BR29: =SUMIFS(Imput[[Importe Neto]:[Importe Neto]],Imput[[C. Imp.]:[C. Imp.]],$D29,Imput[[PERIODO Imp.]:[PERIODO Imp.]],BR$9) -> 7425 | BS29: =SUMIFS(Imput[[Importe Neto]:[Importe Neto]],Imput[[C. Imp.]:[C. Imp.]],$D29,Imput[[PERIODO Imp.]:[PERIODO Imp.]],BS$9) -> 0 | BT29: =SUMIFS(Imput[[Importe Neto]:[Importe Neto]],Imput[[C. Imp.]:[C. Imp.]],$D29,Imput[[PERIODO Imp.]:[PERIODO Imp.]],BT$9) -> 0 | ... DH29: =SUMIFS(Imput[[Importe Neto]:[Importe Neto]],Imput[[C. Imp.]:[C. Imp.]],$D29,Imput[[PERIODO Imp.]:[PERIODO Imp.]],DH$9) -> 0
A30: =IF(J30="","",IF(J30=0,"","Imprimir")) -> Imprimir | D30: MAN-P2-2 | E30: VIBRADOR DE CONCRETO | G30: 500 | H30: =Producción!G12*0.25 -> 4.25 | I30: =IF(E30>0,$J$5,"") -> 1 | J30: =IFERROR(G30*H30*I30,"") -> 2125 | L30: 0.3 | P30: 0.3 | W30: 0.3 | AE30: 0.1 | BJ30: =IFERROR(BK30/J30,0) -> 0 | BK30: =SUM(BM30:DH30) -> 0 | BM30: =SUMIFS(Imput[[Importe Neto]:[Importe Neto]],Imput[[C. Imp.]:[C. Imp.]],$D30,Imput[[PERIODO Imp.]:[PERIODO Imp.]],BM$9) -> 0 | BN30: =SUMIFS(Imput[[Importe Neto]:[Importe Neto]],Imput[[C. Imp.]:[C. Imp.]],$D30,Imput[[PERIODO Imp.]:[PERIODO Imp.]],BN$9) -> 0 | BO30: =SUMIFS(Imput[[Importe Neto]:[Importe Neto]],Imput[[C. Imp.]:[C. Imp.]],$D30,Imput[[PERIODO Imp.]:[PERIODO Imp.]],BO$9) -> 0 | BP30: =SUMIFS(Imput[[Importe Neto]:[Importe Neto]],Imput[[C. Imp.]:[C. Imp.]],$D30,Imput[[PERIODO Imp.]:[PERIODO Imp.]],BP$9) -> 0 | BQ30: =SUMIFS(Imput[[Importe Neto]:[Importe Neto]],Imput[[C. Imp.]:[C. Imp.]],$D30,Imput[[PERIODO Imp.]:[PERIODO Imp.]],BQ$9) -> 0 | BR30: =SUMIFS(Imput[[Importe Neto]:[Importe Neto]],Imput[[C. Imp.]:[C. Imp.]],$D30,Imput[[PERIODO Imp.]:[PERIODO Imp.]],BR$9) -> 0 | BS30: =SUMIFS(Imput[[Importe Neto]:[Importe Neto]],Imput[[C. Imp.]:[C. Imp.]],$D30,Imput[[PERIODO Imp.]:[PERIODO Imp.]],BS$9) -> 0 | BT30: =SUMIFS(Imput[[Importe Neto]:[Importe Neto]],Imput[[C. Imp.]:[C. Imp.]],$D30,Imput[[PERIODO Imp.]:[PERIODO Imp.]],BT$9) -> 0 | ... DH30: =SUMIFS(Imput[[Importe Neto]:[Importe Neto]],Imput[[C. Imp.]:[C. Imp.]],$D30,Imput[[PERIODO Imp.]:[PERIODO Imp.]],DH$9) -> 0
A31: =IF(J31="","",IF(J31=0,"","Imprimir")) -> Imprimir | D31: MAN-P2-3 | E31: VIBROCOMPACTADOR MANUAL | G31: 300 | H31: =Producción!G12*0.01 -> 0.17 | I31: =IF(E31>0,$J$5,"") -> 1 | J31: =IFERROR(G31*H31*I31,"") -> 51 | L31: 0.3 | P31: 0.3 | W31: 0.3 | AE31: 0.1 | BJ31: =IFERROR(BK31/J31,0) -> 0 | BK31: =SUM(BM31:DH31) -> 0 | BM31: =SUMIFS(Imput[[Importe Neto]:[Importe Neto]],Imput[[C. Imp.]:[C. Imp.]],$D31,Imput[[PERIODO Imp.]:[PERIODO Imp.]],BM$9) -> 0 | BN31: =SUMIFS(Imput[[Importe Neto]:[Importe Neto]],Imput[[C. Imp.]:[C. Imp.]],$D31,Imput[[PERIODO Imp.]:[PERIODO Imp.]],BN$9) -> 0 | BO31: =SUMIFS(Imput[[Importe Neto]:[Importe Neto]],Imput[[C. Imp.]:[C. Imp.]],$D31,Imput[[PERIODO Imp.]:[PERIODO Imp.]],BO$9) -> 0 | BP31: =SUMIFS(Imput[[Importe Neto]:[Importe Neto]],Imput[[C. Imp.]:[C. Imp.]],$D31,Imput[[PERIODO Imp.]:[PERIODO Imp.]],BP$9) -> 0 | BQ31: =SUMIFS(Imput[[Importe Neto]:[Importe Neto]],Imput[[C. Imp.]:[C. Imp.]],$D31,Imput[[PERIODO Imp.]:[PERIODO Imp.]],BQ$9) -> 0 | BR31: =SUMIFS(Imput[[Importe Neto]:[Importe Neto]],Imput[[C. Imp.]:[C. Imp.]],$D31,Imput[[PERIODO Imp.]:[PERIODO Imp.]],BR$9) -> 0 | BS31: =SUMIFS(Imput[[Importe Neto]:[Importe Neto]],Imput[[C. Imp.]:[C. Imp.]],$D31,Imput[[PERIODO Imp.]:[PERIODO Imp.]],BS$9) -> 0 | BT31: =SUMIFS(Imput[[Importe Neto]:[Importe Neto]],Imput[[C. Imp.]:[C. Imp.]],$D31,Imput[[PERIODO Imp.]:[PERIODO Imp.]],BT$9) -> 0 | ... DH31: =SUMIFS(Imput[[Importe Neto]:[Importe Neto]],Imput[[C. Imp.]:[C. Imp.]],$D31,Imput[[PERIODO Imp.]:[PERIODO Imp.]],DH$9) -> 0
A32: =IF(J32="","",IF(J32=0,"","Imprimir")) | D32: MAN-P2-4 | I32: =IF(E32>0,$J$5,"") | J32: =IFERROR(G32*H32*I32,"") | BJ32: =IFERROR(BK32/J32,0) -> 0 | BK32: =SUM(BM32:DH32) -> 0 | BM32: =SUMIFS(Imput[[Importe Neto]:[Importe Neto]],Imput[[C. Imp.]:[C. Imp.]],$D32,Imput[[PERIODO Imp.]:[PERIODO Imp.]],BM$9) -> 0 | BN32: =SUMIFS(Imput[[Importe Neto]:[Importe Neto]],Imput[[C. Imp.]:[C. Imp.]],$D32,Imput[[PERIODO Imp.]:[PERIODO Imp.]],BN$9) -> 0 | BO32: =SUMIFS(Imput[[Importe Neto]:[Importe Neto]],Imput[[C. Imp.]:[C. Imp.]],$D32,Imput[[PERIODO Imp.]:[PERIODO Imp.]],BO$9) -> 0 | BP32: =SUMIFS(Imput[[Importe Neto]:[Importe Neto]],Imput[[C. Imp.]:[C. Imp.]],$D32,Imput[[PERIODO Imp.]:[PERIODO Imp.]],BP$9) -> 0 | BQ32: =SUMIFS(Imput[[Importe Neto]:[Importe Neto]],Imput[[C. Imp.]:[C. Imp.]],$D32,Imput[[PERIODO Imp.]:[PERIODO Imp.]],BQ$9) -> 0 | BR32: =SUMIFS(Imput[[Importe Neto]:[Importe Neto]],Imput[[C. Imp.]:[C. Imp.]],$D32,Imput[[PERIODO Imp.]:[PERIODO Imp.]],BR$9) -> 0 | BS32: =SUMIFS(Imput[[Importe Neto]:[Importe Neto]],Imput[[C. Imp.]:[C. Imp.]],$D32,Imput[[PERIODO Imp.]:[PERIODO Imp.]],BS$9) -> 0 | BT32: =SUMIFS(Imput[[Importe Neto]:[Importe Neto]],Imput[[C. Imp.]:[C. Imp.]],$D32,Imput[[PERIODO Imp.]:[PERIODO Imp.]],BT$9) -> 0 | ... DH32: =SUMIFS(Imput[[Importe Neto]:[Importe Neto]],Imput[[C. Imp.]:[C. Imp.]],$D32,Imput[[PERIODO Imp.]:[PERIODO Imp.]],DH$9) -> 0
A33: =IF(J33="","",IF(J33=0,"","Imprimir")) | D33: MAN-P2-5 | I33: =IF(E33>0,$J$5,"") | J33: =IFERROR(G33*H33*I33,"") | BJ33: =IFERROR(BK33/J33,0) -> 0 | BK33: =SUM(BM33:DH33) -> 0 | BM33: =SUMIFS(Imput[[Importe Neto]:[Importe Neto]],Imput[[C. Imp.]:[C. Imp.]],$D33,Imput[[PERIODO Imp.]:[PERIODO Imp.]],BM$9) -> 0 | BN33: =SUMIFS(Imput[[Importe Neto]:[Importe Neto]],Imput[[C. Imp.]:[C. Imp.]],$D33,Imput[[PERIODO Imp.]:[PERIODO Imp.]],BN$9) -> 0 | BO33: =SUMIFS(Imput[[Importe Neto]:[Importe Neto]],Imput[[C. Imp.]:[C. Imp.]],$D33,Imput[[PERIODO Imp.]:[PERIODO Imp.]],BO$9) -> 0 | BP33: =SUMIFS(Imput[[Importe Neto]:[Importe Neto]],Imput[[C. Imp.]:[C. Imp.]],$D33,Imput[[PERIODO Imp.]:[PERIODO Imp.]],BP$9) -> 0 | BQ33: =SUMIFS(Imput[[Importe Neto]:[Importe Neto]],Imput[[C. Imp.]:[C. Imp.]],$D33,Imput[[PERIODO Imp.]:[PERIODO Imp.]],BQ$9) -> 0 | BR33: =SUMIFS(Imput[[Importe Neto]:[Importe Neto]],Imput[[C. Imp.]:[C. Imp.]],$D33,Imput[[PERIODO Imp.]:[PERIODO Imp.]],BR$9) -> 0 | BS33: =SUMIFS(Imput[[Importe Neto]:[Importe Neto]],Imput[[C. Imp.]:[C. Imp.]],$D33,Imput[[PERIODO Imp.]:[PERIODO Imp.]],BS$9) -> 0 | BT33: =SUMIFS(Imput[[Importe Neto]:[Importe Neto]],Imput[[C. Imp.]:[C. Imp.]],$D33,Imput[[PERIODO Imp.]:[PERIODO Imp.]],BT$9) -> 0 | ... DH33: =SUMIFS(Imput[[Importe Neto]:[Importe Neto]],Imput[[C. Imp.]:[C. Imp.]],$D33,Imput[[PERIODO Imp.]:[PERIODO Imp.]],DH$9) -> 0
A34: =IF(J34="","",IF(J34=0,"","Imprimir")) | D34: MAN-P2-6 | I34: =IF(E34>0,$J$5,"") | J34: =IFERROR(G34*H34*I34,"") | BJ34: =IFERROR(BK34/J34,0) -> 0 | BK34: =SUM(BM34:DH34) -> 0 | BM34: =SUMIFS(Imput[[Importe Neto]:[Importe Neto]],Imput[[C. Imp.]:[C. Imp.]],$D34,Imput[[PERIODO Imp.]:[PERIODO Imp.]],BM$9) -> 0 | BN34: =SUMIFS(Imput[[Importe Neto]:[Importe Neto]],Imput[[C. Imp.]:[C. Imp.]],$D34,Imput[[PERIODO Imp.]:[PERIODO Imp.]],BN$9) -> 0 | BO34: =SUMIFS(Imput[[Importe Neto]:[Importe Neto]],Imput[[C. Imp.]:[C. Imp.]],$D34,Imput[[PERIODO Imp.]:[PERIODO Imp.]],BO$9) -> 0 | BP34: =SUMIFS(Imput[[Importe Neto]:[Importe Neto]],Imput[[C. Imp.]:[C. Imp.]],$D34,Imput[[PERIODO Imp.]:[PERIODO Imp.]],BP$9) -> 0 | BQ34: =SUMIFS(Imput[[Importe Neto]:[Importe Neto]],Imput[[C. Imp.]:[C. Imp.]],$D34,Imput[[PERIODO Imp.]:[PERIODO Imp.]],BQ$9) -> 0 | BR34: =SUMIFS(Imput[[Importe Neto]:[Importe Neto]],Imput[[C. Imp.]:[C. Imp.]],$D34,Imput[[PERIODO Imp.]:[PERIODO Imp.]],BR$9) -> 0 | BS34: =SUMIFS(Imput[[Importe Neto]:[Importe Neto]],Imput[[C. Imp.]:[C. Imp.]],$D34,Imput[[PERIODO Imp.]:[PERIODO Imp.]],BS$9) -> 0 | BT34: =SUMIFS(Imput[[Importe Neto]:[Importe Neto]],Imput[[C. Imp.]:[C. Imp.]],$D34,Imput[[PERIODO Imp.]:[PERIODO Imp.]],BT$9) -> 0 | ... DH34: =SUMIFS(Imput[[Importe Neto]:[Importe Neto]],Imput[[C. Imp.]:[C. Imp.]],$D34,Imput[[PERIODO Imp.]:[PERIODO Imp.]],DH$9) -> 0
A35: =IF(J35="","",IF(J35=0,"","Imprimir")) | D35: MAN-P2-7 | I35: =IF(E35>0,$J$5,"") | J35: =IFERROR(G35*H35*I35,"") | BJ35: =IFERROR(BK35/J35,0) -> 0 | BK35: =SUM(BM35:DH35) -> 0 | BM35: =SUMIFS(Imput[[Importe Neto]:[Importe Neto]],Imput[[C. Imp.]:[C. Imp.]],$D35,Imput[[PERIODO Imp.]:[PERIODO Imp.]],BM$9) -> 0 | BN35: =SUMIFS(Imput[[Importe Neto]:[Importe Neto]],Imput[[C. Imp.]:[C. Imp.]],$D35,Imput[[PERIODO Imp.]:[PERIODO Imp.]],BN$9) -> 0 | BO35: =SUMIFS(Imput[[Importe Neto]:[Importe Neto]],Imput[[C. Imp.]:[C. Imp.]],$D35,Imput[[PERIODO Imp.]:[PERIODO Imp.]],BO$9) -> 0 | BP35: =SUMIFS(Imput[[Importe Neto]:[Importe Neto]],Imput[[C. Imp.]:[C. Imp.]],$D35,Imput[[PERIODO Imp.]:[PERIODO Imp.]],BP$9) -> 0 | BQ35: =SUMIFS(Imput[[Importe Neto]:[Importe Neto]],Imput[[C. Imp.]:[C. Imp.]],$D35,Imput[[PERIODO Imp.]:[PERIODO Imp.]],BQ$9) -> 0 | BR35: =SUMIFS(Imput[[Importe Neto]:[Importe Neto]],Imput[[C. Imp.]:[C. Imp.]],$D35,Imput[[PERIODO Imp.]:[PERIODO Imp.]],BR$9) -> 0 | BS35: =SUMIFS(Imput[[Importe Neto]:[Importe Neto]],Imput[[C. Imp.]:[C. Imp.]],$D35,Imput[[PERIODO Imp.]:[PERIODO Imp.]],BS$9) -> 0 | BT35: =SUMIFS(Imput[[Importe Neto]:[Importe Neto]],Imput[[C. Imp.]:[C. Imp.]],$D35,Imput[[PERIODO Imp.]:[PERIODO Imp.]],BT$9) -> 0 | ... DH35: =SUMIFS(Imput[[Importe Neto]:[Importe Neto]],Imput[[C. Imp.]:[C. Imp.]],$D35,Imput[[PERIODO Imp.]:[PERIODO Imp.]],DH$9) -> 0
A36: =IF(J36="","",IF(J36=0,"","Imprimir")) | D36: MAN-P2-8 | I36: =IF(E36>0,$J$5,"") | J36: =IFERROR(G36*H36*I36,"") | BJ36: =IFERROR(BK36/J36,0) -> 0 | BK36: =SUM(BM36:DH36) -> 0 | BM36: =SUMIFS(Imput[[Importe Neto]:[Importe Neto]],Imput[[C. Imp.]:[C. Imp.]],$D36,Imput[[PERIODO Imp.]:[PERIODO Imp.]],BM$9) -> 0 | BN36: =SUMIFS(Imput[[Importe Neto]:[Importe Neto]],Imput[[C. Imp.]:[C. Imp.]],$D36,Imput[[PERIODO Imp.]:[PERIODO Imp.]],BN$9) -> 0 | BO36: =SUMIFS(Imput[[Importe Neto]:[Importe Neto]],Imput[[C. Imp.]:[C. Imp.]],$D36,Imput[[PERIODO Imp.]:[PERIODO Imp.]],BO$9) -> 0 | BP36: =SUMIFS(Imput[[Importe Neto]:[Importe Neto]],Imput[[C. Imp.]:[C. Imp.]],$D36,Imput[[PERIODO Imp.]:[PERIODO Imp.]],BP$9) -> 0 | BQ36: =SUMIFS(Imput[[Importe Neto]:[Importe Neto]],Imput[[C. Imp.]:[C. Imp.]],$D36,Imput[[PERIODO Imp.]:[PERIODO Imp.]],BQ$9) -> 0 | BR36: =SUMIFS(Imput[[Importe Neto]:[Importe Neto]],Imput[[C. Imp.]:[C. Imp.]],$D36,Imput[[PERIODO Imp.]:[PERIODO Imp.]],BR$9) -> 0 | BS36: =SUMIFS(Imput[[Importe Neto]:[Importe Neto]],Imput[[C. Imp.]:[C. Imp.]],$D36,Imput[[PERIODO Imp.]:[PERIODO Imp.]],BS$9) -> 0 | BT36: =SUMIFS(Imput[[Importe Neto]:[Importe Neto]],Imput[[C. Imp.]:[C. Imp.]],$D36,Imput[[PERIODO Imp.]:[PERIODO Imp.]],BT$9) -> 0 | ... DH36: =SUMIFS(Imput[[Importe Neto]:[Importe Neto]],Imput[[C. Imp.]:[C. Imp.]],$D36,Imput[[PERIODO Imp.]:[PERIODO Imp.]],DH$9) -> 0
A37: =IF(J37="","",IF(J37=0,"","Imprimir")) | D37: MAN-P2-9 | I37: =IF(E37>0,$J$5,"") | J37: =IFERROR(G37*H37*I37,"") | BJ37: =IFERROR(BK37/J37,0) -> 0 | BK37: =SUM(BM37:DH37) -> 0 | BM37: =SUMIFS(Imput[[Importe Neto]:[Importe Neto]],Imput[[C. Imp.]:[C. Imp.]],$D37,Imput[[PERIODO Imp.]:[PERIODO Imp.]],BM$9) -> 0 | BN37: =SUMIFS(Imput[[Importe Neto]:[Importe Neto]],Imput[[C. Imp.]:[C. Imp.]],$D37,Imput[[PERIODO Imp.]:[PERIODO Imp.]],BN$9) -> 0 | BO37: =SUMIFS(Imput[[Importe Neto]:[Importe Neto]],Imput[[C. Imp.]:[C. Imp.]],$D37,Imput[[PERIODO Imp.]:[PERIODO Imp.]],BO$9) -> 0 | BP37: =SUMIFS(Imput[[Importe Neto]:[Importe Neto]],Imput[[C. Imp.]:[C. Imp.]],$D37,Imput[[PERIODO Imp.]:[PERIODO Imp.]],BP$9) -> 0 | BQ37: =SUMIFS(Imput[[Importe Neto]:[Importe Neto]],Imput[[C. Imp.]:[C. Imp.]],$D37,Imput[[PERIODO Imp.]:[PERIODO Imp.]],BQ$9) -> 0 | BR37: =SUMIFS(Imput[[Importe Neto]:[Importe Neto]],Imput[[C. Imp.]:[C. Imp.]],$D37,Imput[[PERIODO Imp.]:[PERIODO Imp.]],BR$9) -> 0 | BS37: =SUMIFS(Imput[[Importe Neto]:[Importe Neto]],Imput[[C. Imp.]:[C. Imp.]],$D37,Imput[[PERIODO Imp.]:[PERIODO Imp.]],BS$9) -> 0 | BT37: =SUMIFS(Imput[[Importe Neto]:[Importe Neto]],Imput[[C. Imp.]:[C. Imp.]],$D37,Imput[[PERIODO Imp.]:[PERIODO Imp.]],BT$9) -> 0 | ... DH37: =SUMIFS(Imput[[Importe Neto]:[Importe Neto]],Imput[[C. Imp.]:[C. Imp.]],$D37,Imput[[PERIODO Imp.]:[PERIODO Imp.]],DH$9) -> 0
A38: =IF(J38="","",IF(J38=0,"","Imprimir")) | D38: MAN-P2-10 | I38: =IF(E38>0,$J$5,"") | J38: =IFERROR(G38*H38*I38,"") | BJ38: =IFERROR(BK38/J38,0) -> 0 | BK38: =SUM(BM38:DH38) -> 0 | BM38: =SUMIFS(Imput[[Importe Neto]:[Importe Neto]],Imput[[C. Imp.]:[C. Imp.]],$D38,Imput[[PERIODO Imp.]:[PERIODO Imp.]],BM$9) -> 0 | BN38: =SUMIFS(Imput[[Importe Neto]:[Importe Neto]],Imput[[C. Imp.]:[C. Imp.]],$D38,Imput[[PERIODO Imp.]:[PERIODO Imp.]],BN$9) -> 0 | BO38: =SUMIFS(Imput[[Importe Neto]:[Importe Neto]],Imput[[C. Imp.]:[C. Imp.]],$D38,Imput[[PERIODO Imp.]:[PERIODO Imp.]],BO$9) -> 0 | BP38: =SUMIFS(Imput[[Importe Neto]:[Importe Neto]],Imput[[C. Imp.]:[C. Imp.]],$D38,Imput[[PERIODO Imp.]:[PERIODO Imp.]],BP$9) -> 0 | BQ38: =SUMIFS(Imput[[Importe Neto]:[Importe Neto]],Imput[[C. Imp.]:[C. Imp.]],$D38,Imput[[PERIODO Imp.]:[PERIODO Imp.]],BQ$9) -> 0 | BR38: =SUMIFS(Imput[[Importe Neto]:[Importe Neto]],Imput[[C. Imp.]:[C. Imp.]],$D38,Imput[[PERIODO Imp.]:[PERIODO Imp.]],BR$9) -> 0 | BS38: =SUMIFS(Imput[[Importe Neto]:[Importe Neto]],Imput[[C. Imp.]:[C. Imp.]],$D38,Imput[[PERIODO Imp.]:[PERIODO Imp.]],BS$9) -> 0 | BT38: =SUMIFS(Imput[[Importe Neto]:[Importe Neto]],Imput[[C. Imp.]:[C. Imp.]],$D38,Imput[[PERIODO Imp.]:[PERIODO Imp.]],BT$9) -> 0 | ... DH38: =SUMIFS(Imput[[Importe Neto]:[Importe Neto]],Imput[[C. Imp.]:[C. Imp.]],$D38,Imput[[PERIODO Imp.]:[PERIODO Imp.]],DH$9) -> 0
A39: =IF(J39="","",IF(J39=0,"","Imprimir")) | D39: MAN-P2-11 | I39: =IF(E39>0,$J$5,"") | J39: =IFERROR(G39*H39*I39,"") | BJ39: =IFERROR(BK39/J39,0) -> 0 | BK39: =SUM(BM39:DH39) -> 0 | BM39: =SUMIFS(Imput[[Importe Neto]:[Importe Neto]],Imput[[C. Imp.]:[C. Imp.]],$D39,Imput[[PERIODO Imp.]:[PERIODO Imp.]],BM$9) -> 0 | BN39: =SUMIFS(Imput[[Importe Neto]:[Importe Neto]],Imput[[C. Imp.]:[C. Imp.]],$D39,Imput[[PERIODO Imp.]:[PERIODO Imp.]],BN$9) -> 0 | BO39: =SUMIFS(Imput[[Importe Neto]:[Importe Neto]],Imput[[C. Imp.]:[C. Imp.]],$D39,Imput[[PERIODO Imp.]:[PERIODO Imp.]],BO$9) -> 0 | BP39: =SUMIFS(Imput[[Importe Neto]:[Importe Neto]],Imput[[C. Imp.]:[C. Imp.]],$D39,Imput[[PERIODO Imp.]:[PERIODO Imp.]],BP$9) -> 0 | BQ39: =SUMIFS(Imput[[Importe Neto]:[Importe Neto]],Imput[[C. Imp.]:[C. Imp.]],$D39,Imput[[PERIODO Imp.]:[PERIODO Imp.]],BQ$9) -> 0 | BR39: =SUMIFS(Imput[[Importe Neto]:[Importe Neto]],Imput[[C. Imp.]:[C. Imp.]],$D39,Imput[[PERIODO Imp.]:[PERIODO Imp.]],BR$9) -> 0 | BS39: =SUMIFS(Imput[[Importe Neto]:[Importe Neto]],Imput[[C. Imp.]:[C. Imp.]],$D39,Imput[[PERIODO Imp.]:[PERIODO Imp.]],BS$9) -> 0 | BT39: =SUMIFS(Imput[[Importe Neto]:[Importe Neto]],Imput[[C. Imp.]:[C. Imp.]],$D39,Imput[[PERIODO Imp.]:[PERIODO Imp.]],BT$9) -> 0 | ... DH39: =SUMIFS(Imput[[Importe Neto]:[Importe Neto]],Imput[[C. Imp.]:[C. Imp.]],$D39,Imput[[PERIODO Imp.]:[PERIODO Imp.]],DH$9) -> 0
A40: =IF(J40="","",IF(J40=0,"","Imprimir")) | D40: MAN-P2-12 | I40: =IF(E40>0,$J$5,"") | J40: =IFERROR(G40*H40*I40,"") | BJ40: =IFERROR(BK40/J40,0) -> 0 | BK40: =SUM(BM40:DH40) -> 0 | BM40: =SUMIFS(Imput[[Importe Neto]:[Importe Neto]],Imput[[C. Imp.]:[C. Imp.]],$D40,Imput[[PERIODO Imp.]:[PERIODO Imp.]],BM$9) -> 0 | BN40: =SUMIFS(Imput[[Importe Neto]:[Importe Neto]],Imput[[C. Imp.]:[C. Imp.]],$D40,Imput[[PERIODO Imp.]:[PERIODO Imp.]],BN$9) -> 0 | BO40: =SUMIFS(Imput[[Importe Neto]:[Importe Neto]],Imput[[C. Imp.]:[C. Imp.]],$D40,Imput[[PERIODO Imp.]:[PERIODO Imp.]],BO$9) -> 0 | BP40: =SUMIFS(Imput[[Importe Neto]:[Importe Neto]],Imput[[C. Imp.]:[C. Imp.]],$D40,Imput[[PERIODO Imp.]:[PERIODO Imp.]],BP$9) -> 0 | BQ40: =SUMIFS(Imput[[Importe Neto]:[Importe Neto]],Imput[[C. Imp.]:[C. Imp.]],$D40,Imput[[PERIODO Imp.]:[PERIODO Imp.]],BQ$9) -> 0 | BR40: =SUMIFS(Imput[[Importe Neto]:[Importe Neto]],Imput[[C. Imp.]:[C. Imp.]],$D40,Imput[[PERIODO Imp.]:[PERIODO Imp.]],BR$9) -> 0 | BS40: =SUMIFS(Imput[[Importe Neto]:[Importe Neto]],Imput[[C. Imp.]:[C. Imp.]],$D40,Imput[[PERIODO Imp.]:[PERIODO Imp.]],BS$9) -> 0 | BT40: =SUMIFS(Imput[[Importe Neto]:[Importe Neto]],Imput[[C. Imp.]:[C. Imp.]],$D40,Imput[[PERIODO Imp.]:[PERIODO Imp.]],BT$9) -> 0 | ... DH40: =SUMIFS(Imput[[Importe Neto]:[Importe Neto]],Imput[[C. Imp.]:[C. Imp.]],$D40,Imput[[PERIODO Imp.]:[PERIODO Imp.]],DH$9) -> 0
A41: =IF(J41="","",IF(J41=0,"","Imprimir")) | D41: MAN-P2-13 | I41: =IF(E41>0,$J$5,"") | J41: =IFERROR(G41*H41*I41,"") | BJ41: =IFERROR(BK41/J41,0) -> 0 | BK41: =SUM(BM41:DH41) -> 0 | BM41: =SUMIFS(Imput[[Importe Neto]:[Importe Neto]],Imput[[C. Imp.]:[C. Imp.]],$D41,Imput[[PERIODO Imp.]:[PERIODO Imp.]],BM$9) -> 0 | BN41: =SUMIFS(Imput[[Importe Neto]:[Importe Neto]],Imput[[C. Imp.]:[C. Imp.]],$D41,Imput[[PERIODO Imp.]:[PERIODO Imp.]],BN$9) -> 0 | BO41: =SUMIFS(Imput[[Importe Neto]:[Importe Neto]],Imput[[C. Imp.]:[C. Imp.]],$D41,Imput[[PERIODO Imp.]:[PERIODO Imp.]],BO$9) -> 0 | BP41: =SUMIFS(Imput[[Importe Neto]:[Importe Neto]],Imput[[C. Imp.]:[C. Imp.]],$D41,Imput[[PERIODO Imp.]:[PERIODO Imp.]],BP$9) -> 0 | BQ41: =SUMIFS(Imput[[Importe Neto]:[Importe Neto]],Imput[[C. Imp.]:[C. Imp.]],$D41,Imput[[PERIODO Imp.]:[PERIODO Imp.]],BQ$9) -> 0 | BR41: =SUMIFS(Imput[[Importe Neto]:[Importe Neto]],Imput[[C. Imp.]:[C. Imp.]],$D41,Imput[[PERIODO Imp.]:[PERIODO Imp.]],BR$9) -> 0 | BS41: =SUMIFS(Imput[[Importe Neto]:[Importe Neto]],Imput[[C. Imp.]:[C. Imp.]],$D41,Imput[[PERIODO Imp.]:[PERIODO Imp.]],BS$9) -> 0 | BT41: =SUMIFS(Imput[[Importe Neto]:[Importe Neto]],Imput[[C. Imp.]:[C. Imp.]],$D41,Imput[[PERIODO Imp.]:[PERIODO Imp.]],BT$9) -> 0 | ... DH41: =SUMIFS(Imput[[Importe Neto]:[Importe Neto]],Imput[[C. Imp.]:[C. Imp.]],$D41,Imput[[PERIODO Imp.]:[PERIODO Imp.]],DH$9) -> 0
A42: =IF(J42="","",IF(J42=0,"","Imprimir")) | D42: MAN-P2-14 | I42: =IF(E42>0,$J$5,"") | J42: =IFERROR(G42*H42*I42,"") | BJ42: =IFERROR(BK42/J42,0) -> 0 | BK42: =SUM(BM42:DH42) -> 0 | BM42: =SUMIFS(Imput[[Importe Neto]:[Importe Neto]],Imput[[C. Imp.]:[C. Imp.]],$D42,Imput[[PERIODO Imp.]:[PERIODO Imp.]],BM$9) -> 0 | BN42: =SUMIFS(Imput[[Importe Neto]:[Importe Neto]],Imput[[C. Imp.]:[C. Imp.]],$D42,Imput[[PERIODO Imp.]:[PERIODO Imp.]],BN$9) -> 0 | BO42: =SUMIFS(Imput[[Importe Neto]:[Importe Neto]],Imput[[C. Imp.]:[C. Imp.]],$D42,Imput[[PERIODO Imp.]:[PERIODO Imp.]],BO$9) -> 0 | BP42: =SUMIFS(Imput[[Importe Neto]:[Importe Neto]],Imput[[C. Imp.]:[C. Imp.]],$D42,Imput[[PERIODO Imp.]:[PERIODO Imp.]],BP$9) -> 0 | BQ42: =SUMIFS(Imput[[Importe Neto]:[Importe Neto]],Imput[[C. Imp.]:[C. Imp.]],$D42,Imput[[PERIODO Imp.]:[PERIODO Imp.]],BQ$9) -> 0 | BR42: =SUMIFS(Imput[[Importe Neto]:[Importe Neto]],Imput[[C. Imp.]:[C. Imp.]],$D42,Imput[[PERIODO Imp.]:[PERIODO Imp.]],BR$9) -> 0 | BS42: =SUMIFS(Imput[[Importe Neto]:[Importe Neto]],Imput[[C. Imp.]:[C. Imp.]],$D42,Imput[[PERIODO Imp.]:[PERIODO Imp.]],BS$9) -> 0 | BT42: =SUMIFS(Imput[[Importe Neto]:[Importe Neto]],Imput[[C. Imp.]:[C. Imp.]],$D42,Imput[[PERIODO Imp.]:[PERIODO Imp.]],BT$9) -> 0 | ... DH42: =SUMIFS(Imput[[Importe Neto]:[Importe Neto]],Imput[[C. Imp.]:[C. Imp.]],$D42,Imput[[PERIODO Imp.]:[PERIODO Imp.]],DH$9) -> 0
A43: =IF(J43="","",IF(J43=0,"","Imprimir")) | D43: MAN-P2-15 | I43: =IF(E43>0,$J$5,"") | J43: =IFERROR(G43*H43*I43,"") | BJ43: =IFERROR(BK43/J43,0) -> 0 | BK43: =SUM(BM43:DH43) -> 0 | BM43: =SUMIFS(Imput[[Importe Neto]:[Importe Neto]],Imput[[C. Imp.]:[C. Imp.]],$D43,Imput[[PERIODO Imp.]:[PERIODO Imp.]],BM$9) -> 0 | BN43: =SUMIFS(Imput[[Importe Neto]:[Importe Neto]],Imput[[C. Imp.]:[C. Imp.]],$D43,Imput[[PERIODO Imp.]:[PERIODO Imp.]],BN$9) -> 0 | BO43: =SUMIFS(Imput[[Importe Neto]:[Importe Neto]],Imput[[C. Imp.]:[C. Imp.]],$D43,Imput[[PERIODO Imp.]:[PERIODO Imp.]],BO$9) -> 0 | BP43: =SUMIFS(Imput[[Importe Neto]:[Importe Neto]],Imput[[C. Imp.]:[C. Imp.]],$D43,Imput[[PERIODO Imp.]:[PERIODO Imp.]],BP$9) -> 0 | BQ43: =SUMIFS(Imput[[Importe Neto]:[Importe Neto]],Imput[[C. Imp.]:[C. Imp.]],$D43,Imput[[PERIODO Imp.]:[PERIODO Imp.]],BQ$9) -> 0 | BR43: =SUMIFS(Imput[[Importe Neto]:[Importe Neto]],Imput[[C. Imp.]:[C. Imp.]],$D43,Imput[[PERIODO Imp.]:[PERIODO Imp.]],BR$9) -> 0 | BS43: =SUMIFS(Imput[[Importe Neto]:[Importe Neto]],Imput[[C. Imp.]:[C. Imp.]],$D43,Imput[[PERIODO Imp.]:[PERIODO Imp.]],BS$9) -> 0 | BT43: =SUMIFS(Imput[[Importe Neto]:[Importe Neto]],Imput[[C. Imp.]:[C. Imp.]],$D43,Imput[[PERIODO Imp.]:[PERIODO Imp.]],BT$9) -> 0 | ... DH43: =SUMIFS(Imput[[Importe Neto]:[Importe Neto]],Imput[[C. Imp.]:[C. Imp.]],$D43,Imput[[PERIODO Imp.]:[PERIODO Imp.]],DH$9) -> 0
... A66: =IF(J66="","",IF(J66=0,"","Imprimir")) | D66: MAN-P2-38 | I66: =IF(E66>0,$J$5,"") | J66: =IFERROR(G66*H66*I66,"") | BJ66: =IFERROR(BK66/J66,0) -> 0 | BK66: =SUM(BM66:DH66) -> 0 | BM66: =SUMIFS(Imput[[Importe Neto]:[Importe Neto]],Imput[[C. Imp.]:[C. Imp.]],$D66,Imput[[PERIODO Imp.]:[PERIODO Imp.]],BM$9) -> 0 | BN66: =SUMIFS(Imput[[Importe Neto]:[Importe Neto]],Imput[[C. Imp.]:[C. Imp.]],$D66,Imput[[PERIODO Imp.]:[PERIODO Imp.]],BN$9) -> 0 | BO66: =SUMIFS(Imput[[Importe Neto]:[Importe Neto]],Imput[[C. Imp.]:[C. Imp.]],$D66,Imput[[PERIODO Imp.]:[PERIODO Imp.]],BO$9) -> 0 | BP66: =SUMIFS(Imput[[Importe Neto]:[Importe Neto]],Imput[[C. Imp.]:[C. Imp.]],$D66,Imput[[PERIODO Imp.]:[PERIODO Imp.]],BP$9) -> 0 | BQ66: =SUMIFS(Imput[[Importe Neto]:[Importe Neto]],Imput[[C. Imp.]:[C. Imp.]],$D66,Imput[[PERIODO Imp.]:[PERIODO Imp.]],BQ$9) -> 0 | BR66: =SUMIFS(Imput[[Importe Neto]:[Importe Neto]],Imput[[C. Imp.]:[C. Imp.]],$D66,Imput[[PERIODO Imp.]:[PERIODO Imp.]],BR$9) -> 0 | BS66: =SUMIFS(Imput[[Importe Neto]:[Importe Neto]],Imput[[C. Imp.]:[C. Imp.]],$D66,Imput[[PERIODO Imp.]:[PERIODO Imp.]],BS$9) -> 0 | BT66: =SUMIFS(Imput[[Importe Neto]:[Importe Neto]],Imput[[C. Imp.]:[C. Imp.]],$D66,Imput[[PERIODO Imp.]:[PERIODO Imp.]],BT$9) -> 0 | ... DH66: =SUMIFS(Imput[[Importe Neto]:[Importe Neto]],Imput[[C. Imp.]:[C. Imp.]],$D66,Imput[[PERIODO Imp.]:[PERIODO Imp.]],DH$9) -> 0
A67: =IF(J26>0,"Imprimir","") -> Imprimir
A68: =IF(J68>0,"Imprimir","") -> Imprimir | D68: P3 | E68: MANO DE OBRA | J68: =SUBTOTAL(9,J71:J120) -> 29063.929 | L68: =SUMPRODUCT($J71:$J120,L71:L120) -> 1162.5571 | M68: =SUMPRODUCT($J71:$J120,M71:M120) -> 1162.5571 | N68: =SUMPRODUCT($J71:$J120,N71:N120) -> 1162.5571 | O68: =SUMPRODUCT($J71:$J120,O71:O120) -> 1162.5571 | P68: =SUMPRODUCT($J71:$J120,P71:P120) -> 1162.5571 | Q68: =SUMPRODUCT($J71:$J120,Q71:Q120) -> 1162.5571 | R68: =SUMPRODUCT($J71:$J120,R71:R120) -> 1162.5571 | S68: =SUMPRODUCT($J71:$J120,S71:S120) -> 1162.5571 | ... BG68: =SUMPRODUCT($J71:$J120,BG71:BG120) -> 0 | BJ68: =IFERROR(BK68/J68,0) -> 1.2457301 | BK68: =SUBTOTAL(9,BK69:BK120) -> 36205.812 | BM68: =SUBTOTAL(9,BM69:BM120) -> 0 | BN68: =SUBTOTAL(9,BN69:BN120) -> 0 | BO68: =SUBTOTAL(9,BO69:BO120) -> 0 | BP68: =SUBTOTAL(9,BP69:BP120) -> 0 | BQ68: =SUBTOTAL(9,BQ69:BQ120) -> 0 | BR68: =SUBTOTAL(9,BR69:BR120) -> 36205.812 | BS68: =SUBTOTAL(9,BS69:BS120) -> 0 | BT68: =SUBTOTAL(9,BT69:BT120) -> 0 | ... DH68: =SUBTOTAL(9,DH69:DH120) -> 0
A69: =IF(J68>0,"Imprimir","") -> Imprimir | F69: Proveedor | G69: Costo Empresa | H69: =H15 -> Cantidad | I69: Meses | J69: Importe
A70: =IF(J70>0,"Imprimir","") -> Imprimir | E70: Lunes a Viernes de 7 a 18. Sábado de 7 a 13. El costo incluye comida y campamento | J70: =SUBTOTAL(9,J71:J120) -> 29063.929
A71: =IF(J71="","",IF(J71=0,"","Imprimir")) -> Imprimir | D71: MAN-P3-1 | E71: AYUDANTE 01 | G71: 442.85714 | H71: =Producción!G12*1.4625 -> 24.8625 | I71: =IF(E71>0,$J$5,"") -> 1 | J71: =IFERROR(G71*H71*I71,"") -> 11010.536 | L71: 0.04 | M71: 0.04 | N71: 0.04 | O71: 0.04 | P71: 0.04 | Q71: 0.04 | R71: 0.04 | S71: 0.04 | T71: 0.04 | U71: 0.04 | V71: 0.04 | W71: 0.04 | X71: 0.04 | Y71: 0.04 | Z71: 0.04 | AA71: 0.04 | AB71: 0.04 | AC71: 0.04 | AD71: 0.04 | AE71: 0.04 | AF71: 0.04 | AG71: 0.04 | AH71: 0.04 | AI71: 0.04 | AJ71: 0.04 | BJ71: =IFERROR(BK71/J71,0) -> 1.90212 | BK71: =SUM(BM71:DH71) -> 20943.36 | BM71: =SUMIFS(Imput[[Importe Neto]:[Importe Neto]],Imput[[C. Imp.]:[C. Imp.]],$D71,Imput[[PERIODO Imp.]:[PERIODO Imp.]],BM$9) -> 0 | BN71: =SUMIFS(Imput[[Importe Neto]:[Importe Neto]],Imput[[C. Imp.]:[C. Imp.]],$D71,Imput[[PERIODO Imp.]:[PERIODO Imp.]],BN$9) -> 0 | BO71: =SUMIFS(Imput[[Importe Neto]:[Importe Neto]],Imput[[C. Imp.]:[C. Imp.]],$D71,Imput[[PERIODO Imp.]:[PERIODO Imp.]],BO$9) -> 0 | BP71: =SUMIFS(Imput[[Importe Neto]:[Importe Neto]],Imput[[C. Imp.]:[C. Imp.]],$D71,Imput[[PERIODO Imp.]:[PERIODO Imp.]],BP$9) -> 0 | BQ71: =SUMIFS(Imput[[Importe Neto]:[Importe Neto]],Imput[[C. Imp.]:[C. Imp.]],$D71,Imput[[PERIODO Imp.]:[PERIODO Imp.]],BQ$9) -> 0 | BR71: =SUMIFS(Imput[[Importe Neto]:[Importe Neto]],Imput[[C. Imp.]:[C. Imp.]],$D71,Imput[[PERIODO Imp.]:[PERIODO Imp.]],BR$9) -> 20943.36 | BS71: =SUMIFS(Imput[[Importe Neto]:[Importe Neto]],Imput[[C. Imp.]:[C. Imp.]],$D71,Imput[[PERIODO Imp.]:[PERIODO Imp.]],BS$9) -> 0 | BT71: =SUMIFS(Imput[[Importe Neto]:[Importe Neto]],Imput[[C. Imp.]:[C. Imp.]],$D71,Imput[[PERIODO Imp.]:[PERIODO Imp.]],BT$9) -> 0 | ... DH71: =SUMIFS(Imput[[Importe Neto]:[Importe Neto]],Imput[[C. Imp.]:[C. Imp.]],$D71,Imput[[PERIODO Imp.]:[PERIODO Imp.]],DH$9) -> 0
A72: =IF(J72="","",IF(J72=0,"","Imprimir")) -> Imprimir | D72: MAN-P3-2 | E72: AYUDANTE 02 | G72: 442.85714 | H72: =Producción!G12*0.275 -> 4.675 | I72: =IF(E72>0,$J$5,"") -> 1 | J72: =IFERROR(G72*H72*I72,"") -> 2070.3571 | L72: 0.04 | M72: 0.04 | N72: 0.04 | O72: 0.04 | P72: 0.04 | Q72: 0.04 | R72: 0.04 | S72: 0.04 | T72: 0.04 | U72: 0.04 | V72: 0.04 | W72: 0.04 | X72: 0.04 | Y72: 0.04 | Z72: 0.04 | AA72: 0.04 | AB72: 0.04 | AC72: 0.04 | AD72: 0.04 | AE72: 0.04 | AF72: 0.04 | AG72: 0.04 | AH72: 0.04 | AI72: 0.04 | AJ72: 0.04 | BJ72: =IFERROR(BK72/J72,0) -> 0.99113334 | BK72: =SUM(BM72:DH72) -> 2052 | BM72: =SUMIFS(Imput[[Importe Neto]:[Importe Neto]],Imput[[C. Imp.]:[C. Imp.]],$D72,Imput[[PERIODO Imp.]:[PERIODO Imp.]],BM$9) -> 0 | BN72: =SUMIFS(Imput[[Importe Neto]:[Importe Neto]],Imput[[C. Imp.]:[C. Imp.]],$D72,Imput[[PERIODO Imp.]:[PERIODO Imp.]],BN$9) -> 0 | BO72: =SUMIFS(Imput[[Importe Neto]:[Importe Neto]],Imput[[C. Imp.]:[C. Imp.]],$D72,Imput[[PERIODO Imp.]:[PERIODO Imp.]],BO$9) -> 0 | BP72: =SUMIFS(Imput[[Importe Neto]:[Importe Neto]],Imput[[C. Imp.]:[C. Imp.]],$D72,Imput[[PERIODO Imp.]:[PERIODO Imp.]],BP$9) -> 0 | BQ72: =SUMIFS(Imput[[Importe Neto]:[Importe Neto]],Imput[[C. Imp.]:[C. Imp.]],$D72,Imput[[PERIODO Imp.]:[PERIODO Imp.]],BQ$9) -> 0 | BR72: =SUMIFS(Imput[[Importe Neto]:[Importe Neto]],Imput[[C. Imp.]:[C. Imp.]],$D72,Imput[[PERIODO Imp.]:[PERIODO Imp.]],BR$9) -> 2052 | BS72: =SUMIFS(Imput[[Importe Neto]:[Importe Neto]],Imput[[C. Imp.]:[C. Imp.]],$D72,Imput[[PERIODO Imp.]:[PERIODO Imp.]],BS$9) -> 0 | BT72: =SUMIFS(Imput[[Importe Neto]:[Importe Neto]],Imput[[C. Imp.]:[C. Imp.]],$D72,Imput[[PERIODO Imp.]:[PERIODO Imp.]],BT$9) -> 0 | ... DH72: =SUMIFS(Imput[[Importe Neto]:[Importe Neto]],Imput[[C. Imp.]:[C. Imp.]],$D72,Imput[[PERIODO Imp.]:[PERIODO Imp.]],DH$9) -> 0
A73: =IF(J73="","",IF(J73=0,"","Imprimir")) -> Imprimir | D73: MAN-P3-3 | E73: OFICIAL | G73: 642.85714 | H73: =Producción!G12*1.4625 -> 24.8625 | I73: =IF(E73>0,$J$5,"") -> 1 | J73: =IFERROR(G73*H73*I73,"") -> 15983.036 | L73: 0.04 | M73: 0.04 | N73: 0.04 | O73: 0.04 | P73: 0.04 | Q73: 0.04 | R73: 0.04 | S73: 0.04 | T73: 0.04 | U73: 0.04 | V73: 0.04 | W73: 0.04 | X73: 0.04 | Y73: 0.04 | Z73: 0.04 | AA73: 0.04 | AB73: 0.04 | AC73: 0.04 | AD73: 0.04 | AE73: 0.04 | AF73: 0.04 | AG73: 0.04 | AH73: 0.04 | AI73: 0.04 | AJ73: 0.04 | BJ73: =IFERROR(BK73/J73,0) -> 0.82652959 | BK73: =SUM(BM73:DH73) -> 13210.452 | BM73: =SUMIFS(Imput[[Importe Neto]:[Importe Neto]],Imput[[C. Imp.]:[C. Imp.]],$D73,Imput[[PERIODO Imp.]:[PERIODO Imp.]],BM$9) -> 0 | BN73: =SUMIFS(Imput[[Importe Neto]:[Importe Neto]],Imput[[C. Imp.]:[C. Imp.]],$D73,Imput[[PERIODO Imp.]:[PERIODO Imp.]],BN$9) -> 0 | BO73: =SUMIFS(Imput[[Importe Neto]:[Importe Neto]],Imput[[C. Imp.]:[C. Imp.]],$D73,Imput[[PERIODO Imp.]:[PERIODO Imp.]],BO$9) -> 0 | BP73: =SUMIFS(Imput[[Importe Neto]:[Importe Neto]],Imput[[C. Imp.]:[C. Imp.]],$D73,Imput[[PERIODO Imp.]:[PERIODO Imp.]],BP$9) -> 0 | BQ73: =SUMIFS(Imput[[Importe Neto]:[Importe Neto]],Imput[[C. Imp.]:[C. Imp.]],$D73,Imput[[PERIODO Imp.]:[PERIODO Imp.]],BQ$9) -> 0 | BR73: =SUMIFS(Imput[[Importe Neto]:[Importe Neto]],Imput[[C. Imp.]:[C. Imp.]],$D73,Imput[[PERIODO Imp.]:[PERIODO Imp.]],BR$9) -> 13210.452 | BS73: =SUMIFS(Imput[[Importe Neto]:[Importe Neto]],Imput[[C. Imp.]:[C. Imp.]],$D73,Imput[[PERIODO Imp.]:[PERIODO Imp.]],BS$9) -> 0 | BT73: =SUMIFS(Imput[[Importe Neto]:[Importe Neto]],Imput[[C. Imp.]:[C. Imp.]],$D73,Imput[[PERIODO Imp.]:[PERIODO Imp.]],BT$9) -> 0 | ... DH73: =SUMIFS(Imput[[Importe Neto]:[Importe Neto]],Imput[[C. Imp.]:[C. Imp.]],$D73,Imput[[PERIODO Imp.]:[PERIODO Imp.]],DH$9) -> 0
A74: =IF(J74="","",IF(J74=0,"","Imprimir")) | D74: MAN-P3-4 | I74: =IF(E74>0,$J$5,"") | J74: =IFERROR(G74*H74*I74,"") | BJ74: =IFERROR(BK74/J74,0) -> 0 | BK74: =SUM(BM74:DH74) -> 0 | BM74: =SUMIFS(Imput[[Importe Neto]:[Importe Neto]],Imput[[C. Imp.]:[C. Imp.]],$D74,Imput[[PERIODO Imp.]:[PERIODO Imp.]],BM$9) -> 0 | BN74: =SUMIFS(Imput[[Importe Neto]:[Importe Neto]],Imput[[C. Imp.]:[C. Imp.]],$D74,Imput[[PERIODO Imp.]:[PERIODO Imp.]],BN$9) -> 0 | BO74: =SUMIFS(Imput[[Importe Neto]:[Importe Neto]],Imput[[C. Imp.]:[C. Imp.]],$D74,Imput[[PERIODO Imp.]:[PERIODO Imp.]],BO$9) -> 0 | BP74: =SUMIFS(Imput[[Importe Neto]:[Importe Neto]],Imput[[C. Imp.]:[C. Imp.]],$D74,Imput[[PERIODO Imp.]:[PERIODO Imp.]],BP$9) -> 0 | BQ74: =SUMIFS(Imput[[Importe Neto]:[Importe Neto]],Imput[[C. Imp.]:[C. Imp.]],$D74,Imput[[PERIODO Imp.]:[PERIODO Imp.]],BQ$9) -> 0 | BR74: =SUMIFS(Imput[[Importe Neto]:[Importe Neto]],Imput[[C. Imp.]:[C. Imp.]],$D74,Imput[[PERIODO Imp.]:[PERIODO Imp.]],BR$9) -> 0 | BS74: =SUMIFS(Imput[[Importe Neto]:[Importe Neto]],Imput[[C. Imp.]:[C. Imp.]],$D74,Imput[[PERIODO Imp.]:[PERIODO Imp.]],BS$9) -> 0 | BT74: =SUMIFS(Imput[[Importe Neto]:[Importe Neto]],Imput[[C. Imp.]:[C. Imp.]],$D74,Imput[[PERIODO Imp.]:[PERIODO Imp.]],BT$9) -> 0 | ... DH74: =SUMIFS(Imput[[Importe Neto]:[Importe Neto]],Imput[[C. Imp.]:[C. Imp.]],$D74,Imput[[PERIODO Imp.]:[PERIODO Imp.]],DH$9) -> 0
A75: =IF(J75="","",IF(J75=0,"","Imprimir")) | D75: MAN-P3-5 | I75: =IF(E75>0,$J$5,"") | J75: =IFERROR(G75*H75*I75,"") | BJ75: =IFERROR(BK75/J75,0) -> 0 | BK75: =SUM(BM75:DH75) -> 0 | BM75: =SUMIFS(Imput[[Importe Neto]:[Importe Neto]],Imput[[C. Imp.]:[C. Imp.]],$D75,Imput[[PERIODO Imp.]:[PERIODO Imp.]],BM$9) -> 0 | BN75: =SUMIFS(Imput[[Importe Neto]:[Importe Neto]],Imput[[C. Imp.]:[C. Imp.]],$D75,Imput[[PERIODO Imp.]:[PERIODO Imp.]],BN$9) -> 0 | BO75: =SUMIFS(Imput[[Importe Neto]:[Importe Neto]],Imput[[C. Imp.]:[C. Imp.]],$D75,Imput[[PERIODO Imp.]:[PERIODO Imp.]],BO$9) -> 0 | BP75: =SUMIFS(Imput[[Importe Neto]:[Importe Neto]],Imput[[C. Imp.]:[C. Imp.]],$D75,Imput[[PERIODO Imp.]:[PERIODO Imp.]],BP$9) -> 0 | BQ75: =SUMIFS(Imput[[Importe Neto]:[Importe Neto]],Imput[[C. Imp.]:[C. Imp.]],$D75,Imput[[PERIODO Imp.]:[PERIODO Imp.]],BQ$9) -> 0 | BR75: =SUMIFS(Imput[[Importe Neto]:[Importe Neto]],Imput[[C. Imp.]:[C. Imp.]],$D75,Imput[[PERIODO Imp.]:[PERIODO Imp.]],BR$9) -> 0 | BS75: =SUMIFS(Imput[[Importe Neto]:[Importe Neto]],Imput[[C. Imp.]:[C. Imp.]],$D75,Imput[[PERIODO Imp.]:[PERIODO Imp.]],BS$9) -> 0 | BT75: =SUMIFS(Imput[[Importe Neto]:[Importe Neto]],Imput[[C. Imp.]:[C. Imp.]],$D75,Imput[[PERIODO Imp.]:[PERIODO Imp.]],BT$9) -> 0 | ... DH75: =SUMIFS(Imput[[Importe Neto]:[Importe Neto]],Imput[[C. Imp.]:[C. Imp.]],$D75,Imput[[PERIODO Imp.]:[PERIODO Imp.]],DH$9) -> 0
A76: =IF(J76="","",IF(J76=0,"","Imprimir")) | D76: MAN-P3-6 | I76: =IF(E76>0,$J$5,"") | J76: =IFERROR(G76*H76*I76,"") | BJ76: =IFERROR(BK76/J76,0) -> 0 | BK76: =SUM(BM76:DH76) -> 0 | BM76: =SUMIFS(Imput[[Importe Neto]:[Importe Neto]],Imput[[C. Imp.]:[C. Imp.]],$D76,Imput[[PERIODO Imp.]:[PERIODO Imp.]],BM$9) -> 0 | BN76: =SUMIFS(Imput[[Importe Neto]:[Importe Neto]],Imput[[C. Imp.]:[C. Imp.]],$D76,Imput[[PERIODO Imp.]:[PERIODO Imp.]],BN$9) -> 0 | BO76: =SUMIFS(Imput[[Importe Neto]:[Importe Neto]],Imput[[C. Imp.]:[C. Imp.]],$D76,Imput[[PERIODO Imp.]:[PERIODO Imp.]],BO$9) -> 0 | BP76: =SUMIFS(Imput[[Importe Neto]:[Importe Neto]],Imput[[C. Imp.]:[C. Imp.]],$D76,Imput[[PERIODO Imp.]:[PERIODO Imp.]],BP$9) -> 0 | BQ76: =SUMIFS(Imput[[Importe Neto]:[Importe Neto]],Imput[[C. Imp.]:[C. Imp.]],$D76,Imput[[PERIODO Imp.]:[PERIODO Imp.]],BQ$9) -> 0 | BR76: =SUMIFS(Imput[[Importe Neto]:[Importe Neto]],Imput[[C. Imp.]:[C. Imp.]],$D76,Imput[[PERIODO Imp.]:[PERIODO Imp.]],BR$9) -> 0 | BS76: =SUMIFS(Imput[[Importe Neto]:[Importe Neto]],Imput[[C. Imp.]:[C. Imp.]],$D76,Imput[[PERIODO Imp.]:[PERIODO Imp.]],BS$9) -> 0 | BT76: =SUMIFS(Imput[[Importe Neto]:[Importe Neto]],Imput[[C. Imp.]:[C. Imp.]],$D76,Imput[[PERIODO Imp.]:[PERIODO Imp.]],BT$9) -> 0 | ... DH76: =SUMIFS(Imput[[Importe Neto]:[Importe Neto]],Imput[[C. Imp.]:[C. Imp.]],$D76,Imput[[PERIODO Imp.]:[PERIODO Imp.]],DH$9) -> 0
A77: =IF(J77="","",IF(J77=0,"","Imprimir")) | D77: MAN-P3-7 | I77: =IF(E77>0,$J$5,"") | J77: =IFERROR(G77*H77*I77,"") | BJ77: =IFERROR(BK77/J77,0) -> 0 | BK77: =SUM(BM77:DH77) -> 0 | BM77: =SUMIFS(Imput[[Importe Neto]:[Importe Neto]],Imput[[C. Imp.]:[C. Imp.]],$D77,Imput[[PERIODO Imp.]:[PERIODO Imp.]],BM$9) -> 0 | BN77: =SUMIFS(Imput[[Importe Neto]:[Importe Neto]],Imput[[C. Imp.]:[C. Imp.]],$D77,Imput[[PERIODO Imp.]:[PERIODO Imp.]],BN$9) -> 0 | BO77: =SUMIFS(Imput[[Importe Neto]:[Importe Neto]],Imput[[C. Imp.]:[C. Imp.]],$D77,Imput[[PERIODO Imp.]:[PERIODO Imp.]],BO$9) -> 0 | BP77: =SUMIFS(Imput[[Importe Neto]:[Importe Neto]],Imput[[C. Imp.]:[C. Imp.]],$D77,Imput[[PERIODO Imp.]:[PERIODO Imp.]],BP$9) -> 0 | BQ77: =SUMIFS(Imput[[Importe Neto]:[Importe Neto]],Imput[[C. Imp.]:[C. Imp.]],$D77,Imput[[PERIODO Imp.]:[PERIODO Imp.]],BQ$9) -> 0 | BR77: =SUMIFS(Imput[[Importe Neto]:[Importe Neto]],Imput[[C. Imp.]:[C. Imp.]],$D77,Imput[[PERIODO Imp.]:[PERIODO Imp.]],BR$9) -> 0 | BS77: =SUMIFS(Imput[[Importe Neto]:[Importe Neto]],Imput[[C. Imp.]:[C. Imp.]],$D77,Imput[[PERIODO Imp.]:[PERIODO Imp.]],BS$9) -> 0 | BT77: =SUMIFS(Imput[[Importe Neto]:[Importe Neto]],Imput[[C. Imp.]:[C. Imp.]],$D77,Imput[[PERIODO Imp.]:[PERIODO Imp.]],BT$9) -> 0 | ... DH77: =SUMIFS(Imput[[Importe Neto]:[Importe Neto]],Imput[[C. Imp.]:[C. Imp.]],$D77,Imput[[PERIODO Imp.]:[PERIODO Imp.]],DH$9) -> 0
A78: =IF(J78="","",IF(J78=0,"","Imprimir")) | D78: MAN-P3-8 | I78: =IF(E78>0,$J$5,"") | J78: =IFERROR(G78*H78*I78,"") | BJ78: =IFERROR(BK78/J78,0) -> 0 | BK78: =SUM(BM78:DH78) -> 0 | BM78: =SUMIFS(Imput[[Importe Neto]:[Importe Neto]],Imput[[C. Imp.]:[C. Imp.]],$D78,Imput[[PERIODO Imp.]:[PERIODO Imp.]],BM$9) -> 0 | BN78: =SUMIFS(Imput[[Importe Neto]:[Importe Neto]],Imput[[C. Imp.]:[C. Imp.]],$D78,Imput[[PERIODO Imp.]:[PERIODO Imp.]],BN$9) -> 0 | BO78: =SUMIFS(Imput[[Importe Neto]:[Importe Neto]],Imput[[C. Imp.]:[C. Imp.]],$D78,Imput[[PERIODO Imp.]:[PERIODO Imp.]],BO$9) -> 0 | BP78: =SUMIFS(Imput[[Importe Neto]:[Importe Neto]],Imput[[C. Imp.]:[C. Imp.]],$D78,Imput[[PERIODO Imp.]:[PERIODO Imp.]],BP$9) -> 0 | BQ78: =SUMIFS(Imput[[Importe Neto]:[Importe Neto]],Imput[[C. Imp.]:[C. Imp.]],$D78,Imput[[PERIODO Imp.]:[PERIODO Imp.]],BQ$9) -> 0 | BR78: =SUMIFS(Imput[[Importe Neto]:[Importe Neto]],Imput[[C. Imp.]:[C. Imp.]],$D78,Imput[[PERIODO Imp.]:[PERIODO Imp.]],BR$9) -> 0 | BS78: =SUMIFS(Imput[[Importe Neto]:[Importe Neto]],Imput[[C. Imp.]:[C. Imp.]],$D78,Imput[[PERIODO Imp.]:[PERIODO Imp.]],BS$9) -> 0 | BT78: =SUMIFS(Imput[[Importe Neto]:[Importe Neto]],Imput[[C. Imp.]:[C. Imp.]],$D78,Imput[[PERIODO Imp.]:[PERIODO Imp.]],BT$9) -> 0 | ... DH78: =SUMIFS(Imput[[Importe Neto]:[Importe Neto]],Imput[[C. Imp.]:[C. Imp.]],$D78,Imput[[PERIODO Imp.]:[PERIODO Imp.]],DH$9) -> 0
A79: =IF(J79="","",IF(J79=0,"","Imprimir")) | D79: MAN-P3-9 | I79: =IF(E79>0,$J$5,"") | J79: =IFERROR(G79*H79*I79,"") | BJ79: =IFERROR(BK79/J79,0) -> 0 | BK79: =SUM(BM79:DH79) -> 0 | BM79: =SUMIFS(Imput[[Importe Neto]:[Importe Neto]],Imput[[C. Imp.]:[C. Imp.]],$D79,Imput[[PERIODO Imp.]:[PERIODO Imp.]],BM$9) -> 0 | BN79: =SUMIFS(Imput[[Importe Neto]:[Importe Neto]],Imput[[C. Imp.]:[C. Imp.]],$D79,Imput[[PERIODO Imp.]:[PERIODO Imp.]],BN$9) -> 0 | BO79: =SUMIFS(Imput[[Importe Neto]:[Importe Neto]],Imput[[C. Imp.]:[C. Imp.]],$D79,Imput[[PERIODO Imp.]:[PERIODO Imp.]],BO$9) -> 0 | BP79: =SUMIFS(Imput[[Importe Neto]:[Importe Neto]],Imput[[C. Imp.]:[C. Imp.]],$D79,Imput[[PERIODO Imp.]:[PERIODO Imp.]],BP$9) -> 0 | BQ79: =SUMIFS(Imput[[Importe Neto]:[Importe Neto]],Imput[[C. Imp.]:[C. Imp.]],$D79,Imput[[PERIODO Imp.]:[PERIODO Imp.]],BQ$9) -> 0 | BR79: =SUMIFS(Imput[[Importe Neto]:[Importe Neto]],Imput[[C. Imp.]:[C. Imp.]],$D79,Imput[[PERIODO Imp.]:[PERIODO Imp.]],BR$9) -> 0 | BS79: =SUMIFS(Imput[[Importe Neto]:[Importe Neto]],Imput[[C. Imp.]:[C. Imp.]],$D79,Imput[[PERIODO Imp.]:[PERIODO Imp.]],BS$9) -> 0 | BT79: =SUMIFS(Imput[[Importe Neto]:[Importe Neto]],Imput[[C. Imp.]:[C. Imp.]],$D79,Imput[[PERIODO Imp.]:[PERIODO Imp.]],BT$9) -> 0 | ... DH79: =SUMIFS(Imput[[Importe Neto]:[Importe Neto]],Imput[[C. Imp.]:[C. Imp.]],$D79,Imput[[PERIODO Imp.]:[PERIODO Imp.]],DH$9) -> 0
A80: =IF(J80="","",IF(J80=0,"","Imprimir")) | D80: MAN-P3-10 | I80: =IF(E80>0,$J$5,"") | J80: =IFERROR(G80*H80*I80,"") | BJ80: =IFERROR(BK80/J80,0) -> 0 | BK80: =SUM(BM80:DH80) -> 0 | BM80: =SUMIFS(Imput[[Importe Neto]:[Importe Neto]],Imput[[C. Imp.]:[C. Imp.]],$D80,Imput[[PERIODO Imp.]:[PERIODO Imp.]],BM$9) -> 0 | BN80: =SUMIFS(Imput[[Importe Neto]:[Importe Neto]],Imput[[C. Imp.]:[C. Imp.]],$D80,Imput[[PERIODO Imp.]:[PERIODO Imp.]],BN$9) -> 0 | BO80: =SUMIFS(Imput[[Importe Neto]:[Importe Neto]],Imput[[C. Imp.]:[C. Imp.]],$D80,Imput[[PERIODO Imp.]:[PERIODO Imp.]],BO$9) -> 0 | BP80: =SUMIFS(Imput[[Importe Neto]:[Importe Neto]],Imput[[C. Imp.]:[C. Imp.]],$D80,Imput[[PERIODO Imp.]:[PERIODO Imp.]],BP$9) -> 0 | BQ80: =SUMIFS(Imput[[Importe Neto]:[Importe Neto]],Imput[[C. Imp.]:[C. Imp.]],$D80,Imput[[PERIODO Imp.]:[PERIODO Imp.]],BQ$9) -> 0 | BR80: =SUMIFS(Imput[[Importe Neto]:[Importe Neto]],Imput[[C. Imp.]:[C. Imp.]],$D80,Imput[[PERIODO Imp.]:[PERIODO Imp.]],BR$9) -> 0 | BS80: =SUMIFS(Imput[[Importe Neto]:[Importe Neto]],Imput[[C. Imp.]:[C. Imp.]],$D80,Imput[[PERIODO Imp.]:[PERIODO Imp.]],BS$9) -> 0 | BT80: =SUMIFS(Imput[[Importe Neto]:[Importe Neto]],Imput[[C. Imp.]:[C. Imp.]],$D80,Imput[[PERIODO Imp.]:[PERIODO Imp.]],BT$9) -> 0 | ... DH80: =SUMIFS(Imput[[Importe Neto]:[Importe Neto]],Imput[[C. Imp.]:[C. Imp.]],$D80,Imput[[PERIODO Imp.]:[PERIODO Imp.]],DH$9) -> 0
A81: =IF(J81="","",IF(J81=0,"","Imprimir")) | D81: MAN-P3-11 | I81: =IF(E81>0,$J$5,"") | J81: =IFERROR(G81*H81*I81,"") | BJ81: =IFERROR(BK81/J81,0) -> 0 | BK81: =SUM(BM81:DH81) -> 0 | BM81: =SUMIFS(Imput[[Importe Neto]:[Importe Neto]],Imput[[C. Imp.]:[C. Imp.]],$D81,Imput[[PERIODO Imp.]:[PERIODO Imp.]],BM$9) -> 0 | BN81: =SUMIFS(Imput[[Importe Neto]:[Importe Neto]],Imput[[C. Imp.]:[C. Imp.]],$D81,Imput[[PERIODO Imp.]:[PERIODO Imp.]],BN$9) -> 0 | BO81: =SUMIFS(Imput[[Importe Neto]:[Importe Neto]],Imput[[C. Imp.]:[C. Imp.]],$D81,Imput[[PERIODO Imp.]:[PERIODO Imp.]],BO$9) -> 0 | BP81: =SUMIFS(Imput[[Importe Neto]:[Importe Neto]],Imput[[C. Imp.]:[C. Imp.]],$D81,Imput[[PERIODO Imp.]:[PERIODO Imp.]],BP$9) -> 0 | BQ81: =SUMIFS(Imput[[Importe Neto]:[Importe Neto]],Imput[[C. Imp.]:[C. Imp.]],$D81,Imput[[PERIODO Imp.]:[PERIODO Imp.]],BQ$9) -> 0 | BR81: =SUMIFS(Imput[[Importe Neto]:[Importe Neto]],Imput[[C. Imp.]:[C. Imp.]],$D81,Imput[[PERIODO Imp.]:[PERIODO Imp.]],BR$9) -> 0 | BS81: =SUMIFS(Imput[[Importe Neto]:[Importe Neto]],Imput[[C. Imp.]:[C. Imp.]],$D81,Imput[[PERIODO Imp.]:[PERIODO Imp.]],BS$9) -> 0 | BT81: =SUMIFS(Imput[[Importe Neto]:[Importe Neto]],Imput[[C. Imp.]:[C. Imp.]],$D81,Imput[[PERIODO Imp.]:[PERIODO Imp.]],BT$9) -> 0 | ... DH81: =SUMIFS(Imput[[Importe Neto]:[Importe Neto]],Imput[[C. Imp.]:[C. Imp.]],$D81,Imput[[PERIODO Imp.]:[PERIODO Imp.]],DH$9) -> 0
A82: =IF(J82="","",IF(J82=0,"","Imprimir")) | D82: MAN-P3-12 | I82: =IF(E82>0,$J$5,"") | J82: =IFERROR(G82*H82*I82,"") | BJ82: =IFERROR(BK82/J82,0) -> 0 | BK82: =SUM(BM82:DH82) -> 0 | BM82: =SUMIFS(Imput[[Importe Neto]:[Importe Neto]],Imput[[C. Imp.]:[C. Imp.]],$D82,Imput[[PERIODO Imp.]:[PERIODO Imp.]],BM$9) -> 0 | BN82: =SUMIFS(Imput[[Importe Neto]:[Importe Neto]],Imput[[C. Imp.]:[C. Imp.]],$D82,Imput[[PERIODO Imp.]:[PERIODO Imp.]],BN$9) -> 0 | BO82: =SUMIFS(Imput[[Importe Neto]:[Importe Neto]],Imput[[C. Imp.]:[C. Imp.]],$D82,Imput[[PERIODO Imp.]:[PERIODO Imp.]],BO$9) -> 0 | BP82: =SUMIFS(Imput[[Importe Neto]:[Importe Neto]],Imput[[C. Imp.]:[C. Imp.]],$D82,Imput[[PERIODO Imp.]:[PERIODO Imp.]],BP$9) -> 0 | BQ82: =SUMIFS(Imput[[Importe Neto]:[Importe Neto]],Imput[[C. Imp.]:[C. Imp.]],$D82,Imput[[PERIODO Imp.]:[PERIODO Imp.]],BQ$9) -> 0 | BR82: =SUMIFS(Imput[[Importe Neto]:[Importe Neto]],Imput[[C. Imp.]:[C. Imp.]],$D82,Imput[[PERIODO Imp.]:[PERIODO Imp.]],BR$9) -> 0 | BS82: =SUMIFS(Imput[[Importe Neto]:[Importe Neto]],Imput[[C. Imp.]:[C. Imp.]],$D82,Imput[[PERIODO Imp.]:[PERIODO Imp.]],BS$9) -> 0 | BT82: =SUMIFS(Imput[[Importe Neto]:[Importe Neto]],Imput[[C. Imp.]:[C. Imp.]],$D82,Imput[[PERIODO Imp.]:[PERIODO Imp.]],BT$9) -> 0 | ... DH82: =SUMIFS(Imput[[Importe Neto]:[Importe Neto]],Imput[[C. Imp.]:[C. Imp.]],$D82,Imput[[PERIODO Imp.]:[PERIODO Imp.]],DH$9) -> 0
A83: =IF(J83="","",IF(J83=0,"","Imprimir")) | D83: MAN-P3-13 | I83: =IF(E83>0,$J$5,"") | J83: =IFERROR(G83*H83*I83,"") | BJ83: =IFERROR(BK83/J83,0) -> 0 | BK83: =SUM(BM83:DH83) -> 0 | BM83: =SUMIFS(Imput[[Importe Neto]:[Importe Neto]],Imput[[C. Imp.]:[C. Imp.]],$D83,Imput[[PERIODO Imp.]:[PERIODO Imp.]],BM$9) -> 0 | BN83: =SUMIFS(Imput[[Importe Neto]:[Importe Neto]],Imput[[C. Imp.]:[C. Imp.]],$D83,Imput[[PERIODO Imp.]:[PERIODO Imp.]],BN$9) -> 0 | BO83: =SUMIFS(Imput[[Importe Neto]:[Importe Neto]],Imput[[C. Imp.]:[C. Imp.]],$D83,Imput[[PERIODO Imp.]:[PERIODO Imp.]],BO$9) -> 0 | BP83: =SUMIFS(Imput[[Importe Neto]:[Importe Neto]],Imput[[C. Imp.]:[C. Imp.]],$D83,Imput[[PERIODO Imp.]:[PERIODO Imp.]],BP$9) -> 0 | BQ83: =SUMIFS(Imput[[Importe Neto]:[Importe Neto]],Imput[[C. Imp.]:[C. Imp.]],$D83,Imput[[PERIODO Imp.]:[PERIODO Imp.]],BQ$9) -> 0 | BR83: =SUMIFS(Imput[[Importe Neto]:[Importe Neto]],Imput[[C. Imp.]:[C. Imp.]],$D83,Imput[[PERIODO Imp.]:[PERIODO Imp.]],BR$9) -> 0 | BS83: =SUMIFS(Imput[[Importe Neto]:[Importe Neto]],Imput[[C. Imp.]:[C. Imp.]],$D83,Imput[[PERIODO Imp.]:[PERIODO Imp.]],BS$9) -> 0 | BT83: =SUMIFS(Imput[[Importe Neto]:[Importe Neto]],Imput[[C. Imp.]:[C. Imp.]],$D83,Imput[[PERIODO Imp.]:[PERIODO Imp.]],BT$9) -> 0 | ... DH83: =SUMIFS(Imput[[Importe Neto]:[Importe Neto]],Imput[[C. Imp.]:[C. Imp.]],$D83,Imput[[PERIODO Imp.]:[PERIODO Imp.]],DH$9) -> 0
A84: =IF(J84="","",IF(J84=0,"","Imprimir")) | D84: MAN-P3-14 | I84: =IF(E84>0,$J$5,"") | J84: =IFERROR(G84*H84*I84,"") | BJ84: =IFERROR(BK84/J84,0) -> 0 | BK84: =SUM(BM84:DH84) -> 0 | BM84: =SUMIFS(Imput[[Importe Neto]:[Importe Neto]],Imput[[C. Imp.]:[C. Imp.]],$D84,Imput[[PERIODO Imp.]:[PERIODO Imp.]],BM$9) -> 0 | BN84: =SUMIFS(Imput[[Importe Neto]:[Importe Neto]],Imput[[C. Imp.]:[C. Imp.]],$D84,Imput[[PERIODO Imp.]:[PERIODO Imp.]],BN$9) -> 0 | BO84: =SUMIFS(Imput[[Importe Neto]:[Importe Neto]],Imput[[C. Imp.]:[C. Imp.]],$D84,Imput[[PERIODO Imp.]:[PERIODO Imp.]],BO$9) -> 0 | BP84: =SUMIFS(Imput[[Importe Neto]:[Importe Neto]],Imput[[C. Imp.]:[C. Imp.]],$D84,Imput[[PERIODO Imp.]:[PERIODO Imp.]],BP$9) -> 0 | BQ84: =SUMIFS(Imput[[Importe Neto]:[Importe Neto]],Imput[[C. Imp.]:[C. Imp.]],$D84,Imput[[PERIODO Imp.]:[PERIODO Imp.]],BQ$9) -> 0 | BR84: =SUMIFS(Imput[[Importe Neto]:[Importe Neto]],Imput[[C. Imp.]:[C. Imp.]],$D84,Imput[[PERIODO Imp.]:[PERIODO Imp.]],BR$9) -> 0 | BS84: =SUMIFS(Imput[[Importe Neto]:[Importe Neto]],Imput[[C. Imp.]:[C. Imp.]],$D84,Imput[[PERIODO Imp.]:[PERIODO Imp.]],BS$9) -> 0 | BT84: =SUMIFS(Imput[[Importe Neto]:[Importe Neto]],Imput[[C. Imp.]:[C. Imp.]],$D84,Imput[[PERIODO Imp.]:[PERIODO Imp.]],BT$9) -> 0 | ... DH84: =SUMIFS(Imput[[Importe Neto]:[Importe Neto]],Imput[[C. Imp.]:[C. Imp.]],$D84,Imput[[PERIODO Imp.]:[PERIODO Imp.]],DH$9) -> 0
A85: =IF(J85="","",IF(J85=0,"","Imprimir")) | D85: MAN-P3-15 | I85: =IF(E85>0,$J$5,"") | J85: =IFERROR(G85*H85*I85,"") | BJ85: =IFERROR(BK85/J85,0) -> 0 | BK85: =SUM(BM85:DH85) -> 0 | BM85: =SUMIFS(Imput[[Importe Neto]:[Importe Neto]],Imput[[C. Imp.]:[C. Imp.]],$D85,Imput[[PERIODO Imp.]:[PERIODO Imp.]],BM$9) -> 0 | BN85: =SUMIFS(Imput[[Importe Neto]:[Importe Neto]],Imput[[C. Imp.]:[C. Imp.]],$D85,Imput[[PERIODO Imp.]:[PERIODO Imp.]],BN$9) -> 0 | BO85: =SUMIFS(Imput[[Importe Neto]:[Importe Neto]],Imput[[C. Imp.]:[C. Imp.]],$D85,Imput[[PERIODO Imp.]:[PERIODO Imp.]],BO$9) -> 0 | BP85: =SUMIFS(Imput[[Importe Neto]:[Importe Neto]],Imput[[C. Imp.]:[C. Imp.]],$D85,Imput[[PERIODO Imp.]:[PERIODO Imp.]],BP$9) -> 0 | BQ85: =SUMIFS(Imput[[Importe Neto]:[Importe Neto]],Imput[[C. Imp.]:[C. Imp.]],$D85,Imput[[PERIODO Imp.]:[PERIODO Imp.]],BQ$9) -> 0 | BR85: =SUMIFS(Imput[[Importe Neto]:[Importe Neto]],Imput[[C. Imp.]:[C. Imp.]],$D85,Imput[[PERIODO Imp.]:[PERIODO Imp.]],BR$9) -> 0 | BS85: =SUMIFS(Imput[[Importe Neto]:[Importe Neto]],Imput[[C. Imp.]:[C. Imp.]],$D85,Imput[[PERIODO Imp.]:[PERIODO Imp.]],BS$9) -> 0 | BT85: =SUMIFS(Imput[[Importe Neto]:[Importe Neto]],Imput[[C. Imp.]:[C. Imp.]],$D85,Imput[[PERIODO Imp.]:[PERIODO Imp.]],BT$9) -> 0 | ... DH85: =SUMIFS(Imput[[Importe Neto]:[Importe Neto]],Imput[[C. Imp.]:[C. Imp.]],$D85,Imput[[PERIODO Imp.]:[PERIODO Imp.]],DH$9) -> 0
... A119: =IF(J119="","",IF(J119=0,"","Imprimir")) | D119: MAN-P3-49 | I119: =IF(E119>0,$J$5,"") | J119: =IFERROR(G119*H119*I119,"") | BJ119: =IFERROR(BK119/J119,0) -> 0 | BK119: =SUM(BM119:DH119) -> 0 | BM119: =SUMIFS(Imput[[Importe Neto]:[Importe Neto]],Imput[[C. Imp.]:[C. Imp.]],$D119,Imput[[PERIODO Imp.]:[PERIODO Imp.]],BM$9) -> 0 | BN119: =SUMIFS(Imput[[Importe Neto]:[Importe Neto]],Imput[[C. Imp.]:[C. Imp.]],$D119,Imput[[PERIODO Imp.]:[PERIODO Imp.]],BN$9) -> 0 | BO119: =SUMIFS(Imput[[Importe Neto]:[Importe Neto]],Imput[[C. Imp.]:[C. Imp.]],$D119,Imput[[PERIODO Imp.]:[PERIODO Imp.]],BO$9) -> 0 | BP119: =SUMIFS(Imput[[Importe Neto]:[Importe Neto]],Imput[[C. Imp.]:[C. Imp.]],$D119,Imput[[PERIODO Imp.]:[PERIODO Imp.]],BP$9) -> 0 | BQ119: =SUMIFS(Imput[[Importe Neto]:[Importe Neto]],Imput[[C. Imp.]:[C. Imp.]],$D119,Imput[[PERIODO Imp.]:[PERIODO Imp.]],BQ$9) -> 0 | BR119: =SUMIFS(Imput[[Importe Neto]:[Importe Neto]],Imput[[C. Imp.]:[C. Imp.]],$D119,Imput[[PERIODO Imp.]:[PERIODO Imp.]],BR$9) -> 0 | BS119: =SUMIFS(Imput[[Importe Neto]:[Importe Neto]],Imput[[C. Imp.]:[C. Imp.]],$D119,Imput[[PERIODO Imp.]:[PERIODO Imp.]],BS$9) -> 0 | BT119: =SUMIFS(Imput[[Importe Neto]:[Importe Neto]],Imput[[C. Imp.]:[C. Imp.]],$D119,Imput[[PERIODO Imp.]:[PERIODO Imp.]],BT$9) -> 0 | ... DH119: =SUMIFS(Imput[[Importe Neto]:[Importe Neto]],Imput[[C. Imp.]:[C. Imp.]],$D119,Imput[[PERIODO Imp.]:[PERIODO Imp.]],DH$9) -> 0
A120: =IF(J68>0,"Imprimir","") -> Imprimir
A121: =IF(J121>0,"Imprimir","") -> Imprimir | D121: P4 | E121: MATERIALES | J121: =SUBTOTAL(9,J124:J173) -> 124378.58 | L121: =SUMPRODUCT($J124:$J173,L124:L173) -> 79001.605 | M121: =SUMPRODUCT($J124:$J173,M124:M173) -> 1965.6038 | N121: =SUMPRODUCT($J124:$J173,N124:N173) -> 1965.6038 | O121: =SUMPRODUCT($J124:$J173,O124:O173) -> 3534.0238 | P121: =SUMPRODUCT($J124:$J173,P124:P173) -> 8395.9898 | Q121: =SUMPRODUCT($J124:$J173,Q124:Q173) -> 1965.6038 | R121: =SUMPRODUCT($J124:$J173,R124:R173) -> 1965.6038 | S121: =SUMPRODUCT($J124:$J173,S124:S173) -> 2034.6238 | ... BG121: =SUMPRODUCT($J124:$J173,BG124:BG173) -> 0 | BJ121: =IFERROR(BK121/J121,0) -> 0.91191625 | BK121: =SUBTOTAL(9,BK122:BK173) -> 113422.85 | BM121: =SUBTOTAL(9,BM122:BM173) -> 0 | BN121: =SUBTOTAL(9,BN122:BN173) -> 0 | BO121: =SUBTOTAL(9,BO122:BO173) -> 43812.69 | BP121: =SUBTOTAL(9,BP122:BP173) -> 58749.893 | BQ121: =SUBTOTAL(9,BQ122:BQ173) -> 1290.0091 | BR121: =SUBTOTAL(9,BR122:BR173) -> 9570.2552 | BS121: =SUBTOTAL(9,BS122:BS173) -> 0 | BT121: =SUBTOTAL(9,BT122:BT173) -> 0 | ... DH121: =SUBTOTAL(9,DH122:DH173) -> 0
A122: =IF(J121>0,"Imprimir","") -> Imprimir | F122: Proveedor | G122: Costo Empresa | H122: =H15 -> Cantidad | I122: Meses | J122: Importe
A123: =IF(J123>0,"Imprimir","") -> Imprimir | J123: =SUBTOTAL(9,J124:J173) -> 124378.58
A124: =IF(J124="","",IF(J124=0,"","Imprimir")) -> Imprimir | D124: MAN-P4-1 | E124: ADITIVO CURADOR | G124: 68.421053 | H124: =Producción!G12*0.1 -> 1.7 | I124: =IF(E124>0,$J$5,"") -> 1 | J124: =IFERROR(G124*H124*I124,"") -> 116.31579 | L124: 1 | BJ124: =IFERROR(BK124/J124,0) -> 0 | BK124: =SUM(BM124:DH124) -> 0 | BM124: =SUMIFS(Imput[[Importe Neto]:[Importe Neto]],Imput[[C. Imp.]:[C. Imp.]],$D124,Imput[[PERIODO Imp.]:[PERIODO Imp.]],BM$9) -> 0 | BN124: =SUMIFS(Imput[[Importe Neto]:[Importe Neto]],Imput[[C. Imp.]:[C. Imp.]],$D124,Imput[[PERIODO Imp.]:[PERIODO Imp.]],BN$9) -> 0 | BO124: =SUMIFS(Imput[[Importe Neto]:[Importe Neto]],Imput[[C. Imp.]:[C. Imp.]],$D124,Imput[[PERIODO Imp.]:[PERIODO Imp.]],BO$9) -> 0 | BP124: =SUMIFS(Imput[[Importe Neto]:[Importe Neto]],Imput[[C. Imp.]:[C. Imp.]],$D124,Imput[[PERIODO Imp.]:[PERIODO Imp.]],BP$9) -> 0 | BQ124: =SUMIFS(Imput[[Importe Neto]:[Importe Neto]],Imput[[C. Imp.]:[C. Imp.]],$D124,Imput[[PERIODO Imp.]:[PERIODO Imp.]],BQ$9) -> 0 | BR124: =SUMIFS(Imput[[Importe Neto]:[Importe Neto]],Imput[[C. Imp.]:[C. Imp.]],$D124,Imput[[PERIODO Imp.]:[PERIODO Imp.]],BR$9) -> 0 | BS124: =SUMIFS(Imput[[Importe Neto]:[Importe Neto]],Imput[[C. Imp.]:[C. Imp.]],$D124,Imput[[PERIODO Imp.]:[PERIODO Imp.]],BS$9) -> 0 | BT124: =SUMIFS(Imput[[Importe Neto]:[Importe Neto]],Imput[[C. Imp.]:[C. Imp.]],$D124,Imput[[PERIODO Imp.]:[PERIODO Imp.]],BT$9) -> 0 | ... DH124: =SUMIFS(Imput[[Importe Neto]:[Importe Neto]],Imput[[C. Imp.]:[C. Imp.]],$D124,Imput[[PERIODO Imp.]:[PERIODO Imp.]],DH$9) -> 0
A125: =IF(J125="","",IF(J125=0,"","Imprimir")) -> Imprimir | D125: MAN-P4-2 | E125: ADITIVO DESMOLDANTE SIKA O SIMILAR | G125: 115.73684 | H125: =Producción!G12*0.09 -> 1.53 | I125: =IF(E125>0,$J$5,"") -> 1 | J125: =IFERROR(G125*H125*I125,"") -> 177.07737 | L125: 1 | BJ125: =IFERROR(BK125/J125,0) -> 0 | BK125: =SUM(BM125:DH125) -> 0 | BM125: =SUMIFS(Imput[[Importe Neto]:[Importe Neto]],Imput[[C. Imp.]:[C. Imp.]],$D125,Imput[[PERIODO Imp.]:[PERIODO Imp.]],BM$9) -> 0 | BN125: =SUMIFS(Imput[[Importe Neto]:[Importe Neto]],Imput[[C. Imp.]:[C. Imp.]],$D125,Imput[[PERIODO Imp.]:[PERIODO Imp.]],BN$9) -> 0 | BO125: =SUMIFS(Imput[[Importe Neto]:[Importe Neto]],Imput[[C. Imp.]:[C. Imp.]],$D125,Imput[[PERIODO Imp.]:[PERIODO Imp.]],BO$9) -> 0 | BP125: =SUMIFS(Imput[[Importe Neto]:[Importe Neto]],Imput[[C. Imp.]:[C. Imp.]],$D125,Imput[[PERIODO Imp.]:[PERIODO Imp.]],BP$9) -> 0 | BQ125: =SUMIFS(Imput[[Importe Neto]:[Importe Neto]],Imput[[C. Imp.]:[C. Imp.]],$D125,Imput[[PERIODO Imp.]:[PERIODO Imp.]],BQ$9) -> 0 | BR125: =SUMIFS(Imput[[Importe Neto]:[Importe Neto]],Imput[[C. Imp.]:[C. Imp.]],$D125,Imput[[PERIODO Imp.]:[PERIODO Imp.]],BR$9) -> 0 | BS125: =SUMIFS(Imput[[Importe Neto]:[Importe Neto]],Imput[[C. Imp.]:[C. Imp.]],$D125,Imput[[PERIODO Imp.]:[PERIODO Imp.]],BS$9) -> 0 | BT125: =SUMIFS(Imput[[Importe Neto]:[Importe Neto]],Imput[[C. Imp.]:[C. Imp.]],$D125,Imput[[PERIODO Imp.]:[PERIODO Imp.]],BT$9) -> 0 | ... DH125: =SUMIFS(Imput[[Importe Neto]:[Importe Neto]],Imput[[C. Imp.]:[C. Imp.]],$D125,Imput[[PERIODO Imp.]:[PERIODO Imp.]],DH$9) -> 0
A126: =IF(J126="","",IF(J126=0,"","Imprimir")) -> Imprimir | D126: MAN-P4-3 | E126: AGUA | G126: 50 | H126: =Producción!G12*0.812 -> 13.804 | I126: =IF(E126>0,$J$5,"") -> 1 | J126: =IFERROR(G126*H126*I126,"") -> 690.2 | L126: 0.1 | O126: 0.1 | S126: 0.1 | W126: 0.1 | Y126: 0.1 | AA126: 0.1 | AC126: 0.1 | AE126: 0.1 | AG126: 0.1 | AI126: 0.1 | BJ126: =IFERROR(BK126/J126,0) -> 0 | BK126: =SUM(BM126:DH126) -> 0 | BM126: =SUMIFS(Imput[[Importe Neto]:[Importe Neto]],Imput[[C. Imp.]:[C. Imp.]],$D126,Imput[[PERIODO Imp.]:[PERIODO Imp.]],BM$9) -> 0 | BN126: =SUMIFS(Imput[[Importe Neto]:[Importe Neto]],Imput[[C. Imp.]:[C. Imp.]],$D126,Imput[[PERIODO Imp.]:[PERIODO Imp.]],BN$9) -> 0 | BO126: =SUMIFS(Imput[[Importe Neto]:[Importe Neto]],Imput[[C. Imp.]:[C. Imp.]],$D126,Imput[[PERIODO Imp.]:[PERIODO Imp.]],BO$9) -> 0 | BP126: =SUMIFS(Imput[[Importe Neto]:[Importe Neto]],Imput[[C. Imp.]:[C. Imp.]],$D126,Imput[[PERIODO Imp.]:[PERIODO Imp.]],BP$9) -> 0 | BQ126: =SUMIFS(Imput[[Importe Neto]:[Importe Neto]],Imput[[C. Imp.]:[C. Imp.]],$D126,Imput[[PERIODO Imp.]:[PERIODO Imp.]],BQ$9) -> 0 | BR126: =SUMIFS(Imput[[Importe Neto]:[Importe Neto]],Imput[[C. Imp.]:[C. Imp.]],$D126,Imput[[PERIODO Imp.]:[PERIODO Imp.]],BR$9) -> 0 | BS126: =SUMIFS(Imput[[Importe Neto]:[Importe Neto]],Imput[[C. Imp.]:[C. Imp.]],$D126,Imput[[PERIODO Imp.]:[PERIODO Imp.]],BS$9) -> 0 | BT126: =SUMIFS(Imput[[Importe Neto]:[Importe Neto]],Imput[[C. Imp.]:[C. Imp.]],$D126,Imput[[PERIODO Imp.]:[PERIODO Imp.]],BT$9) -> 0 | ... DH126: =SUMIFS(Imput[[Importe Neto]:[Importe Neto]],Imput[[C. Imp.]:[C. Imp.]],$D126,Imput[[PERIODO Imp.]:[PERIODO Imp.]],DH$9) -> 0
A127: =IF(J127="","",IF(J127=0,"","Imprimir")) -> Imprimir | D127: MAN-P4-4 | E127: ALAMBRE RECOCIDO | G127: 24 | H127: =Producción!G12*4.0215 -> 68.3655 | I127: =IF(E127>0,$J$5,"") -> 1 | J127: =IFERROR(G127*H127*I127,"") -> 1640.772 | L127: 0.3 | P127: 0.5 | W127: 0.2 | BJ127: =IFERROR(BK127/J127,0) -> 1.2280479 | BK127: =SUM(BM127:DH127) -> 2014.9467 | BM127: =SUMIFS(Imput[[Importe Neto]:[Importe Neto]],Imput[[C. Imp.]:[C. Imp.]],$D127,Imput[[PERIODO Imp.]:[PERIODO Imp.]],BM$9) -> 0 | BN127: =SUMIFS(Imput[[Importe Neto]:[Importe Neto]],Imput[[C. Imp.]:[C. Imp.]],$D127,Imput[[PERIODO Imp.]:[PERIODO Imp.]],BN$9) -> 0 | BO127: =SUMIFS(Imput[[Importe Neto]:[Importe Neto]],Imput[[C. Imp.]:[C. Imp.]],$D127,Imput[[PERIODO Imp.]:[PERIODO Imp.]],BO$9) -> 1595.9976 | BP127: =SUMIFS(Imput[[Importe Neto]:[Importe Neto]],Imput[[C. Imp.]:[C. Imp.]],$D127,Imput[[PERIODO Imp.]:[PERIODO Imp.]],BP$9) -> 418.94908 | BQ127: =SUMIFS(Imput[[Importe Neto]:[Importe Neto]],Imput[[C. Imp.]:[C. Imp.]],$D127,Imput[[PERIODO Imp.]:[PERIODO Imp.]],BQ$9) -> 0 | BR127: =SUMIFS(Imput[[Importe Neto]:[Importe Neto]],Imput[[C. Imp.]:[C. Imp.]],$D127,Imput[[PERIODO Imp.]:[PERIODO Imp.]],BR$9) -> 0 | BS127: =SUMIFS(Imput[[Importe Neto]:[Importe Neto]],Imput[[C. Imp.]:[C. Imp.]],$D127,Imput[[PERIODO Imp.]:[PERIODO Imp.]],BS$9) -> 0 | BT127: =SUMIFS(Imput[[Importe Neto]:[Importe Neto]],Imput[[C. Imp.]:[C. Imp.]],$D127,Imput[[PERIODO Imp.]:[PERIODO Imp.]],BT$9) -> 0 | ... DH127: =SUMIFS(Imput[[Importe Neto]:[Importe Neto]],Imput[[C. Imp.]:[C. Imp.]],$D127,Imput[[PERIODO Imp.]:[PERIODO Imp.]],DH$9) -> 0
A128: =IF(J128="","",IF(J128=0,"","Imprimir")) -> Imprimir | D128: MAN-P4-5 | E128: ARENA | G128: 600 | H128: =Producción!G12*0.01936 -> 0.32912 | I128: =IF(E128>0,$J$5,"") -> 1 | J128: =IFERROR(G128*H128*I128,"") -> 197.472 | L128: 1 | BJ128: =IFERROR(BK128/J128,0) -> 0 | BK128: =SUM(BM128:DH128) -> 0 | BM128: =SUMIFS(Imput[[Importe Neto]:[Importe Neto]],Imput[[C. Imp.]:[C. Imp.]],$D128,Imput[[PERIODO Imp.]:[PERIODO Imp.]],BM$9) -> 0 | BN128: =SUMIFS(Imput[[Importe Neto]:[Importe Neto]],Imput[[C. Imp.]:[C. Imp.]],$D128,Imput[[PERIODO Imp.]:[PERIODO Imp.]],BN$9) -> 0 | BO128: =SUMIFS(Imput[[Importe Neto]:[Importe Neto]],Imput[[C. Imp.]:[C. Imp.]],$D128,Imput[[PERIODO Imp.]:[PERIODO Imp.]],BO$9) -> 0 | BP128: =SUMIFS(Imput[[Importe Neto]:[Importe Neto]],Imput[[C. Imp.]:[C. Imp.]],$D128,Imput[[PERIODO Imp.]:[PERIODO Imp.]],BP$9) -> 0 | BQ128: =SUMIFS(Imput[[Importe Neto]:[Importe Neto]],Imput[[C. Imp.]:[C. Imp.]],$D128,Imput[[PERIODO Imp.]:[PERIODO Imp.]],BQ$9) -> 0 | BR128: =SUMIFS(Imput[[Importe Neto]:[Importe Neto]],Imput[[C. Imp.]:[C. Imp.]],$D128,Imput[[PERIODO Imp.]:[PERIODO Imp.]],BR$9) -> 0 | BS128: =SUMIFS(Imput[[Importe Neto]:[Importe Neto]],Imput[[C. Imp.]:[C. Imp.]],$D128,Imput[[PERIODO Imp.]:[PERIODO Imp.]],BS$9) -> 0 | BT128: =SUMIFS(Imput[[Importe Neto]:[Importe Neto]],Imput[[C. Imp.]:[C. Imp.]],$D128,Imput[[PERIODO Imp.]:[PERIODO Imp.]],BT$9) -> 0 | ... DH128: =SUMIFS(Imput[[Importe Neto]:[Importe Neto]],Imput[[C. Imp.]:[C. Imp.]],$D128,Imput[[PERIODO Imp.]:[PERIODO Imp.]],DH$9) -> 0
A129: =IF(J129="","",IF(J129=0,"","Imprimir")) -> Imprimir | D129: MAN-P4-6 | E129: CEMENTO | G129: 4.74 | H129: =Producción!G12*8.228 -> 139.876 | I129: =IF(E129>0,$J$5,"") -> 1 | J129: =IFERROR(G129*H129*I129,"") -> 663.01224 | L129: 1 | BJ129: =IFERROR(BK129/J129,0) -> 0 | BK129: =SUM(BM129:DH129) -> 0 | BM129: =SUMIFS(Imput[[Importe Neto]:[Importe Neto]],Imput[[C. Imp.]:[C. Imp.]],$D129,Imput[[PERIODO Imp.]:[PERIODO Imp.]],BM$9) -> 0 | BN129: =SUMIFS(Imput[[Importe Neto]:[Importe Neto]],Imput[[C. Imp.]:[C. Imp.]],$D129,Imput[[PERIODO Imp.]:[PERIODO Imp.]],BN$9) -> 0 | BO129: =SUMIFS(Imput[[Importe Neto]:[Importe Neto]],Imput[[C. Imp.]:[C. Imp.]],$D129,Imput[[PERIODO Imp.]:[PERIODO Imp.]],BO$9) -> 0 | BP129: =SUMIFS(Imput[[Importe Neto]:[Importe Neto]],Imput[[C. Imp.]:[C. Imp.]],$D129,Imput[[PERIODO Imp.]:[PERIODO Imp.]],BP$9) -> 0 | BQ129: =SUMIFS(Imput[[Importe Neto]:[Importe Neto]],Imput[[C. Imp.]:[C. Imp.]],$D129,Imput[[PERIODO Imp.]:[PERIODO Imp.]],BQ$9) -> 0 | BR129: =SUMIFS(Imput[[Importe Neto]:[Importe Neto]],Imput[[C. Imp.]:[C. Imp.]],$D129,Imput[[PERIODO Imp.]:[PERIODO Imp.]],BR$9) -> 0 | BS129: =SUMIFS(Imput[[Importe Neto]:[Importe Neto]],Imput[[C. Imp.]:[C. Imp.]],$D129,Imput[[PERIODO Imp.]:[PERIODO Imp.]],BS$9) -> 0 | BT129: =SUMIFS(Imput[[Importe Neto]:[Importe Neto]],Imput[[C. Imp.]:[C. Imp.]],$D129,Imput[[PERIODO Imp.]:[PERIODO Imp.]],BT$9) -> 0 | ... DH129: =SUMIFS(Imput[[Importe Neto]:[Importe Neto]],Imput[[C. Imp.]:[C. Imp.]],$D129,Imput[[PERIODO Imp.]:[PERIODO Imp.]],DH$9) -> 0
A130: =IF(J130="","",IF(J130=0,"","Imprimir")) -> Imprimir | D130: MAN-P4-7 | E130: CONCRETO F'C=250 KG/CM2 | G130: 2803 | H130: =Producción!G12*1.155 -> 19.635 | I130: =IF(E130>0,$J$5,"") -> 1 | J130: =IFERROR(G130*H130*I130,"") -> 55036.905 | L130: 0.5 | M130: 0.035714286 | N130: 0.035714286 | O130: 0.035714286 | P130: 0.035714286 | Q130: 0.035714286 | R130: 0.035714286 | S130: 0.035714286 | T130: 0.035714286 | U130: 0.035714286 | V130: 0.035714286 | W130: 0.035714286 | X130: 0.035714286 | Y130: 0.035714286 | Z130: 0.035714286 | BJ130: =IFERROR(BK130/J130,0) -> 1.0338444 | BK130: =SUM(BM130:DH130) -> 56899.596 | BM130: =SUMIFS(Imput[[Importe Neto]:[Importe Neto]],Imput[[C. Imp.]:[C. Imp.]],$D130,Imput[[PERIODO Imp.]:[PERIODO Imp.]],BM$9) -> 0 | BN130: =SUMIFS(Imput[[Importe Neto]:[Importe Neto]],Imput[[C. Imp.]:[C. Imp.]],$D130,Imput[[PERIODO Imp.]:[PERIODO Imp.]],BN$9) -> 0 | BO130: =SUMIFS(Imput[[Importe Neto]:[Importe Neto]],Imput[[C. Imp.]:[C. Imp.]],$D130,Imput[[PERIODO Imp.]:[PERIODO Imp.]],BO$9) -> 0 | BP130: =SUMIFS(Imput[[Importe Neto]:[Importe Neto]],Imput[[C. Imp.]:[C. Imp.]],$D130,Imput[[PERIODO Imp.]:[PERIODO Imp.]],BP$9) -> 56495.951 | BQ130: =SUMIFS(Imput[[Importe Neto]:[Importe Neto]],Imput[[C. Imp.]:[C. Imp.]],$D130,Imput[[PERIODO Imp.]:[PERIODO Imp.]],BQ$9) -> 0 | BR130: =SUMIFS(Imput[[Importe Neto]:[Importe Neto]],Imput[[C. Imp.]:[C. Imp.]],$D130,Imput[[PERIODO Imp.]:[PERIODO Imp.]],BR$9) -> 403.6452 | BS130: =SUMIFS(Imput[[Importe Neto]:[Importe Neto]],Imput[[C. Imp.]:[C. Imp.]],$D130,Imput[[PERIODO Imp.]:[PERIODO Imp.]],BS$9) -> 0 | BT130: =SUMIFS(Imput[[Importe Neto]:[Importe Neto]],Imput[[C. Imp.]:[C. Imp.]],$D130,Imput[[PERIODO Imp.]:[PERIODO Imp.]],BT$9) -> 0 | ... DH130: =SUMIFS(Imput[[Importe Neto]:[Importe Neto]],Imput[[C. Imp.]:[C. Imp.]],$D130,Imput[[PERIODO Imp.]:[PERIODO Imp.]],DH$9) -> 0
A131: =IF(J131="","",IF(J131=0,"","Imprimir")) -> Imprimir | D131: MAN-P4-8 | E131: GRAVA | G131: 600 | H131: =Producción!G12*0.0242 -> 0.4114 | I131: =IF(E131>0,$J$5,"") -> 1 | J131: =IFERROR(G131*H131*I131,"") -> 246.84 | L131: 1 | BJ131: =IFERROR(BK131/J131,0) -> 0 | BK131: =SUM(BM131:DH131) -> 0 | BM131: =SUMIFS(Imput[[Importe Neto]:[Importe Neto]],Imput[[C. Imp.]:[C. Imp.]],$D131,Imput[[PERIODO Imp.]:[PERIODO Imp.]],BM$9) -> 0 | BN131: =SUMIFS(Imput[[Importe Neto]:[Importe Neto]],Imput[[C. Imp.]:[C. Imp.]],$D131,Imput[[PERIODO Imp.]:[PERIODO Imp.]],BN$9) -> 0 | BO131: =SUMIFS(Imput[[Importe Neto]:[Importe Neto]],Imput[[C. Imp.]:[C. Imp.]],$D131,Imput[[PERIODO Imp.]:[PERIODO Imp.]],BO$9) -> 0 | BP131: =SUMIFS(Imput[[Importe Neto]:[Importe Neto]],Imput[[C. Imp.]:[C. Imp.]],$D131,Imput[[PERIODO Imp.]:[PERIODO Imp.]],BP$9) -> 0 | BQ131: =SUMIFS(Imput[[Importe Neto]:[Importe Neto]],Imput[[C. Imp.]:[C. Imp.]],$D131,Imput[[PERIODO Imp.]:[PERIODO Imp.]],BQ$9) -> 0 | BR131: =SUMIFS(Imput[[Importe Neto]:[Importe Neto]],Imput[[C. Imp.]:[C. Imp.]],$D131,Imput[[PERIODO Imp.]:[PERIODO Imp.]],BR$9) -> 0 | BS131: =SUMIFS(Imput[[Importe Neto]:[Importe Neto]],Imput[[C. Imp.]:[C. Imp.]],$D131,Imput[[PERIODO Imp.]:[PERIODO Imp.]],BS$9) -> 0 | BT131: =SUMIFS(Imput[[Importe Neto]:[Importe Neto]],Imput[[C. Imp.]:[C. Imp.]],$D131,Imput[[PERIODO Imp.]:[PERIODO Imp.]],BT$9) -> 0 | ... DH131: =SUMIFS(Imput[[Importe Neto]:[Importe Neto]],Imput[[C. Imp.]:[C. Imp.]],$D131,Imput[[PERIODO Imp.]:[PERIODO Imp.]],DH$9) -> 0
A132: =IF(J132="","",IF(J132=0,"","Imprimir")) -> Imprimir | D132: MAN-P4-9 | E132: MADERA PARA CIMBRA DE FRONTERA DE PILA | G132: 450 | H132: =Producción!G12*0.024 -> 0.408 | I132: =IF(E132>0,$J$5,"") -> 1 | J132: =IFERROR(G132*H132*I132,"") -> 183.6 | L132: 1 | BJ132: =IFERROR(BK132/J132,0) -> 0 | BK132: =SUM(BM132:DH132) -> 0 | BM132: =SUMIFS(Imput[[Importe Neto]:[Importe Neto]],Imput[[C. Imp.]:[C. Imp.]],$D132,Imput[[PERIODO Imp.]:[PERIODO Imp.]],BM$9) -> 0 | BN132: =SUMIFS(Imput[[Importe Neto]:[Importe Neto]],Imput[[C. Imp.]:[C. Imp.]],$D132,Imput[[PERIODO Imp.]:[PERIODO Imp.]],BN$9) -> 0 | BO132: =SUMIFS(Imput[[Importe Neto]:[Importe Neto]],Imput[[C. Imp.]:[C. Imp.]],$D132,Imput[[PERIODO Imp.]:[PERIODO Imp.]],BO$9) -> 0 | BP132: =SUMIFS(Imput[[Importe Neto]:[Importe Neto]],Imput[[C. Imp.]:[C. Imp.]],$D132,Imput[[PERIODO Imp.]:[PERIODO Imp.]],BP$9) -> 0 | BQ132: =SUMIFS(Imput[[Importe Neto]:[Importe Neto]],Imput[[C. Imp.]:[C. Imp.]],$D132,Imput[[PERIODO Imp.]:[PERIODO Imp.]],BQ$9) -> 0 | BR132: =SUMIFS(Imput[[Importe Neto]:[Importe Neto]],Imput[[C. Imp.]:[C. Imp.]],$D132,Imput[[PERIODO Imp.]:[PERIODO Imp.]],BR$9) -> 0 | BS132: =SUMIFS(Imput[[Importe Neto]:[Importe Neto]],Imput[[C. Imp.]:[C. Imp.]],$D132,Imput[[PERIODO Imp.]:[PERIODO Imp.]],BS$9) -> 0 | BT132: =SUMIFS(Imput[[Importe Neto]:[Importe Neto]],Imput[[C. Imp.]:[C. Imp.]],$D132,Imput[[PERIODO Imp.]:[PERIODO Imp.]],BT$9) -> 0 | ... DH132: =SUMIFS(Imput[[Importe Neto]:[Importe Neto]],Imput[[C. Imp.]:[C. Imp.]],$D132,Imput[[PERIODO Imp.]:[PERIODO Imp.]],DH$9) -> 0
A133: =IF(J133="","",IF(J133=0,"","Imprimir")) -> Imprimir | D133: MAN-P4-10 | E133: MALLA NARANJA DE PERFORACIÓN | G133: 9.8333333 | H133: =Producción!G12*12 -> 204 | I133: =IF(E133>0,$J$5,"") -> 1 | J133: =IFERROR(G133*H133*I133,"") -> 2006 | L133: 0.3 | P133: 0.3 | W133: 0.3 | AE133: 0.1 | BJ133: =IFERROR(BK133/J133,0) -> 1.3231344 | BK133: =SUM(BM133:DH133) -> 2654.2076 | BM133: =SUMIFS(Imput[[Importe Neto]:[Importe Neto]],Imput[[C. Imp.]:[C. Imp.]],$D133,Imput[[PERIODO Imp.]:[PERIODO Imp.]],BM$9) -> 0 | BN133: =SUMIFS(Imput[[Importe Neto]:[Importe Neto]],Imput[[C. Imp.]:[C. Imp.]],$D133,Imput[[PERIODO Imp.]:[PERIODO Imp.]],BN$9) -> 0 | BO133: =SUMIFS(Imput[[Importe Neto]:[Importe Neto]],Imput[[C. Imp.]:[C. Imp.]],$D133,Imput[[PERIODO Imp.]:[PERIODO Imp.]],BO$9) -> 0 | BP133: =SUMIFS(Imput[[Importe Neto]:[Importe Neto]],Imput[[C. Imp.]:[C. Imp.]],$D133,Imput[[PERIODO Imp.]:[PERIODO Imp.]],BP$9) -> 1416.0004 | BQ133: =SUMIFS(Imput[[Importe Neto]:[Importe Neto]],Imput[[C. Imp.]:[C. Imp.]],$D133,Imput[[PERIODO Imp.]:[PERIODO Imp.]],BQ$9) -> 406.3016 | BR133: =SUMIFS(Imput[[Importe Neto]:[Importe Neto]],Imput[[C. Imp.]:[C. Imp.]],$D133,Imput[[PERIODO Imp.]:[PERIODO Imp.]],BR$9) -> 831.9056 | BS133: =SUMIFS(Imput[[Importe Neto]:[Importe Neto]],Imput[[C. Imp.]:[C. Imp.]],$D133,Imput[[PERIODO Imp.]:[PERIODO Imp.]],BS$9) -> 0 | BT133: =SUMIFS(Imput[[Importe Neto]:[Importe Neto]],Imput[[C. Imp.]:[C. Imp.]],$D133,Imput[[PERIODO Imp.]:[PERIODO Imp.]],BT$9) -> 0 | ... DH133: =SUMIFS(Imput[[Importe Neto]:[Importe Neto]],Imput[[C. Imp.]:[C. Imp.]],$D133,Imput[[PERIODO Imp.]:[PERIODO Imp.]],DH$9) -> 0
A134: =IF(J134="","",IF(J134=0,"","Imprimir")) -> Imprimir | D134: MAN-P4-11 | E134: MORTERO CEMENTICIO AUTONIVELANTE IMPAC GROUT PRO O SIMILAR | G134: 19 | H134: =Producción!G12*50 -> 850 | I134: =IF(E134>0,$J$5,"") -> 1 | J134: =IFERROR(G134*H134*I134,"") -> 16150 | L134: 0.3 | P134: 0.3 | W134: 0.3 | AE134: 0.1 | BJ134: =IFERROR(BK134/J134,0) -> 0.41470611 | BK134: =SUM(BM134:DH134) -> 6697.5036 | BM134: =SUMIFS(Imput[[Importe Neto]:[Importe Neto]],Imput[[C. Imp.]:[C. Imp.]],$D134,Imput[[PERIODO Imp.]:[PERIODO Imp.]],BM$9) -> 0 | BN134: =SUMIFS(Imput[[Importe Neto]:[Importe Neto]],Imput[[C. Imp.]:[C. Imp.]],$D134,Imput[[PERIODO Imp.]:[PERIODO Imp.]],BN$9) -> 0 | BO134: =SUMIFS(Imput[[Importe Neto]:[Importe Neto]],Imput[[C. Imp.]:[C. Imp.]],$D134,Imput[[PERIODO Imp.]:[PERIODO Imp.]],BO$9) -> 0 | BP134: =SUMIFS(Imput[[Importe Neto]:[Importe Neto]],Imput[[C. Imp.]:[C. Imp.]],$D134,Imput[[PERIODO Imp.]:[PERIODO Imp.]],BP$9) -> 0 | BQ134: =SUMIFS(Imput[[Importe Neto]:[Importe Neto]],Imput[[C. Imp.]:[C. Imp.]],$D134,Imput[[PERIODO Imp.]:[PERIODO Imp.]],BQ$9) -> 0 | BR134: =SUMIFS(Imput[[Importe Neto]:[Importe Neto]],Imput[[C. Imp.]:[C. Imp.]],$D134,Imput[[PERIODO Imp.]:[PERIODO Imp.]],BR$9) -> 6697.5036 | BS134: =SUMIFS(Imput[[Importe Neto]:[Importe Neto]],Imput[[C. Imp.]:[C. Imp.]],$D134,Imput[[PERIODO Imp.]:[PERIODO Imp.]],BS$9) -> 0 | BT134: =SUMIFS(Imput[[Importe Neto]:[Importe Neto]],Imput[[C. Imp.]:[C. Imp.]],$D134,Imput[[PERIODO Imp.]:[PERIODO Imp.]],BT$9) -> 0 | ... DH134: =SUMIFS(Imput[[Importe Neto]:[Importe Neto]],Imput[[C. Imp.]:[C. Imp.]],$D134,Imput[[PERIODO Imp.]:[PERIODO Imp.]],DH$9) -> 0
A135: =IF(J135="","",IF(J135=0,"","Imprimir")) -> Imprimir | D135: MAN-P4-12 | E135: POSTE ANARANJADO DE 1.2M PARA CONTROL VIAL | G135: 735 | H135: =Producción!G12*0.24 -> 4.08 | I135: =IF(E135>0,$J$5,"") -> 1 | J135: =IFERROR(G135*H135*I135,"") -> 2998.8 | O135: 0.5 | AA135: 0.5 | BJ135: =IFERROR(BK135/J135,0) -> 0 | BK135: =SUM(BM135:DH135) -> 0 | BM135: =SUMIFS(Imput[[Importe Neto]:[Importe Neto]],Imput[[C. Imp.]:[C. Imp.]],$D135,Imput[[PERIODO Imp.]:[PERIODO Imp.]],BM$9) -> 0 | BN135: =SUMIFS(Imput[[Importe Neto]:[Importe Neto]],Imput[[C. Imp.]:[C. Imp.]],$D135,Imput[[PERIODO Imp.]:[PERIODO Imp.]],BN$9) -> 0 | BO135: =SUMIFS(Imput[[Importe Neto]:[Importe Neto]],Imput[[C. Imp.]:[C. Imp.]],$D135,Imput[[PERIODO Imp.]:[PERIODO Imp.]],BO$9) -> 0 | BP135: =SUMIFS(Imput[[Importe Neto]:[Importe Neto]],Imput[[C. Imp.]:[C. Imp.]],$D135,Imput[[PERIODO Imp.]:[PERIODO Imp.]],BP$9) -> 0 | BQ135: =SUMIFS(Imput[[Importe Neto]:[Importe Neto]],Imput[[C. Imp.]:[C. Imp.]],$D135,Imput[[PERIODO Imp.]:[PERIODO Imp.]],BQ$9) -> 0 | BR135: =SUMIFS(Imput[[Importe Neto]:[Importe Neto]],Imput[[C. Imp.]:[C. Imp.]],$D135,Imput[[PERIODO Imp.]:[PERIODO Imp.]],BR$9) -> 0 | BS135: =SUMIFS(Imput[[Importe Neto]:[Importe Neto]],Imput[[C. Imp.]:[C. Imp.]],$D135,Imput[[PERIODO Imp.]:[PERIODO Imp.]],BS$9) -> 0 | BT135: =SUMIFS(Imput[[Importe Neto]:[Importe Neto]],Imput[[C. Imp.]:[C. Imp.]],$D135,Imput[[PERIODO Imp.]:[PERIODO Imp.]],BT$9) -> 0 | ... DH135: =SUMIFS(Imput[[Importe Neto]:[Importe Neto]],Imput[[C. Imp.]:[C. Imp.]],$D135,Imput[[PERIODO Imp.]:[PERIODO Imp.]],DH$9) -> 0
A136: =IF(J136="","",IF(J136=0,"","Imprimir")) -> Imprimir | D136: MAN-P4-13 | E136: SILLETAS INFERIORES (SU 75 Ó SIMILAR) | G136: 8 | H136: =Producción!G12*4 -> 68 | I136: =IF(E136>0,$J$5,"") -> 1 | J136: =IFERROR(G136*H136*I136,"") -> 544 | L136: 0.3 | P136: 0.3 | W136: 0.3 | AE136: 0.1 | BJ136: =IFERROR(BK136/J136,0) -> 0 | BK136: =SUM(BM136:DH136) -> 0 | BM136: =SUMIFS(Imput[[Importe Neto]:[Importe Neto]],Imput[[C. Imp.]:[C. Imp.]],$D136,Imput[[PERIODO Imp.]:[PERIODO Imp.]],BM$9) -> 0 | BN136: =SUMIFS(Imput[[Importe Neto]:[Importe Neto]],Imput[[C. Imp.]:[C. Imp.]],$D136,Imput[[PERIODO Imp.]:[PERIODO Imp.]],BN$9) -> 0 | BO136: =SUMIFS(Imput[[Importe Neto]:[Importe Neto]],Imput[[C. Imp.]:[C. Imp.]],$D136,Imput[[PERIODO Imp.]:[PERIODO Imp.]],BO$9) -> 0 | BP136: =SUMIFS(Imput[[Importe Neto]:[Importe Neto]],Imput[[C. Imp.]:[C. Imp.]],$D136,Imput[[PERIODO Imp.]:[PERIODO Imp.]],BP$9) -> 0 | BQ136: =SUMIFS(Imput[[Importe Neto]:[Importe Neto]],Imput[[C. Imp.]:[C. Imp.]],$D136,Imput[[PERIODO Imp.]:[PERIODO Imp.]],BQ$9) -> 0 | BR136: =SUMIFS(Imput[[Importe Neto]:[Importe Neto]],Imput[[C. Imp.]:[C. Imp.]],$D136,Imput[[PERIODO Imp.]:[PERIODO Imp.]],BR$9) -> 0 | BS136: =SUMIFS(Imput[[Importe Neto]:[Importe Neto]],Imput[[C. Imp.]:[C. Imp.]],$D136,Imput[[PERIODO Imp.]:[PERIODO Imp.]],BS$9) -> 0 | BT136: =SUMIFS(Imput[[Importe Neto]:[Importe Neto]],Imput[[C. Imp.]:[C. Imp.]],$D136,Imput[[PERIODO Imp.]:[PERIODO Imp.]],BT$9) -> 0 | ... DH136: =SUMIFS(Imput[[Importe Neto]:[Importe Neto]],Imput[[C. Imp.]:[C. Imp.]],$D136,Imput[[PERIODO Imp.]:[PERIODO Imp.]],DH$9) -> 0
A137: =IF(J137="","",IF(J137=0,"","Imprimir")) -> Imprimir | D137: MAN-P4-14 | E137: SILLETAS LATERALES (PIL 50 Ó SIMILAR) | G137: 6 | H137: =Producción!G12*12 -> 204 | I137: =IF(E137>0,$J$5,"") -> 1 | J137: =IFERROR(G137*H137*I137,"") -> 1224 | L137: 1 | BJ137: =IFERROR(BK137/J137,0) -> 0 | BK137: =SUM(BM137:DH137) -> 0 | BM137: =SUMIFS(Imput[[Importe Neto]:[Importe Neto]],Imput[[C. Imp.]:[C. Imp.]],$D137,Imput[[PERIODO Imp.]:[PERIODO Imp.]],BM$9) -> 0 | BN137: =SUMIFS(Imput[[Importe Neto]:[Importe Neto]],Imput[[C. Imp.]:[C. Imp.]],$D137,Imput[[PERIODO Imp.]:[PERIODO Imp.]],BN$9) -> 0 | BO137: =SUMIFS(Imput[[Importe Neto]:[Importe Neto]],Imput[[C. Imp.]:[C. Imp.]],$D137,Imput[[PERIODO Imp.]:[PERIODO Imp.]],BO$9) -> 0 | BP137: =SUMIFS(Imput[[Importe Neto]:[Importe Neto]],Imput[[C. Imp.]:[C. Imp.]],$D137,Imput[[PERIODO Imp.]:[PERIODO Imp.]],BP$9) -> 0 | BQ137: =SUMIFS(Imput[[Importe Neto]:[Importe Neto]],Imput[[C. Imp.]:[C. Imp.]],$D137,Imput[[PERIODO Imp.]:[PERIODO Imp.]],BQ$9) -> 0 | BR137: =SUMIFS(Imput[[Importe Neto]:[Importe Neto]],Imput[[C. Imp.]:[C. Imp.]],$D137,Imput[[PERIODO Imp.]:[PERIODO Imp.]],BR$9) -> 0 | BS137: =SUMIFS(Imput[[Importe Neto]:[Importe Neto]],Imput[[C. Imp.]:[C. Imp.]],$D137,Imput[[PERIODO Imp.]:[PERIODO Imp.]],BS$9) -> 0 | BT137: =SUMIFS(Imput[[Importe Neto]:[Importe Neto]],Imput[[C. Imp.]:[C. Imp.]],$D137,Imput[[PERIODO Imp.]:[PERIODO Imp.]],BT$9) -> 0 | ... DH137: =SUMIFS(Imput[[Importe Neto]:[Importe Neto]],Imput[[C. Imp.]:[C. Imp.]],$D137,Imput[[PERIODO Imp.]:[PERIODO Imp.]],DH$9) -> 0
A138: =IF(J138="","",IF(J138=0,"","Imprimir")) -> Imprimir | D138: MAN-P4-15 | E138: TUBO DE PVC VERDE DE 1" | G138: 30 | H138: =Producción!G12*2.9 -> 49.3 | I138: =IF(E138>0,$J$5,"") -> 1 | J138: =IFERROR(G138*H138*I138,"") -> 1479 | L138: 1 | BJ138: =IFERROR(BK138/J138,0) -> 1.0048075 | BK138: =SUM(BM138:DH138) -> 1486.1102 | BM138: =SUMIFS(Imput[[Importe Neto]:[Importe Neto]],Imput[[C. Imp.]:[C. Imp.]],$D138,Imput[[PERIODO Imp.]:[PERIODO Imp.]],BM$9) -> 0 | BN138: =SUMIFS(Imput[[Importe Neto]:[Importe Neto]],Imput[[C. Imp.]:[C. Imp.]],$D138,Imput[[PERIODO Imp.]:[PERIODO Imp.]],BN$9) -> 0 | BO138: =SUMIFS(Imput[[Importe Neto]:[Importe Neto]],Imput[[C. Imp.]:[C. Imp.]],$D138,Imput[[PERIODO Imp.]:[PERIODO Imp.]],BO$9) -> 0 | BP138: =SUMIFS(Imput[[Importe Neto]:[Importe Neto]],Imput[[C. Imp.]:[C. Imp.]],$D138,Imput[[PERIODO Imp.]:[PERIODO Imp.]],BP$9) -> 0 | BQ138: =SUMIFS(Imput[[Importe Neto]:[Importe Neto]],Imput[[C. Imp.]:[C. Imp.]],$D138,Imput[[PERIODO Imp.]:[PERIODO Imp.]],BQ$9) -> 743.90742 | BR138: =SUMIFS(Imput[[Importe Neto]:[Importe Neto]],Imput[[C. Imp.]:[C. Imp.]],$D138,Imput[[PERIODO Imp.]:[PERIODO Imp.]],BR$9) -> 742.2028 | BS138: =SUMIFS(Imput[[Importe Neto]:[Importe Neto]],Imput[[C. Imp.]:[C. Imp.]],$D138,Imput[[PERIODO Imp.]:[PERIODO Imp.]],BS$9) -> 0 | BT138: =SUMIFS(Imput[[Importe Neto]:[Importe Neto]],Imput[[C. Imp.]:[C. Imp.]],$D138,Imput[[PERIODO Imp.]:[PERIODO Imp.]],BT$9) -> 0 | ... DH138: =SUMIFS(Imput[[Importe Neto]:[Importe Neto]],Imput[[C. Imp.]:[C. Imp.]],$D138,Imput[[PERIODO Imp.]:[PERIODO Imp.]],DH$9) -> 0
